Workbook

Sheet LEEME
A1: TCNB_calibracion_series.xlsx
A2: Series mensuales de la calibracion de PD de TC No Bancarizado.
A4: QUE HAY EN CADA HOJA
A5: IBK_general / IBK_N1 / N2 / N3 Interbank, poblacion clean, total y por nodo de politica.
A6: SSFF_con_BCP el sistema SIN Interbank: BCP, Scotiabank, BBVA y Falabella.
A7: SSFF_sin_BCP lo mismo, sacando ademas a BCP.
A8: SISTEMA_5 las cinco entidades del alcance, Interbank incluido.
A9: ENT_xxxxx cada entidad por separado.
A11: POBLACION
A12: flg_clean = 1 y pd_raw no nula, en cada entidad. Ventana 202303 a 202605.
A13: Sobre IBK la fuente es full_calibrated.parquet, la salida del propio pipeline.
A15: LA COLUMNA "PD cal NUEVA"
... A64: Generado por Programas/reportes/10_excel_series.py

Sheet RESUMEN
A1: RESUMEN
A2: Ponderado por n sobre los meses con mora 12m cerrada. Todo formula viva.
A4: poblacion | B4: n total | C4: PD sin calibrar | D4: PD cal vigente | E4: PD cal NUEVA | F4: mora 12m | G4: EC vigente | H4: EC NUEVA | I4: semaforo NUEVA | J4: n visible IBK | K4: % visible | L4: PD NUEVA visible | M4: mora 12m visible | N4: EC NUEVA visible | O4: semaforo visible
A5: IBK_general | B5: =SUMPRODUCT(ISNUMBER('IBK_general'!$O$5:$O$43)*'IBK_general'!$B$5:$B$43) | C5: =IFERROR(SUMPRODUCT(ISNUMBER('IBK_general'!$O$5:$O$43)*'IBK_general'!$B$5:$B$43*'IBK_general'!$C$5:$C$43)/SUMPRODUCT(ISNUMBER('IBK_general'!$O$5:$O$43)*'IBK_general'!$B$5:$B$43),"") | D5: =IFERROR(SUMPRODUCT(ISNUMBER('IBK_general'!$O$5:$O$43)*'IBK_general'!$B$5:$B$43*'IBK_general'!$D$5:$D$43)/SUMPRODUCT(ISNUMBER('IBK_general'!$O$5:$O$43)*'IBK_general'!$B$5:$B$43),"") | E5: =IFERROR(SUMPRODUCT(ISNUMBER('IBK_general'!$O$5:$O$43)*'IBK_general'!$B$5:$B$43*'IBK_general'!$E$5:$E$43)/SUMPRODUCT(ISNUMBER('IBK_general'!$O$5:$O$43)*'IBK_general'!$B$5:$B$43),"") | F5: =IFERROR(SUMPRODUCT(ISNUMBER('IBK_general'!$O$5:$O$43)*'IBK_general'!$B$5:$B$43*'IBK_general'!$O$5:$O$43)/SUMPRODUCT(ISNUMBER('IBK_general'!$O$5:$O$43)*'IBK_general'!$B$5:$B$43),"") | G5: =IFERROR(D5/F5-1,"") | H5: =IFERROR(E5/F5-1,"") | I5: =IF(H5="","",IF(OR(H5<-0.25,H5>0.3),"ROJO",IF(OR(H5<-0.1,H5>0.15),"AMBAR","VERDE"))) | J5: =SUMPRODUCT(ISNUMBER('IBK_general'!$AA$5:$AA$43)*'IBK_general'!$Y$5:$Y$43) | K5: =IFERROR(J5/B5,"") | L5: =IFERROR(SUMPRODUCT(ISNUMBER('IBK_general'!$AA$5:$AA$43)*'IBK_general'!$Y$5:$Y$43*'IBK_general'!$Z$5:$Z$43)/SUMPRODUCT(ISNUMBER('IBK_general'!$AA$5:$AA$43)*'IBK_general'!$Y$5:$Y$43),"") | M5: =IFERROR(SUMPRODUCT(ISNUMBER('IBK_general'!$AA$5:$AA$43)*'IBK_general'!$Y$5:$Y$43*'IBK_general'!$AA$5:$AA$43)/SUMPRODUCT(ISNUMBER('IBK_general'!$AA$5:$AA$43)*'IBK_general'!$Y$5:$Y$43),"") | N5: =IFERROR(L5/M5-1,"") | O5: =IF(N5="","",IF(OR(N5<-0.25,N5>0.3),"ROJO",IF(OR(N5<-0.1,N5>0.15),"AMBAR","VERDE")))
A6: IBK_N1 | B6: =SUMPRODUCT(ISNUMBER('IBK_N1'!$O$5:$O$43)*'IBK_N1'!$B$5:$B$43) | C6: =IFERROR(SUMPRODUCT(ISNUMBER('IBK_N1'!$O$5:$O$43)*'IBK_N1'!$B$5:$B$43*'IBK_N1'!$C$5:$C$43)/SUMPRODUCT(ISNUMBER('IBK_N1'!$O$5:$O$43)*'IBK_N1'!$B$5:$B$43),"") | D6: =IFERROR(SUMPRODUCT(ISNUMBER('IBK_N1'!$O$5:$O$43)*'IBK_N1'!$B$5:$B$43*'IBK_N1'!$D$5:$D$43)/SUMPRODUCT(ISNUMBER('IBK_N1'!$O$5:$O$43)*'IBK_N1'!$B$5:$B$43),"") | E6: =IFERROR(SUMPRODUCT(ISNUMBER('IBK_N1'!$O$5:$O$43)*'IBK_N1'!$B$5:$B$43*'IBK_N1'!$E$5:$E$43)/SUMPRODUCT(ISNUMBER('IBK_N1'!$O$5:$O$43)*'IBK_N1'!$B$5:$B$43),"") | F6: =IFERROR(SUMPRODUCT(ISNUMBER('IBK_N1'!$O$5:$O$43)*'IBK_N1'!$B$5:$B$43*'IBK_N1'!$O$5:$O$43)/SUMPRODUCT(ISNUMBER('IBK_N1'!$O$5:$O$43)*'IBK_N1'!$B$5:$B$43),"") | G6: =IFERROR(D6/F6-1,"") | H6: =IFERROR(E6/F6-1,"") | I6: =IF(H6="","",IF(OR(H6<-0.25,H6>0.3),"ROJO",IF(OR(H6<-0.1,H6>0.15),"AMBAR","VERDE"))) | J6: =SUMPRODUCT(ISNUMBER('IBK_N1'!$AA$5:$AA$43)*'IBK_N1'!$Y$5:$Y$43) | K6: =IFERROR(J6/B6,"") | L6: =IFERROR(SUMPRODUCT(ISNUMBER('IBK_N1'!$AA$5:$AA$43)*'IBK_N1'!$Y$5:$Y$43*'IBK_N1'!$Z$5:$Z$43)/SUMPRODUCT(ISNUMBER('IBK_N1'!$AA$5:$AA$43)*'IBK_N1'!$Y$5:$Y$43),"") | M6: =IFERROR(SUMPRODUCT(ISNUMBER('IBK_N1'!$AA$5:$AA$43)*'IBK_N1'!$Y$5:$Y$43*'IBK_N1'!$AA$5:$AA$43)/SUMPRODUCT(ISNUMBER('IBK_N1'!$AA$5:$AA$43)*'IBK_N1'!$Y$5:$Y$43),"") | N6: =IFERROR(L6/M6-1,"") | O6: =IF(N6="","",IF(OR(N6<-0.25,N6>0.3),"ROJO",IF(OR(N6<-0.1,N6>0.15),"AMBAR","VERDE")))
A7: IBK_N2 | B7: =SUMPRODUCT(ISNUMBER('IBK_N2'!$O$5:$O$43)*'IBK_N2'!$B$5:$B$43) | C7: =IFERROR(SUMPRODUCT(ISNUMBER('IBK_N2'!$O$5:$O$43)*'IBK_N2'!$B$5:$B$43*'IBK_N2'!$C$5:$C$43)/SUMPRODUCT(ISNUMBER('IBK_N2'!$O$5:$O$43)*'IBK_N2'!$B$5:$B$43),"") | D7: =IFERROR(SUMPRODUCT(ISNUMBER('IBK_N2'!$O$5:$O$43)*'IBK_N2'!$B$5:$B$43*'IBK_N2'!$D$5:$D$43)/SUMPRODUCT(ISNUMBER('IBK_N2'!$O$5:$O$43)*'IBK_N2'!$B$5:$B$43),"") | E7: =IFERROR(SUMPRODUCT(ISNUMBER('IBK_N2'!$O$5:$O$43)*'IBK_N2'!$B$5:$B$43*'IBK_N2'!$E$5:$E$43)/SUMPRODUCT(ISNUMBER('IBK_N2'!$O$5:$O$43)*'IBK_N2'!$B$5:$B$43),"") | F7: =IFERROR(SUMPRODUCT(ISNUMBER('IBK_N2'!$O$5:$O$43)*'IBK_N2'!$B$5:$B$43*'IBK_N2'!$O$5:$O$43)/SUMPRODUCT(ISNUMBER('IBK_N2'!$O$5:$O$43)*'IBK_N2'!$B$5:$B$43),"") | G7: =IFERROR(D7/F7-1,"") | H7: =IFERROR(E7/F7-1,"") | I7: =IF(H7="","",IF(OR(H7<-0.25,H7>0.3),"ROJO",IF(OR(H7<-0.1,H7>0.15),"AMBAR","VERDE"))) | J7: =SUMPRODUCT(ISNUMBER('IBK_N2'!$AA$5:$AA$43)*'IBK_N2'!$Y$5:$Y$43) | K7: =IFERROR(J7/B7,"") | L7: =IFERROR(SUMPRODUCT(ISNUMBER('IBK_N2'!$AA$5:$AA$43)*'IBK_N2'!$Y$5:$Y$43*'IBK_N2'!$Z$5:$Z$43)/SUMPRODUCT(ISNUMBER('IBK_N2'!$AA$5:$AA$43)*'IBK_N2'!$Y$5:$Y$43),"") | M7: =IFERROR(SUMPRODUCT(ISNUMBER('IBK_N2'!$AA$5:$AA$43)*'IBK_N2'!$Y$5:$Y$43*'IBK_N2'!$AA$5:$AA$43)/SUMPRODUCT(ISNUMBER('IBK_N2'!$AA$5:$AA$43)*'IBK_N2'!$Y$5:$Y$43),"") | N7: =IFERROR(L7/M7-1,"") | O7: =IF(N7="","",IF(OR(N7<-0.25,N7>0.3),"ROJO",IF(OR(N7<-0.1,N7>0.15),"AMBAR","VERDE")))
A8: IBK_N3 | B8: =SUMPRODUCT(ISNUMBER('IBK_N3'!$O$5:$O$43)*'IBK_N3'!$B$5:$B$43) | C8: =IFERROR(SUMPRODUCT(ISNUMBER('IBK_N3'!$O$5:$O$43)*'IBK_N3'!$B$5:$B$43*'IBK_N3'!$C$5:$C$43)/SUMPRODUCT(ISNUMBER('IBK_N3'!$O$5:$O$43)*'IBK_N3'!$B$5:$B$43),"") | D8: =IFERROR(SUMPRODUCT(ISNUMBER('IBK_N3'!$O$5:$O$43)*'IBK_N3'!$B$5:$B$43*'IBK_N3'!$D$5:$D$43)/SUMPRODUCT(ISNUMBER('IBK_N3'!$O$5:$O$43)*'IBK_N3'!$B$5:$B$43),"") | E8: =IFERROR(SUMPRODUCT(ISNUMBER('IBK_N3'!$O$5:$O$43)*'IBK_N3'!$B$5:$B$43*'IBK_N3'!$E$5:$E$43)/SUMPRODUCT(ISNUMBER('IBK_N3'!$O$5:$O$43)*'IBK_N3'!$B$5:$B$43),"") | F8: =IFERROR(SUMPRODUCT(ISNUMBER('IBK_N3'!$O$5:$O$43)*'IBK_N3'!$B$5:$B$43*'IBK_N3'!$O$5:$O$43)/SUMPRODUCT(ISNUMBER('IBK_N3'!$O$5:$O$43)*'IBK_N3'!$B$5:$B$43),"") | G8: =IFERROR(D8/F8-1,"") | H8: =IFERROR(E8/F8-1,"") | I8: =IF(H8="","",IF(OR(H8<-0.25,H8>0.3),"ROJO",IF(OR(H8<-0.1,H8>0.15),"AMBAR","VERDE"))) | J8: =SUMPRODUCT(ISNUMBER('IBK_N3'!$AA$5:$AA$43)*'IBK_N3'!$Y$5:$Y$43) | K8: =IFERROR(J8/B8,"") | L8: =IFERROR(SUMPRODUCT(ISNUMBER('IBK_N3'!$AA$5:$AA$43)*'IBK_N3'!$Y$5:$Y$43*'IBK_N3'!$Z$5:$Z$43)/SUMPRODUCT(ISNUMBER('IBK_N3'!$AA$5:$AA$43)*'IBK_N3'!$Y$5:$Y$43),"") | M8: =IFERROR(SUMPRODUCT(ISNUMBER('IBK_N3'!$AA$5:$AA$43)*'IBK_N3'!$Y$5:$Y$43*'IBK_N3'!$AA$5:$AA$43)/SUMPRODUCT(ISNUMBER('IBK_N3'!$AA$5:$AA$43)*'IBK_N3'!$Y$5:$Y$43),"") | N8: =IFERROR(L8/M8-1,"") | O8: =IF(N8="","",IF(OR(N8<-0.25,N8>0.3),"ROJO",IF(OR(N8<-0.1,N8>0.15),"AMBAR","VERDE")))
A9: SSFF_con_BCP | B9: =SUMPRODUCT(ISNUMBER('SSFF_con_BCP'!$O$5:$O$43)*'SSFF_con_BCP'!$B$5:$B$43) | C9: =IFERROR(SUMPRODUCT(ISNUMBER('SSFF_con_BCP'!$O$5:$O$43)*'SSFF_con_BCP'!$B$5:$B$43*'SSFF_con_BCP'!$C$5:$C$43)/SUMPRODUCT(ISNUMBER('SSFF_con_BCP'!$O$5:$O$43)*'SSFF_con_BCP'!$B$5:$B$43),"") | D9: =IFERROR(SUMPRODUCT(ISNUMBER('SSFF_con_BCP'!$O$5:$O$43)*'SSFF_con_BCP'!$B$5:$B$43*'SSFF_con_BCP'!$D$5:$D$43)/SUMPRODUCT(ISNUMBER('SSFF_con_BCP'!$O$5:$O$43)*'SSFF_con_BCP'!$B$5:$B$43),"") | E9: =IFERROR(SUMPRODUCT(ISNUMBER('SSFF_con_BCP'!$O$5:$O$43)*'SSFF_con_BCP'!$B$5:$B$43*'SSFF_con_BCP'!$E$5:$E$43)/SUMPRODUCT(ISNUMBER('SSFF_con_BCP'!$O$5:$O$43)*'SSFF_con_BCP'!$B$5:$B$43),"") | F9: =IFERROR(SUMPRODUCT(ISNUMBER('SSFF_con_BCP'!$O$5:$O$43)*'SSFF_con_BCP'!$B$5:$B$43*'SSFF_con_BCP'!$O$5:$O$43)/SUMPRODUCT(ISNUMBER('SSFF_con_BCP'!$O$5:$O$43)*'SSFF_con_BCP'!$B$5:$B$43),"") | G9: =IFERROR(D9/F9-1,"") | H9: =IFERROR(E9/F9-1,"") | I9: =IF(H9="","",IF(OR(H9<-0.25,H9>0.3),"ROJO",IF(OR(H9<-0.1,H9>0.15),"AMBAR","VERDE"))) | J9: =SUMPRODUCT(ISNUMBER('SSFF_con_BCP'!$X$5:$X$43)*'SSFF_con_BCP'!$V$5:$V$43) | K9: =IFERROR(J9/B9,"") | L9: =IFERROR(SUMPRODUCT(ISNUMBER('SSFF_con_BCP'!$X$5:$X$43)*'SSFF_con_BCP'!$V$5:$V$43*'SSFF_con_BCP'!$W$5:$W$43)/SUMPRODUCT(ISNUMBER('SSFF_con_BCP'!$X$5:$X$43)*'SSFF_con_BCP'!$V$5:$V$43),"") | M9: =IFERROR(SUMPRODUCT(ISNUMBER('SSFF_con_BCP'!$X$5:$X$43)*'SSFF_con_BCP'!$V$5:$V$43*'SSFF_con_BCP'!$X$5:$X$43)/SUMPRODUCT(ISNUMBER('SSFF_con_BCP'!$X$5:$X$43)*'SSFF_con_BCP'!$V$5:$V$43),"") | N9: =IFERROR(L9/M9-1,"") | O9: =IF(N9="","",IF(OR(N9<-0.25,N9>0.3),"ROJO",IF(OR(N9<-0.1,N9>0.15),"AMBAR","VERDE")))
A10: SSFF_sin_BCP | B10: =SUMPRODUCT(ISNUMBER('SSFF_sin_BCP'!$O$5:$O$43)*'SSFF_sin_BCP'!$B$5:$B$43) | C10: =IFERROR(SUMPRODUCT(ISNUMBER('SSFF_sin_BCP'!$O$5:$O$43)*'SSFF_sin_BCP'!$B$5:$B$43*'SSFF_sin_BCP'!$C$5:$C$43)/SUMPRODUCT(ISNUMBER('SSFF_sin_BCP'!$O$5:$O$43)*'SSFF_sin_BCP'!$B$5:$B$43),"") | D10: =IFERROR(SUMPRODUCT(ISNUMBER('SSFF_sin_BCP'!$O$5:$O$43)*'SSFF_sin_BCP'!$B$5:$B$43*'SSFF_sin_BCP'!$D$5:$D$43)/SUMPRODUCT(ISNUMBER('SSFF_sin_BCP'!$O$5:$O$43)*'SSFF_sin_BCP'!$B$5:$B$43),"") | E10: =IFERROR(SUMPRODUCT(ISNUMBER('SSFF_sin_BCP'!$O$5:$O$43)*'SSFF_sin_BCP'!$B$5:$B$43*'SSFF_sin_BCP'!$E$5:$E$43)/SUMPRODUCT(ISNUMBER('SSFF_sin_BCP'!$O$5:$O$43)*'SSFF_sin_BCP'!$B$5:$B$43),"") | F10: =IFERROR(SUMPRODUCT(ISNUMBER('SSFF_sin_BCP'!$O$5:$O$43)*'SSFF_sin_BCP'!$B$5:$B$43*'SSFF_sin_BCP'!$O$5:$O$43)/SUMPRODUCT(ISNUMBER('SSFF_sin_BCP'!$O$5:$O$43)*'SSFF_sin_BCP'!$B$5:$B$43),"") | G10: =IFERROR(D10/F10-1,"") | H10: =IFERROR(E10/F10-1,"") | I10: =IF(H10="","",IF(OR(H10<-0.25,H10>0.3),"ROJO",IF(OR(H10<-0.1,H10>0.15),"AMBAR","VERDE"))) | J10: =SUMPRODUCT(ISNUMBER('SSFF_sin_BCP'!$X$5:$X$43)*'SSFF_sin_BCP'!$V$5:$V$43) | K10: =IFERROR(J10/B10,"") | L10: =IFERROR(SUMPRODUCT(ISNUMBER('SSFF_sin_BCP'!$X$5:$X$43)*'SSFF_sin_BCP'!$V$5:$V$43*'SSFF_sin_BCP'!$W$5:$W$43)/SUMPRODUCT(ISNUMBER('SSFF_sin_BCP'!$X$5:$X$43)*'SSFF_sin_BCP'!$V$5:$V$43),"") | M10: =IFERROR(SUMPRODUCT(ISNUMBER('SSFF_sin_BCP'!$X$5:$X$43)*'SSFF_sin_BCP'!$V$5:$V$43*'SSFF_sin_BCP'!$X$5:$X$43)/SUMPRODUCT(ISNUMBER('SSFF_sin_BCP'!$X$5:$X$43)*'SSFF_sin_BCP'!$V$5:$V$43),"") | N10: =IFERROR(L10/M10-1,"") | O10: =IF(N10="","",IF(OR(N10<-0.25,N10>0.3),"ROJO",IF(OR(N10<-0.1,N10>0.15),"AMBAR","VERDE")))
A11: SISTEMA_5 | B11: =SUMPRODUCT(ISNUMBER('SISTEMA_5'!$O$5:$O$43)*'SISTEMA_5'!$B$5:$B$43) | C11: =IFERROR(SUMPRODUCT(ISNUMBER('SISTEMA_5'!$O$5:$O$43)*'SISTEMA_5'!$B$5:$B$43*'SISTEMA_5'!$C$5:$C$43)/SUMPRODUCT(ISNUMBER('SISTEMA_5'!$O$5:$O$43)*'SISTEMA_5'!$B$5:$B$43),"") | D11: =IFERROR(SUMPRODUCT(ISNUMBER('SISTEMA_5'!$O$5:$O$43)*'SISTEMA_5'!$B$5:$B$43*'SISTEMA_5'!$D$5:$D$43)/SUMPRODUCT(ISNUMBER('SISTEMA_5'!$O$5:$O$43)*'SISTEMA_5'!$B$5:$B$43),"") | E11: =IFERROR(SUMPRODUCT(ISNUMBER('SISTEMA_5'!$O$5:$O$43)*'SISTEMA_5'!$B$5:$B$43*'SISTEMA_5'!$E$5:$E$43)/SUMPRODUCT(ISNUMBER('SISTEMA_5'!$O$5:$O$43)*'SISTEMA_5'!$B$5:$B$43),"") | F11: =IFERROR(SUMPRODUCT(ISNUMBER('SISTEMA_5'!$O$5:$O$43)*'SISTEMA_5'!$B$5:$B$43*'SISTEMA_5'!$O$5:$O$43)/SUMPRODUCT(ISNUMBER('SISTEMA_5'!$O$5:$O$43)*'SISTEMA_5'!$B$5:$B$43),"") | G11: =IFERROR(D11/F11-1,"") | H11: =IFERROR(E11/F11-1,"") | I11: =IF(H11="","",IF(OR(H11<-0.25,H11>0.3),"ROJO",IF(OR(H11<-0.1,H11>0.15),"AMBAR","VERDE"))) | J11: =SUMPRODUCT(ISNUMBER('SISTEMA_5'!$X$5:$X$43)*'SISTEMA_5'!$V$5:$V$43) | K11: =IFERROR(J11/B11,"") | L11: =IFERROR(SUMPRODUCT(ISNUMBER('SISTEMA_5'!$X$5:$X$43)*'SISTEMA_5'!$V$5:$V$43*'SISTEMA_5'!$W$5:$W$43)/SUMPRODUCT(ISNUMBER('SISTEMA_5'!$X$5:$X$43)*'SISTEMA_5'!$V$5:$V$43),"") | M11: =IFERROR(SUMPRODUCT(ISNUMBER('SISTEMA_5'!$X$5:$X$43)*'SISTEMA_5'!$V$5:$V$43*'SISTEMA_5'!$X$5:$X$43)/SUMPRODUCT(ISNUMBER('SISTEMA_5'!$X$5:$X$43)*'SISTEMA_5'!$V$5:$V$43),"") | N11: =IFERROR(L11/M11-1,"") | O11: =IF(N11="","",IF(OR(N11<-0.25,N11>0.3),"ROJO",IF(OR(N11<-0.1,N11>0.15),"AMBAR","VERDE")))
A12: ENT_00001_BCP | B12: =SUMPRODUCT(ISNUMBER('ENT_00001_BCP'!$O$5:$O$43)*'ENT_00001_BCP'!$B$5:$B$43) | C12: =IFERROR(SUMPRODUCT(ISNUMBER('ENT_00001_BCP'!$O$5:$O$43)*'ENT_00001_BCP'!$B$5:$B$43*'ENT_00001_BCP'!$C$5:$C$43)/SUMPRODUCT(ISNUMBER('ENT_00001_BCP'!$O$5:$O$43)*'ENT_00001_BCP'!$B$5:$B$43),"") | D12: =IFERROR(SUMPRODUCT(ISNUMBER('ENT_00001_BCP'!$O$5:$O$43)*'ENT_00001_BCP'!$B$5:$B$43*'ENT_00001_BCP'!$D$5:$D$43)/SUMPRODUCT(ISNUMBER('ENT_00001_BCP'!$O$5:$O$43)*'ENT_00001_BCP'!$B$5:$B$43),"") | E12: =IFERROR(SUMPRODUCT(ISNUMBER('ENT_00001_BCP'!$O$5:$O$43)*'ENT_00001_BCP'!$B$5:$B$43*'ENT_00001_BCP'!$E$5:$E$43)/SUMPRODUCT(ISNUMBER('ENT_00001_BCP'!$O$5:$O$43)*'ENT_00001_BCP'!$B$5:$B$43),"") | F12: =IFERROR(SUMPRODUCT(ISNUMBER('ENT_00001_BCP'!$O$5:$O$43)*'ENT_00001_BCP'!$B$5:$B$43*'ENT_00001_BCP'!$O$5:$O$43)/SUMPRODUCT(ISNUMBER('ENT_00001_BCP'!$O$5:$O$43)*'ENT_00001_BCP'!$B$5:$B$43),"") | G12: =IFERROR(D12/F12-1,"") | H12: =IFERROR(E12/F12-1,"") | I12: =IF(H12="","",IF(OR(H12<-0.25,H12>0.3),"ROJO",IF(OR(H12<-0.1,H12>0.15),"AMBAR","VERDE"))) | J12: =SUMPRODUCT(ISNUMBER('ENT_00001_BCP'!$X$5:$X$43)*'ENT_00001_BCP'!$V$5:$V$43) | K12: =IFERROR(J12/B12,"") | L12: =IFERROR(SUMPRODUCT(ISNUMBER('ENT_00001_BCP'!$X$5:$X$43)*'ENT_00001_BCP'!$V$5:$V$43*'ENT_00001_BCP'!$W$5:$W$43)/SUMPRODUCT(ISNUMBER('ENT_00001_BCP'!$X$5:$X$43)*'ENT_00001_BCP'!$V$5:$V$43),"") | M12: =IFERROR(SUMPRODUCT(ISNUMBER('ENT_00001_BCP'!$X$5:$X$43)*'ENT_00001_BCP'!$V$5:$V$43*'ENT_00001_BCP'!$X$5:$X$43)/SUMPRODUCT(ISNUMBER('ENT_00001_BCP'!$X$5:$X$43)*'ENT_00001_BCP'!$V$5:$V$43),"") | N12: =IFERROR(L12/M12-1,"") | O12: =IF(N12="","",IF(OR(N12<-0.25,N12>0.3),"ROJO",IF(OR(N12<-0.1,N12>0.15),"AMBAR","VERDE")))
A13: ENT_00006_BBVA | B13: =SUMPRODUCT(ISNUMBER('ENT_00006_BBVA'!$O$5:$O$43)*'ENT_00006_BBVA'!$B$5:$B$43) | C13: =IFERROR(SUMPRODUCT(ISNUMBER('ENT_00006_BBVA'!$O$5:$O$43)*'ENT_00006_BBVA'!$B$5:$B$43*'ENT_00006_BBVA'!$C$5:$C$43)/SUMPRODUCT(ISNUMBER('ENT_00006_BBVA'!$O$5:$O$43)*'ENT_00006_BBVA'!$B$5:$B$43),"") | D13: =IFERROR(SUMPRODUCT(ISNUMBER('ENT_00006_BBVA'!$O$5:$O$43)*'ENT_00006_BBVA'!$B$5:$B$43*'ENT_00006_BBVA'!$D$5:$D$43)/SUMPRODUCT(ISNUMBER('ENT_00006_BBVA'!$O$5:$O$43)*'ENT_00006_BBVA'!$B$5:$B$43),"") | E13: =IFERROR(SUMPRODUCT(ISNUMBER('ENT_00006_BBVA'!$O$5:$O$43)*'ENT_00006_BBVA'!$B$5:$B$43*'ENT_00006_BBVA'!$E$5:$E$43)/SUMPRODUCT(ISNUMBER('ENT_00006_BBVA'!$O$5:$O$43)*'ENT_00006_BBVA'!$B$5:$B$43),"") | F13: =IFERROR(SUMPRODUCT(ISNUMBER('ENT_00006_BBVA'!$O$5:$O$43)*'ENT_00006_BBVA'!$B$5:$B$43*'ENT_00006_BBVA'!$O$5:$O$43)/SUMPRODUCT(ISNUMBER('ENT_00006_BBVA'!$O$5:$O$43)*'ENT_00006_BBVA'!$B$5:$B$43),"") | G13: =IFERROR(D13/F13-1,"") | H13: =IFERROR(E13/F13-1,"") | I13: =IF(H13="","",IF(OR(H13<-0.25,H13>0.3),"ROJO",IF(OR(H13<-0.1,H13>0.15),"AMBAR","VERDE"))) | J13: =SUMPRODUCT(ISNUMBER('ENT_00006_BBVA'!$X$5:$X$43)*'ENT_00006_BBVA'!$V$5:$V$43) | K13: =IFERROR(J13/B13,"") | L13: =IFERROR(SUMPRODUCT(ISNUMBER('ENT_00006_BBVA'!$X$5:$X$43)*'ENT_00006_BBVA'!$V$5:$V$43*'ENT_00006_BBVA'!$W$5:$W$43)/SUMPRODUCT(ISNUMBER('ENT_00006_BBVA'!$X$5:$X$43)*'ENT_00006_BBVA'!$V$5:$V$43),"") | M13: =IFERROR(SUMPRODUCT(ISNUMBER('ENT_00006_BBVA'!$X$5:$X$43)*'ENT_00006_BBVA'!$V$5:$V$43*'ENT_00006_BBVA'!$X$5:$X$43)/SUMPRODUCT(ISNUMBER('ENT_00006_BBVA'!$X$5:$X$43)*'ENT_00006_BBVA'!$V$5:$V$43),"") | N13: =IFERROR(L13/M13-1,"") | O13: =IF(N13="","",IF(OR(N13<-0.25,N13>0.3),"ROJO",IF(OR(N13<-0.1,N13>0.15),"AMBAR","VERDE")))
A14: ENT_00004_Scotiabank | B14: =SUMPRODUCT(ISNUMBER('ENT_00004_Scotiabank'!$O$5:$O$43)*'ENT_00004_Scotiabank'!$B$5:$B$43) | C14: =IFERROR(SUMPRODUCT(ISNUMBER('ENT_00004_Scotiabank'!$O$5:$O$43)*'ENT_00004_Scotiabank'!$B$5:$B$43*'ENT_00004_Scotiabank'!$C$5:$C$43)/SUMPRODUCT(ISNUMBER('ENT_00004_Scotiabank'!$O$5:$O$43)*'ENT_00004_Scotiabank'!$B$5:$B$43),"") | D14: =IFERROR(SUMPRODUCT(ISNUMBER('ENT_00004_Scotiabank'!$O$5:$O$43)*'ENT_00004_Scotiabank'!$B$5:$B$43*'ENT_00004_Scotiabank'!$D$5:$D$43)/SUMPRODUCT(ISNUMBER('ENT_00004_Scotiabank'!$O$5:$O$43)*'ENT_00004_Scotiabank'!$B$5:$B$43),"") | E14: =IFERROR(SUMPRODUCT(ISNUMBER('ENT_00004_Scotiabank'!$O$5:$O$43)*'ENT_00004_Scotiabank'!$B$5:$B$43*'ENT_00004_Scotiabank'!$E$5:$E$43)/SUMPRODUCT(ISNUMBER('ENT_00004_Scotiabank'!$O$5:$O$43)*'ENT_00004_Scotiabank'!$B$5:$B$43),"") | F14: =IFERROR(SUMPRODUCT(ISNUMBER('ENT_00004_Scotiabank'!$O$5:$O$43)*'ENT_00004_Scotiabank'!$B$5:$B$43*'ENT_00004_Scotiabank'!$O$5:$O$43)/SUMPRODUCT(ISNUMBER('ENT_00004_Scotiabank'!$O$5:$O$43)*'ENT_00004_Scotiabank'!$B$5:$B$43),"") | G14: =IFERROR(D14/F14-1,"") | H14: =IFERROR(E14/F14-1,"") | I14: =IF(H14="","",IF(OR(H14<-0.25,H14>0.3),"ROJO",IF(OR(H14<-0.1,H14>0.15),"AMBAR","VERDE"))) | J14: =SUMPRODUCT(ISNUMBER('ENT_00004_Scotiabank'!$X$5:$X$43)*'ENT_00004_Scotiabank'!$V$5:$V$43) | K14: =IFERROR(J14/B14,"") | L14: =IFERROR(SUMPRODUCT(ISNUMBER('ENT_00004_Scotiabank'!$X$5:$X$43)*'ENT_00004_Scotiabank'!$V$5:$V$43*'ENT_00004_Scotiabank'!$W$5:$W$43)/SUMPRODUCT(ISNUMBER('ENT_00004_Scotiabank'!$X$5:$X$43)*'ENT_00004_Scotiabank'!$V$5:$V$43),"") | M14: =IFERROR(SUMPRODUCT(ISNUMBER('ENT_00004_Scotiabank'!$X$5:$X$43)*'ENT_00004_Scotiabank'!$V$5:$V$43*'ENT_00004_Scotiabank'!$X$5:$X$43)/SUMPRODUCT(ISNUMBER('ENT_00004_Scotiabank'!$X$5:$X$43)*'ENT_00004_Scotiabank'!$V$5:$V$43),"") | N14: =IFERROR(L14/M14-1,"") | O14: =IF(N14="","",IF(OR(N14<-0.25,N14>0.3),"ROJO",IF(OR(N14<-0.1,N14>0.15),"AMBAR","VERDE")))
A15: ENT_00142_Falabella | B15: =SUMPRODUCT(ISNUMBER('ENT_00142_Falabella'!$O$5:$O$43)*'ENT_00142_Falabella'!$B$5:$B$43) | C15: =IFERROR(SUMPRODUCT(ISNUMBER('ENT_00142_Falabella'!$O$5:$O$43)*'ENT_00142_Falabella'!$B$5:$B$43*'ENT_00142_Falabella'!$C$5:$C$43)/SUMPRODUCT(ISNUMBER('ENT_00142_Falabella'!$O$5:$O$43)*'ENT_00142_Falabella'!$B$5:$B$43),"") | D15: =IFERROR(SUMPRODUCT(ISNUMBER('ENT_00142_Falabella'!$O$5:$O$43)*'ENT_00142_Falabella'!$B$5:$B$43*'ENT_00142_Falabella'!$D$5:$D$43)/SUMPRODUCT(ISNUMBER('ENT_00142_Falabella'!$O$5:$O$43)*'ENT_00142_Falabella'!$B$5:$B$43),"") | E15: =IFERROR(SUMPRODUCT(ISNUMBER('ENT_00142_Falabella'!$O$5:$O$43)*'ENT_00142_Falabella'!$B$5:$B$43*'ENT_00142_Falabella'!$E$5:$E$43)/SUMPRODUCT(ISNUMBER('ENT_00142_Falabella'!$O$5:$O$43)*'ENT_00142_Falabella'!$B$5:$B$43),"") | F15: =IFERROR(SUMPRODUCT(ISNUMBER('ENT_00142_Falabella'!$O$5:$O$43)*'ENT_00142_Falabella'!$B$5:$B$43*'ENT_00142_Falabella'!$O$5:$O$43)/SUMPRODUCT(ISNUMBER('ENT_00142_Falabella'!$O$5:$O$43)*'ENT_00142_Falabella'!$B$5:$B$43),"") | G15: =IFERROR(D15/F15-1,"") | H15: =IFERROR(E15/F15-1,"") | I15: =IF(H15="","",IF(OR(H15<-0.25,H15>0.3),"ROJO",IF(OR(H15<-0.1,H15>0.15),"AMBAR","VERDE"))) | J15: =SUMPRODUCT(ISNUMBER('ENT_00142_Falabella'!$X$5:$X$43)*'ENT_00142_Falabella'!$V$5:$V$43) | K15: =IFERROR(J15/B15,"") | L15: =IFERROR(SUMPRODUCT(ISNUMBER('ENT_00142_Falabella'!$X$5:$X$43)*'ENT_00142_Falabella'!$V$5:$V$43*'ENT_00142_Falabella'!$W$5:$W$43)/SUMPRODUCT(ISNUMBER('ENT_00142_Falabella'!$X$5:$X$43)*'ENT_00142_Falabella'!$V$5:$V$43),"") | M15: =IFERROR(SUMPRODUCT(ISNUMBER('ENT_00142_Falabella'!$X$5:$X$43)*'ENT_00142_Falabella'!$V$5:$V$43*'ENT_00142_Falabella'!$X$5:$X$43)/SUMPRODUCT(ISNUMBER('ENT_00142_Falabella'!$X$5:$X$43)*'ENT_00142_Falabella'!$V$5:$V$43),"") | N15: =IFERROR(L15/M15-1,"") | O15: =IF(N15="","",IF(OR(N15<-0.25,N15>0.3),"ROJO",IF(OR(N15<-0.1,N15>0.15),"AMBAR","VERDE")))

Sheet FACTORES_DESARROLLO
A1: FACTORES DE DESARROLLO h -> 12 meses
A2: Chain-ladder ponderado por n. Deben decrecer con el horizonte.
A4: poblacion | B4: 3m | C4: 4m | D4: 5m | E4: 6m | F4: 7m | G4: 8m | H4: 9m | I4: 10m | J4: 11m | K4: 12m
A5: IBK_general | B5: 13.724816 | C5: 4.1733284 | D5: 2.7268733 | E5: 2.0882243 | F5: 1.7200924 | G5: 1.4563942 | H5: 1.285172 | I5: 1.16266 | J5: 1.0711409 | K5: 1
A6: IBK_N1 | B6: 19.022222 | C6: 6.0696203 | D6: 3.6863469 | E6: 2.6015625 | F6: 2.068323 | G6: 1.6567164 | H6: 1.4210526 | I6: 1.2742347 | J6: 1.0953947 | K6: 1
A7: IBK_N2 | B7: 14.830303 | C7: 5.0139442 | D7: 3.0252404 | E7: 2.3049451 | F7: 1.8603104 | G7: 1.5489231 | H7: 1.3452699 | I7: 1.1900709 | J7: 1.0830465 | K7: 1
A8: IBK_N3 | B8: 12.675497 | C8: 3.7957362 | D8: 2.5571142 | E8: 1.9762519 | F8: 1.6432711 | G8: 1.4065773 | H8: 1.2511848 | I8: 1.1409836 | J8: 1.0642202 | K8: 1
A9: SSFF_con_BCP | B9: 22.351549 | C9: 5.2444151 | D9: 3.0327167 | E9: 2.2281254 | F9: 1.7901006 | G9: 1.5215924 | H9: 1.3375362 | I9: 1.1985379 | J9: 1.0883006 | K9: 1
A10: SSFF_sin_BCP | B10: 20.738992 | C10: 4.9068398 | D10: 2.869834 | E10: 2.1282253 | F10: 1.7273307 | G10: 1.4800073 | H10: 1.311355 | I10: 1.1841568 | J10: 1.0815362 | K10: 1
A11: SISTEMA_5 | B11: 19.639243 | C11: 4.9644601 | D11: 2.9597765 | E11: 2.1958024 | F11: 1.7742341 | G11: 1.5067714 | H11: 1.3256681 | I11: 1.1904662 | J11: 1.0844833 | K11: 1
A12: ENT_00001_BCP | B12: 33.697115 | C12: 7.6178344 | D12: 4.0819113 | E12: 2.829653 | F12: 2.1427292 | G12: 1.7434402 | H12: 1.4704918 | I12: 1.2682927 | J12: 1.120025 | K12: 1
A13: ENT_00006_BBVA | B13: 22.085612 | C13: 5.0596568 | D13: 3.0741476 | E13: 2.2418829 | F13: 1.7827047 | G13: 1.5150082 | H13: 1.3296585 | I13: 1.1956228 | J13: 1.0884904 | K13: 1
A14: ENT_00004_Scotiabank | B14: 14.558442 | C14: 4.2553191 | D14: 2.7459954 | E14: 2.1057192 | F14: 1.7307692 | G14: 1.4907975 | H14: 1.3293217 | I14: 1.1994077 | J14: 1.0995475 | K14: 1
A15: ENT_00142_Falabella | B15: 19.582435 | C15: 4.7599251 | D15: 2.6231166 | E15: 1.9833021 | F15: 1.6520213 | G15: 1.4307103 | H15: 1.2838671 | I15: 1.1663913 | J15: 1.0698712 | K15: 1

Sheet IBK_general
A1: IBK general
A2: Interbank, poblacion clean
A4: codmes | B4: n | C4: PD sin calibrar | D4: PD cal vigente | E4: PD cal NUEVA | F4: mora 3m | G4: mora 4m | H4: mora 5m | I4: mora 6m | J4: mora 7m | K4: mora 8m | L4: mora 9m | M4: mora 10m | N4: mora 11m | O4: mora 12m | P4: ft ciclo | Q4: inflacion % | R4: madurez | S4: mora base | T4: factor h->12 | U4: proy mediana | V4: proy V1 | W4: proy V2 | X4: proy V3 | Y4: n visible IBK | Z4: PD cal NUEVA visible | AA4: mora 12m visible | AB4: EC vigente | AC4: EC NUEVA | AD4: EC NUEVA vs proy | AE4: EC NUEVA visible
A5: 202303 | B5: 6747 | C5: 0.1237198 | D5: 0.15572498 | E5: 0.13138193 | F5: 0.011857122 | G5: 0.041203498 | H5: 0.057803468 | I5: 0.076923077 | J5: 0.0961909 | K5: 0.11783015 | L5: 0.1332444 | M5: 0.14673188 | N5: 0.15532829 | O5: 0.16436935 | P5: 0.23130779 | Q5: 8.6661549 | R5: 12 | S5: 0.16436935 | T5: 1 | U5: 0.16436935 | Y5: 6405 | Z5: 0.1318232 | AA5: 0.16299766 | AB5: =IFERROR(D5/O5-1,"") | AC5: =IFERROR(E5/O5-1,"") | AD5: =IFERROR(E5/U5-1,"") | AE5: =IFERROR(Z5/AA5-1,"")
A6: 202304 | B6: 5942 | C6: 0.11411484 | D6: 0.14385094 | E6: 0.11766581 | F6: 0.0097610232 | G6: 0.033658701 | H6: 0.050488051 | I6: 0.06866375 | J6: 0.084819926 | K6: 0.10299562 | L6: 0.11814204 | M6: 0.13059576 | N6: 0.14018849 | O6: 0.14692023 | P6: 0.20398831 | Q6: 8.0421126 | R6: 12 | S6: 0.14692023 | T6: 1 | U6: 0.14692023 | Y6: 5708 | Z6: 0.11775088 | AA6: 0.14716188 | AB6: =IFERROR(D6/O6-1,"") | AC6: =IFERROR(E6/O6-1,"") | AD6: =IFERROR(E6/U6-1,"") | AE6: =IFERROR(Z6/AA6-1,"")
A7: 202305 | B7: 7417 | C7: 0.11612884 | D7: 0.14637197 | E7: 0.12110224 | F7: 0.0094377781 | G7: 0.036672509 | H7: 0.057705272 | I7: 0.075906701 | J7: 0.093703654 | K7: 0.11379264 | L7: 0.12956721 | M7: 0.14304975 | N7: 0.1512741 | O7: 0.15774572 | P7: 0.20154202 | Q7: 7.9862335 | R7: 12 | S7: 0.15774572 | T7: 1 | U7: 0.15774572 | Y7: 7070 | Z7: 0.12104071 | AA7: 0.15742574 | AB7: =IFERROR(D7/O7-1,"") | AC7: =IFERROR(E7/O7-1,"") | AD7: =IFERROR(E7/U7-1,"") | AE7: =IFERROR(Z7/AA7-1,"")
A8: 202306 | B8: 5236 | C8: 0.10819611 | D8: 0.13625009 | E8: 0.11068947 | F8: 0.011459129 | G8: 0.033040489 | H8: 0.054239878 | I8: 0.071237586 | J8: 0.084033613 | K8: 0.10103132 | L8: 0.11306341 | M8: 0.12089381 | N8: 0.13101604 | O8: 0.13770053 | P8: 0.14563116 | Q8: 6.7090957 | R8: 12 | S8: 0.13770053 | T8: 1 | U8: 0.13770053 | Y8: 4949 | Z8: 0.11034239 | AA8: 0.13457264 | AB8: =IFERROR(D8/O8-1,"") | AC8: =IFERROR(E8/O8-1,"") | AD8: =IFERROR(E8/U8-1,"") | AE8: =IFERROR(Z8/AA8-1,"")
A9: 202307 | B9: 3361 | C9: 0.089819245 | D9: 0.092360497 | E9: 0.086074495 | F9: 0.0056530794 | G9: 0.018744421 | H9: 0.026480214 | I9: 0.036298721 | J9: 0.045522166 | K9: 0.055340672 | L9: 0.061291282 | M9: 0.068134484 | N9: 0.075275216 | O9: 0.079143112 | P9: 0.11544766 | Q9: 6.0196325 | R9: 12 | S9: 0.079143112 | T9: 1 | U9: 0.079143112 | Y9: 3133 | Z9: 0.084289583 | AA9: 0.075646345 | AB9: =IFERROR(D9/O9-1,"") | AC9: =IFERROR(E9/O9-1,"") | AD9: =IFERROR(E9/U9-1,"") | AE9: =IFERROR(Z9/AA9-1,"")
A10: 202308 | B10: 4277 | C10: 0.095499117 | D10: 0.098508191 | E10: 0.092852791 | F10: 0.0049099836 | G10: 0.017769465 | H10: 0.028524667 | I10: 0.036474164 | J10: 0.047696984 | K10: 0.057049334 | L10: 0.066869301 | M10: 0.073415946 | N10: 0.077624503 | O10: 0.082768296 | P10: 0.10524205 | Q10: 5.7865118 | R10: 12 | S10: 0.082768296 | T10: 1 | U10: 0.082768296 | Y10: 4034 | Z10: 0.091897221 | AA10: 0.080317303 | AB10: =IFERROR(D10/O10-1,"") | AC10: =IFERROR(E10/O10-1,"") | AD10: =IFERROR(E10/U10-1,"") | AE10: =IFERROR(Z10/AA10-1,"")
A11: 202309 | B11: 2877 | C11: 0.093220388 | D11: 0.088391922 | E11: 0.0882549 | F11: 0.0066041015 | G11: 0.022245395 | H11: 0.028849496 | I11: 0.040319778 | J11: 0.049356969 | K11: 0.060827251 | L11: 0.067431352 | M11: 0.072297532 | N11: 0.077511296 | O11: 0.083767814 | P11: 0.082642878 | Q11: 5.2702928 | R11: 12 | S11: 0.083767814 | T11: 1 | U11: 0.083767814 | Y11: 2676 | Z11: 0.086385606 | AA11: 0.081464873 | AB11: =IFERROR(D11/O11-1,"") | AC11: =IFERROR(E11/O11-1,"") | AD11: =IFERROR(E11/U11-1,"") | AE11: =IFERROR(Z11/AA11-1,"")
A12: 202310 | B12: 2474 | C12: 0.094843223 | D12: 0.095298439 | E12: 0.084867105 | F12: 0.0060630558 | G12: 0.014955538 | H12: 0.028698464 | I12: 0.036378335 | J12: 0.044866613 | K12: 0.051333872 | L12: 0.057801132 | M12: 0.061843169 | N12: 0.067097817 | O12: 0.071139854 | P12: 0.049681202 | Q12: 4.5173693 | R12: 12 | S12: 0.071139854 | T12: 1 | U12: 0.071139854 | Y12: 2357 | Z12: 0.08301644 | AA12: 0.070852779 | AB12: =IFERROR(D12/O12-1,"") | AC12: =IFERROR(E12/O12-1,"") | AD12: =IFERROR(E12/U12-1,"") | AE12: =IFERROR(Z12/AA12-1,"")
A13: 202311 | B13: 2866 | C13: 0.13025806 | D13: 0.13194765 | E13: 0.12171049 | F13: 0.0052337753 | G13: 0.034193999 | H13: 0.05722261 | I13: 0.069085834 | J13: 0.083042568 | K13: 0.098743894 | L13: 0.10397767 | M13: 0.11304955 | N13: 0.12002791 | O13: 0.13189114 | P13: 0.017692212 | Q13: 3.7866642 | R13: 12 | S13: 0.13189114 | T13: 1 | U13: 0.13189114 | Y13: 2657 | Z13: 0.12036504 | AA13: 0.12721114 | AB13: =IFERROR(D13/O13-1,"") | AC13: =IFERROR(E13/O13-1,"") | AD13: =IFERROR(E13/U13-1,"") | AE13: =IFERROR(Z13/AA13-1,"")
A14: 202312 | B14: 3376 | C14: 0.14216821 | D14: 0.14358837 | E14: 0.13144005 | F14: 0.013625592 | G14: 0.046504739 | H14: 0.073459716 | I14: 0.091528436 | J14: 0.10367299 | K14: 0.1146327 | L14: 0.12588863 | M14: 0.13477488 | N14: 0.14810427 | O14: 0.15817536 | P14: 0.0012463847 | Q14: 3.4110022 | R14: 12 | S14: 0.15817536 | T14: 1 | U14: 0.15817536 | Y14: 3059 | Z14: 0.13183773 | AA14: 0.15397189 | AB14: =IFERROR(D14/O14-1,"") | AC14: =IFERROR(E14/O14-1,"") | AD14: =IFERROR(E14/U14-1,"") | AE14: =IFERROR(Z14/AA14-1,"")
A15: 202401 | B15: 4019 | C15: 0.12586277 | D15: 0.11865059 | E15: 0.1097944 | F15: 0.0097039064 | G15: 0.036576263 | H15: 0.055735258 | I15: 0.068673799 | J15: 0.074147798 | K15: 0.082109978 | L15: 0.089574521 | M15: 0.1030107 | N15: 0.11047524 | O15: 0.11868624 | P15: -0.019064283 | Q15: 2.947058 | R15: 12 | S15: 0.11868624 | T15: 1 | U15: 0.11868624 | Y15: 3599 | Z15: 0.10890536 | AA15: 0.11614337 | AB15: =IFERROR(D15/O15-1,"") | AC15: =IFERROR(E15/O15-1,"") | AD15: =IFERROR(E15/U15-1,"") | AE15: =IFERROR(Z15/AA15-1,"")
A16: 202402 | B16: 3916 | C16: 0.12972534 | D16: 0.12239881 | E16: 0.11393006 | F16: 0.012512768 | G16: 0.040091931 | H16: 0.05566905 | I16: 0.06639428 | J16: 0.07711951 | K16: 0.086312564 | L16: 0.098825332 | M16: 0.11287028 | N16: 0.12538304 | O16: 0.13406537 | P16: -0.019828668 | Q16: 2.9295976 | R16: 12 | S16: 0.13406537 | T16: 1 | U16: 0.13406537 | Y16: 3533 | Z16: 0.11284441 | AA16: 0.13274837 | AB16: =IFERROR(D16/O16-1,"") | AC16: =IFERROR(E16/O16-1,"") | AD16: =IFERROR(E16/U16-1,"") | AE16: =IFERROR(Z16/AA16-1,"")
... A32: 202506 | B32: 2259 | C32: 0.089828593 | D32: 0.085248871 | E32: 0.064312447 | F32: 0.0022133687 | G32: 0.0097388225 | H32: 0.016378929 | I32: 0.023461709 | J32: 0.03187251 | K32: 0.038069942 | L32: 0.041611332 | M32: 0.048251439 | N32: 0.051350155 | O32: 0.054448871 | P32: -0.073765695 | Q32: 1.697547 | R32: 12 | S32: 0.054448871 | T32: 1 | U32: 0.054448871 | Y32: 1985 | Z32: 0.062608002 | AA32: 0.050881612 | AB32: =IFERROR(D32/O32-1,"") | AC32: =IFERROR(E32/O32-1,"") | AD32: =IFERROR(E32/U32-1,"") | AE32: =IFERROR(Z32/AA32-1,"")
A33: 202507 | B33: 3092 | C33: 0.09961475 | D33: 0.094917748 | E33: 0.074698054 | F33: 0.0042043984 | G33: 0.01228978 | H33: 0.022639069 | I33: 0.027166882 | J33: 0.032988357 | K33: 0.037516171 | L33: 0.044954722 | M33: 0.052716688 | N33: 0.057891332 | P33: -0.073640896 | Q33: 1.7003977 | R33: 11 | S33: 0.057891332 | T33: 1.0711409 | U33: 0.062009776 | V33: 0.061383272 | W33: 0.062258636 | X33: 0.063218319 | Y33: 2705 | Z33: 0.071082782 | AB33: =IFERROR(D33/O33-1,"") | AC33: =IFERROR(E33/O33-1,"") | AD33: =IFERROR(E33/U33-1,"") | AE33: =IFERROR(Z33/AA33-1,"")
A34: 202508 | B34: 3056 | C34: 0.096165002 | D34: 0.091328032 | E34: 0.070116296 | F34: 0.0055628272 | G34: 0.017670157 | H34: 0.025850785 | I34: 0.033704188 | J34: 0.038612565 | K34: 0.044829843 | L34: 0.052356021 | M34: 0.060536649 | P34: -0.10033144 | Q34: 1.0907218 | R34: 10 | S34: 0.060536649 | T34: 1.16266 | U34: 0.070383541 | V34: 0.069720793 | W34: 0.07129536 | X34: 0.073915757 | Y34: 2672 | Z34: 0.067043592 | AB34: =IFERROR(D34/O34-1,"") | AC34: =IFERROR(E34/O34-1,"") | AD34: =IFERROR(E34/U34-1,"") | AE34: =IFERROR(Z34/AA34-1,"")
A35: 202509 | B35: 3136 | C35: 0.098972976 | D35: 0.094113533 | E35: 0.07319844 | F35: 0.0057397959 | G35: 0.017538265 | H35: 0.025191327 | I35: 0.031887755 | J35: 0.037308673 | K35: 0.043367347 | L35: 0.046875 | P35: -0.094338164 | Q35: 1.2276226 | R35: 9 | S35: 0.046875 | T35: 1.285172 | U35: 0.060242436 | V35: 0.058746111 | W35: 0.062081473 | X35: 0.063180296 | Y35: 2742 | Z35: 0.069893857 | AB35: =IFERROR(D35/O35-1,"") | AC35: =IFERROR(E35/O35-1,"") | AD35: =IFERROR(E35/U35-1,"") | AE35: =IFERROR(Z35/AA35-1,"")
A36: 202510 | B36: 3227 | C36: 0.094392252 | D36: 0.089712843 | E36: 0.068591051 | F36: 0.0040285095 | G36: 0.016733808 | H36: 0.023551286 | I36: 0.029439108 | J36: 0.038115897 | K36: 0.046482801 | P36: -0.097186463 | Q36: 1.1625606 | R36: 8 | S36: 0.046482801 | T36: 1.4563942 | U36: 0.067697283 | V36: 0.065940273 | W36: 0.068313117 | X36: 0.072320263 | Y36: 2781 | Z36: 0.065580935 | AB36: =IFERROR(D36/O36-1,"") | AC36: =IFERROR(E36/O36-1,"") | AD36: =IFERROR(E36/U36-1,"") | AE36: =IFERROR(Z36/AA36-1,"")
A37: 202511 | B37: 3016 | C37: 0.099025191 | D37: 0.094348219 | E37: 0.073531271 | F37: 0.0039787798 | G37: 0.018567639 | H37: 0.028514589 | I37: 0.037798408 | J37: 0.045092838 | P37: -0.095195045 | Q37: 1.2080494 | R37: 7 | S37: 0.045092838 | T37: 1.7200924 | U37: 0.077563847 | V37: 0.075792292 | W37: 0.078319602 | X37: 0.081976542 | Y37: 2569 | Z37: 0.070054053 | AB37: =IFERROR(D37/O37-1,"") | AC37: =IFERROR(E37/O37-1,"") | AD37: =IFERROR(E37/U37-1,"") | AE37: =IFERROR(Z37/AA37-1,"")
A38: 202512 | B38: 3285 | C38: 0.10310713 | D38: 0.098163468 | E38: 0.077449696 | F38: 0.0057838661 | G38: 0.020395738 | H38: 0.0304414 | I38: 0.042313546 | P38: -0.090738963 | Q38: 1.3098369 | R38: 6 | S38: 0.042313546 | T38: 2.0882243 | U38: 0.088360176 | V38: 0.084767234 | W38: 0.090562646 | X38: 0.097878393 | Y38: 2865 | Z38: 0.074513933 | AB38: =IFERROR(D38/O38-1,"") | AC38: =IFERROR(E38/O38-1,"") | AD38: =IFERROR(E38/U38-1,"") | AE38: =IFERROR(Z38/AA38-1,"")
A39: 202601 | B39: 3914 | C39: 0.097772737 | D39: 0.09307272 | E39: 0.072344478 | F39: 0.0071538068 | G39: 0.025804803 | H39: 0.038579458 | P39: -0.082751237 | Q39: 1.4922957 | R39: 5 | S39: 0.038579458 | T39: 2.7268733 | U39: 0.1052013 | V39: 0.097809141 | W39: 0.11198177 | X39: 0.12362116 | Y39: 3291 | Z39: 0.0677021 | AB39: =IFERROR(D39/O39-1,"") | AC39: =IFERROR(E39/O39-1,"") | AD39: =IFERROR(E39/U39-1,"") | AE39: =IFERROR(Z39/AA39-1,"")
A40: 202602 | B40: 3664 | C40: 0.098976439 | D40: 0.094103664 | E40: 0.079363752 | F40: 0.0095524017 | G40: 0.024836245 | P40: -0.037038893 | Q40: 2.5364749 | R40: 4 | S40: 0.024836245 | T40: 4.1733284 | U40: 0.1036498 | V40: 0.098604047 | W40: 0.10968347 | X40: 0.12715053 | Y40: 3145 | Z40: 0.075319056 | AB40: =IFERROR(D40/O40-1,"") | AC40: =IFERROR(E40/O40-1,"") | AD40: =IFERROR(E40/U40-1,"") | AE40: =IFERROR(Z40/AA40-1,"")
A41: 202603 | B41: 4269 | C41: 0.10215139 | D41: 0.097274933 | E41: 0.090227935 | F41: 0.0058561724 | P41: 0.014389803 | Q41: 3.7112293 | R41: 3 | S41: 0.0058561724 | T41: 13.724816 | U41: 0.080374887 | V41: 0.06995686 | W41: 0.081583802 | X41: 0.11252217 | Y41: 3623 | Z41: 0.085521044 | AB41: =IFERROR(D41/O41-1,"") | AC41: =IFERROR(E41/O41-1,"") | AD41: =IFERROR(E41/U41-1,"") | AE41: =IFERROR(Z41/AA41-1,"")
A42: 202604 | B42: 4047 | C42: 0.10496608 | D42: 0.098688834 | E42: 0.095354569 | P42: 0.024185191 | Q42: 3.9349794 | Y42: 3438 | Z42: 0.090227083 | AB42: =IFERROR(D42/O42-1,"") | AC42: =IFERROR(E42/O42-1,"") | AD42: =IFERROR(E42/U42-1,"") | AE42: =IFERROR(Z42/AA42-1,"")
A43: 202605 | B43: 4936 | C43: 0.10863506 | D43: 0.10172521 | E43: 0.099563383 | P43: 0.019247124 | Q43: 3.8221822 | Y43: 4132 | Z43: 0.0953794 | AB43: =IFERROR(D43/O43-1,"") | AC43: =IFERROR(E43/O43-1,"") | AD43: =IFERROR(E43/U43-1,"") | AE43: =IFERROR(Z43/AA43-1,"")

Sheet IBK_N1
A1: IBK N1
A2: Interbank, nodo N1
A4: codmes | B4: n | C4: PD sin calibrar | D4: PD cal vigente | E4: PD cal NUEVA | F4: mora 3m | G4: mora 4m | H4: mora 5m | I4: mora 6m | J4: mora 7m | K4: mora 8m | L4: mora 9m | M4: mora 10m | N4: mora 11m | O4: mora 12m | P4: ft ciclo | Q4: inflacion % | R4: madurez | S4: mora base | T4: factor h->12 | U4: proy mediana | V4: proy V1 | W4: proy V2 | X4: proy V3 | Y4: n visible IBK | Z4: PD cal NUEVA visible | AA4: mora 12m visible | AB4: EC vigente | AC4: EC NUEVA | AD4: EC NUEVA vs proy | AE4: EC NUEVA visible
A5: 202303 | B5: 547 | C5: 0.06458557 | D5: 0.078379974 | E5: 0.045464641 | F5: 0 | G5: 0 | H5: 0.0036563071 | I5: 0.012797075 | J5: 0.020109689 | K5: 0.02559415 | L5: 0.034734918 | M5: 0.036563071 | N5: 0.045703839 | O5: 0.053016453 | P5: 0.23130779 | Q5: 8.6661549 | R5: 12 | S5: 0.053016453 | T5: 1 | U5: 0.053016453 | Y5: 547 | Z5: 0.045464641 | AA5: 0.053016453 | AB5: =IFERROR(D5/O5-1,"") | AC5: =IFERROR(E5/O5-1,"") | AD5: =IFERROR(E5/U5-1,"") | AE5: =IFERROR(Z5/AA5-1,"")
A6: 202304 | B6: 639 | C6: 0.061598889 | D6: 0.075066159 | E6: 0.041910253 | F6: 0.0015649452 | G6: 0.0062597809 | H6: 0.0078247261 | I6: 0.012519562 | J6: 0.015649452 | K6: 0.018779343 | L6: 0.026604069 | M6: 0.028169014 | N6: 0.034428795 | O6: 0.03599374 | P6: 0.20398831 | Q6: 8.0421126 | R6: 12 | S6: 0.03599374 | T6: 1 | U6: 0.03599374 | Y6: 639 | Z6: 0.041910253 | AA6: 0.03599374 | AB6: =IFERROR(D6/O6-1,"") | AC6: =IFERROR(E6/O6-1,"") | AD6: =IFERROR(E6/U6-1,"") | AE6: =IFERROR(Z6/AA6-1,"")
A7: 202305 | B7: 746 | C7: 0.065038101 | D7: 0.078119894 | E7: 0.046525449 | F7: 0.0026809651 | G7: 0.0080428954 | H7: 0.012064343 | I7: 0.018766756 | J7: 0.021447721 | K7: 0.029490617 | L7: 0.034852547 | M7: 0.037533512 | N7: 0.042895442 | O7: 0.045576408 | P7: 0.20154202 | Q7: 7.9862335 | R7: 12 | S7: 0.045576408 | T7: 1 | U7: 0.045576408 | Y7: 746 | Z7: 0.046525449 | AA7: 0.045576408 | AB7: =IFERROR(D7/O7-1,"") | AC7: =IFERROR(E7/O7-1,"") | AD7: =IFERROR(E7/U7-1,"") | AE7: =IFERROR(Z7/AA7-1,"")
A8: 202306 | B8: 674 | C8: 0.060066591 | D8: 0.072297283 | E8: 0.040941053 | F8: 0.0029673591 | G8: 0.010385757 | H8: 0.011869436 | I8: 0.017804154 | J8: 0.022255193 | K8: 0.035608309 | L8: 0.040059347 | M8: 0.041543027 | N8: 0.044510386 | O8: 0.045994065 | P8: 0.14563116 | Q8: 6.7090957 | R8: 12 | S8: 0.045994065 | T8: 1 | U8: 0.045994065 | Y8: 674 | Z8: 0.040941053 | AA8: 0.045994065 | AB8: =IFERROR(D8/O8-1,"") | AC8: =IFERROR(E8/O8-1,"") | AD8: =IFERROR(E8/U8-1,"") | AE8: =IFERROR(Z8/AA8-1,"")
A9: 202307 | B9: 558 | C9: 0.055011289 | D9: 0.058060052 | E9: 0.034157772 | F9: 0.0017921147 | G9: 0.0053763441 | H9: 0.0071684588 | I9: 0.010752688 | J9: 0.016129032 | K9: 0.017921147 | L9: 0.021505376 | M9: 0.023297491 | N9: 0.028673835 | O9: 0.035842294 | P9: 0.11544766 | Q9: 6.0196325 | R9: 12 | S9: 0.035842294 | T9: 1 | U9: 0.035842294 | Y9: 558 | Z9: 0.034157772 | AA9: 0.035842294 | AB9: =IFERROR(D9/O9-1,"") | AC9: =IFERROR(E9/O9-1,"") | AD9: =IFERROR(E9/U9-1,"") | AE9: =IFERROR(Z9/AA9-1,"")
A10: 202308 | B10: 784 | C10: 0.073096935 | D10: 0.077683219 | E10: 0.055724923 | F10: 0.0012755102 | G10: 0.0038265306 | H10: 0.014030612 | I10: 0.017857143 | J10: 0.025510204 | K10: 0.031887755 | L10: 0.038265306 | M10: 0.042091837 | N10: 0.042091837 | O10: 0.044642857 | P10: 0.10524205 | Q10: 5.7865118 | R10: 12 | S10: 0.044642857 | T10: 1 | U10: 0.044642857 | Y10: 784 | Z10: 0.055724923 | AA10: 0.044642857 | AB10: =IFERROR(D10/O10-1,"") | AC10: =IFERROR(E10/O10-1,"") | AD10: =IFERROR(E10/U10-1,"") | AE10: =IFERROR(Z10/AA10-1,"")
A11: 202309 | B11: 506 | C11: 0.067996993 | D11: 0.062297749 | E11: 0.048910157 | F11: 0.0019762846 | G11: 0.0059288538 | H11: 0.0098814229 | I11: 0.019762846 | J11: 0.023715415 | K11: 0.035573123 | L11: 0.041501976 | M11: 0.04743083 | N11: 0.053359684 | O11: 0.057312253 | P11: 0.082642878 | Q11: 5.2702928 | R11: 12 | S11: 0.057312253 | T11: 1 | U11: 0.057312253 | Y11: 506 | Z11: 0.048910157 | AA11: 0.057312253 | AB11: =IFERROR(D11/O11-1,"") | AC11: =IFERROR(E11/O11-1,"") | AD11: =IFERROR(E11/U11-1,"") | AE11: =IFERROR(Z11/AA11-1,"")
A12: 202310 | B12: 390 | C12: 0.057893398 | D12: 0.054934826 | E12: 0.034631855 | F12: 0 | G12: 0.0076923077 | H12: 0.0076923077 | I12: 0.01025641 | J12: 0.017948718 | K12: 0.020512821 | L12: 0.020512821 | M12: 0.023076923 | N12: 0.025641026 | O12: 0.030769231 | P12: 0.049681202 | Q12: 4.5173693 | R12: 12 | S12: 0.030769231 | T12: 1 | U12: 0.030769231 | Y12: 390 | Z12: 0.034631855 | AA12: 0.030769231 | AB12: =IFERROR(D12/O12-1,"") | AC12: =IFERROR(E12/O12-1,"") | AD12: =IFERROR(E12/U12-1,"") | AE12: =IFERROR(Z12/AA12-1,"")
A13: 202311 | B13: 413 | C13: 0.12342747 | D13: 0.12370119 | E13: 0.11190965 | F13: 0.0024213075 | G13: 0.024213075 | H13: 0.046004843 | I13: 0.060532688 | J13: 0.07748184 | K13: 0.092009685 | L13: 0.0968523 | M13: 0.10653753 | N13: 0.11864407 | O13: 0.13075061 | P13: 0.017692212 | Q13: 3.7866642 | R13: 12 | S13: 0.13075061 | T13: 1 | U13: 0.13075061 | Y13: 413 | Z13: 0.11190965 | AA13: 0.13075061 | AB13: =IFERROR(D13/O13-1,"") | AC13: =IFERROR(E13/O13-1,"") | AD13: =IFERROR(E13/U13-1,"") | AE13: =IFERROR(Z13/AA13-1,"")
A14: 202312 | B14: 622 | C14: 0.13148555 | D14: 0.13140286 | E14: 0.11869668 | F14: 0.0048231511 | G14: 0.02733119 | H14: 0.045016077 | I14: 0.059485531 | J14: 0.067524116 | K14: 0.075562701 | L14: 0.078778135 | M14: 0.081993569 | N14: 0.096463023 | O14: 0.10128617 | P14: 0.0012463847 | Q14: 3.4110022 | R14: 12 | S14: 0.10128617 | T14: 1 | U14: 0.10128617 | Y14: 622 | Z14: 0.11869668 | AA14: 0.10128617 | AB14: =IFERROR(D14/O14-1,"") | AC14: =IFERROR(E14/O14-1,"") | AD14: =IFERROR(E14/U14-1,"") | AE14: =IFERROR(Z14/AA14-1,"")
A15: 202401 | B15: 858 | C15: 0.10240321 | D15: 0.093820201 | E15: 0.079469767 | F15: 0.0046620047 | G15: 0.017482517 | H15: 0.03030303 | I15: 0.037296037 | J15: 0.03962704 | K15: 0.045454545 | L15: 0.048951049 | M15: 0.055944056 | N15: 0.061771562 | O15: 0.068764569 | P15: -0.019064283 | Q15: 2.947058 | R15: 12 | S15: 0.068764569 | T15: 1 | U15: 0.068764569 | Y15: 858 | Z15: 0.079469767 | AA15: 0.068764569 | AB15: =IFERROR(D15/O15-1,"") | AC15: =IFERROR(E15/O15-1,"") | AD15: =IFERROR(E15/U15-1,"") | AE15: =IFERROR(Z15/AA15-1,"")
A16: 202402 | B16: 768 | C16: 0.10745189 | D16: 0.09841271 | E16: 0.086159465 | F16: 0.0078125 | G16: 0.01953125 | H16: 0.03515625 | I16: 0.044270833 | J16: 0.053385417 | K16: 0.069010417 | L16: 0.080729167 | M16: 0.092447917 | N16: 0.10286458 | O16: 0.11067708 | P16: -0.019828668 | Q16: 2.9295976 | R16: 12 | S16: 0.11067708 | T16: 1 | U16: 0.11067708 | Y16: 768 | Z16: 0.086159465 | AA16: 0.11067708 | AB16: =IFERROR(D16/O16-1,"") | AC16: =IFERROR(E16/O16-1,"") | AD16: =IFERROR(E16/U16-1,"") | AE16: =IFERROR(Z16/AA16-1,"")
... A32: 202506 | B32: 509 | C32: 0.06878093 | D32: 0.063699996 | E32: 0.036090685 | F32: 0 | G32: 0 | H32: 0.0039292731 | I32: 0.0078585462 | J32: 0.0098231827 | K32: 0.015717092 | L32: 0.017681729 | M32: 0.019646365 | N32: 0.021611002 | O32: 0.021611002 | P32: -0.073765695 | Q32: 1.697547 | R32: 12 | S32: 0.021611002 | T32: 1 | U32: 0.021611002 | Y32: 509 | Z32: 0.036090685 | AA32: 0.021611002 | AB32: =IFERROR(D32/O32-1,"") | AC32: =IFERROR(E32/O32-1,"") | AD32: =IFERROR(E32/U32-1,"") | AE32: =IFERROR(Z32/AA32-1,"")
A33: 202507 | B33: 561 | C33: 0.070563703 | D33: 0.065388718 | E33: 0.037468413 | F33: 0 | G33: 0.0017825312 | H33: 0.0035650624 | I33: 0.0035650624 | J33: 0.0053475936 | K33: 0.0071301248 | L33: 0.008912656 | M33: 0.012477718 | N33: 0.016042781 | P33: -0.073640896 | Q33: 1.7003977 | R33: 11 | S33: 0.016042781 | T33: 1.0953947 | U33: 0.017573178 | V33: 0.016726343 | W33: 0.017124453 | X33: 0.01824298 | Y33: 561 | Z33: 0.037468413 | AB33: =IFERROR(D33/O33-1,"") | AC33: =IFERROR(E33/O33-1,"") | AD33: =IFERROR(E33/U33-1,"") | AE33: =IFERROR(Z33/AA33-1,"")
A34: 202508 | B34: 651 | C34: 0.070092345 | D34: 0.064645414 | E34: 0.036383362 | F34: 0.0030721966 | G34: 0.0046082949 | H34: 0.010752688 | I34: 0.012288786 | J34: 0.012288786 | K34: 0.016897081 | L34: 0.01843318 | M34: 0.024577573 | P34: -0.10033144 | Q34: 1.0907218 | R34: 10 | S34: 0.024577573 | T34: 1.2742347 | U34: 0.031317596 | V34: 0.029629389 | W34: 0.030674774 | X34: 0.032770097 | Y34: 651 | Z34: 0.036383362 | AB34: =IFERROR(D34/O34-1,"") | AC34: =IFERROR(E34/O34-1,"") | AD34: =IFERROR(E34/U34-1,"") | AE34: =IFERROR(Z34/AA34-1,"")
A35: 202509 | B35: 592 | C35: 0.06672043 | D35: 0.061585114 | E35: 0.032372495 | F35: 0 | G35: 0.0033783784 | H35: 0.0067567568 | I35: 0.0067567568 | J35: 0.010135135 | K35: 0.011824324 | L35: 0.013513514 | P35: -0.094338164 | Q35: 1.2276226 | R35: 9 | S35: 0.013513514 | T35: 1.4210526 | U35: 0.019203414 | V35: 0.018018018 | W35: 0.019114894 | X35: 0.020778297 | Y35: 592 | Z35: 0.032372495 | AB35: =IFERROR(D35/O35-1,"") | AC35: =IFERROR(E35/O35-1,"") | AD35: =IFERROR(E35/U35-1,"") | AE35: =IFERROR(Z35/AA35-1,"")
A36: 202510 | B36: 600 | C36: 0.071445585 | D36: 0.066184865 | E36: 0.036855367 | F36: 0.0016666667 | G36: 0.0033333333 | H36: 0.0066666667 | I36: 0.0083333333 | J36: 0.0083333333 | K36: 0.011666667 | P36: -0.097186463 | Q36: 1.1625606 | R36: 8 | S36: 0.011666667 | T36: 1.6567164 | U36: 0.019328358 | V36: 0.017612179 | W36: 0.0195125 | X36: 0.022388117 | Y36: 600 | Z36: 0.036855367 | AB36: =IFERROR(D36/O36-1,"") | AC36: =IFERROR(E36/O36-1,"") | AD36: =IFERROR(E36/U36-1,"") | AE36: =IFERROR(Z36/AA36-1,"")
A37: 202511 | B37: 525 | C37: 0.069606633 | D37: 0.064674429 | E37: 0.035126754 | F37: 0 | G37: 0.0038095238 | H37: 0.0057142857 | I37: 0.017142857 | J37: 0.019047619 | P37: -0.095195045 | Q37: 1.2080494 | R37: 7 | S37: 0.019047619 | T37: 2.068323 | U37: 0.039396628 | V37: 0.037414966 | W37: 0.041190476 | X37: 0.04482684 | Y37: 525 | Z37: 0.035126754 | AB37: =IFERROR(D37/O37-1,"") | AC37: =IFERROR(E37/O37-1,"") | AD37: =IFERROR(E37/U37-1,"") | AE37: =IFERROR(Z37/AA37-1,"")
A38: 202512 | B38: 538 | C38: 0.078449248 | D38: 0.073034969 | E38: 0.043669776 | F38: 0.0018587361 | G38: 0.0037174721 | H38: 0.0055762082 | I38: 0.0074349442 | P38: -0.090738963 | Q38: 1.3098369 | R38: 6 | S38: 0.0074349442 | T38: 2.6015625 | U38: 0.019342472 | V38: 0.018454594 | W38: 0.020213755 | X38: 0.023215613 | Y38: 538 | Z38: 0.043669776 | AB38: =IFERROR(D38/O38-1,"") | AC38: =IFERROR(E38/O38-1,"") | AD38: =IFERROR(E38/U38-1,"") | AE38: =IFERROR(Z38/AA38-1,"")
A39: 202601 | B39: 656 | C39: 0.071884733 | D39: 0.066606593 | E39: 0.037285058 | F39: 0.0015243902 | G39: 0.0015243902 | H39: 0.0076219512 | P39: -0.082751237 | Q39: 1.4922957 | R39: 5 | S39: 0.0076219512 | T39: 3.6863469 | U39: 0.028097156 | V39: 0.024641422 | W39: 0.031546409 | X39: 0.040015244 | Y39: 656 | Z39: 0.037285058 | AB39: =IFERROR(D39/O39-1,"") | AC39: =IFERROR(E39/O39-1,"") | AD39: =IFERROR(E39/U39-1,"") | AE39: =IFERROR(Z39/AA39-1,"")
A40: 202602 | B40: 607 | C40: 0.072678548 | D40: 0.066877625 | E40: 0.041506508 | F40: 0.0016474465 | G40: 0.0016474465 | P40: -0.037038893 | Q40: 2.5364749 | R40: 4 | S40: 0.0016474465 | T40: 6.0696203 | U40: 0.0099993744 | V40: 0.0088138386 | W40: 0.010414215 | X40: 0.016831411 | Y40: 607 | Z40: 0.041506508 | AB40: =IFERROR(D40/O40-1,"") | AC40: =IFERROR(E40/O40-1,"") | AD40: =IFERROR(E40/U40-1,"") | AE40: =IFERROR(Z40/AA40-1,"")
A41: 202603 | B41: 698 | C41: 0.068862964 | D41: 0.063474054 | E41: 0.041229335 | F41: 0 | P41: 0.014389803 | Q41: 3.7112293 | R41: 3 | S41: 0 | T41: 19.022222 | U41: 0 | V41: 0 | W41: 0 | X41: 0 | Y41: 698 | Z41: 0.041229335 | AB41: =IFERROR(D41/O41-1,"") | AC41: =IFERROR(E41/O41-1,"") | AD41: =IFERROR(E41/U41-1,"") | AE41: =IFERROR(Z41/AA41-1,"")
A42: 202604 | B42: 602 | C42: 0.065371956 | D42: 0.060103768 | E42: 0.037920143 | P42: 0.024185191 | Q42: 3.9349794 | Y42: 602 | Z42: 0.037920143 | AB42: =IFERROR(D42/O42-1,"") | AC42: =IFERROR(E42/O42-1,"") | AD42: =IFERROR(E42/U42-1,"") | AE42: =IFERROR(Z42/AA42-1,"")
A43: 202605 | B43: 608 | C43: 0.071671278 | D43: 0.065289819 | E43: 0.044664622 | P43: 0.019247124 | Q43: 3.8221822 | Y43: 608 | Z43: 0.044664622 | AB43: =IFERROR(D43/O43-1,"") | AC43: =IFERROR(E43/O43-1,"") | AD43: =IFERROR(E43/U43-1,"") | AE43: =IFERROR(Z43/AA43-1,"")

Sheet IBK_N2
A1: IBK N2
A2: Interbank, nodo N2
A4: codmes | B4: n | C4: PD sin calibrar | D4: PD cal vigente | E4: PD cal NUEVA | F4: mora 3m | G4: mora 4m | H4: mora 5m | I4: mora 6m | J4: mora 7m | K4: mora 8m | L4: mora 9m | M4: mora 10m | N4: mora 11m | O4: mora 12m | P4: ft ciclo | Q4: inflacion % | R4: madurez | S4: mora base | T4: factor h->12 | U4: proy mediana | V4: proy V1 | W4: proy V2 | X4: proy V3 | Y4: n visible IBK | Z4: PD cal NUEVA visible | AA4: mora 12m visible | AB4: EC vigente | AC4: EC NUEVA | AD4: EC NUEVA vs proy | AE4: EC NUEVA visible
A5: 202303 | B5: 2129 | C5: 0.10951389 | D5: 0.13796817 | E5: 0.095852056 | F5: 0.0046970409 | G5: 0.021606388 | H5: 0.036167215 | I5: 0.047909817 | J5: 0.063879756 | K5: 0.080319399 | L5: 0.093940817 | M5: 0.10662283 | N5: 0.1146078 | O5: 0.1258807 | P5: 0.23130779 | Q5: 8.6661549 | R5: 12 | S5: 0.1258807 | T5: 1 | U5: 0.1258807 | Y5: 2129 | Z5: 0.095852056 | AA5: 0.1258807 | AB5: =IFERROR(D5/O5-1,"") | AC5: =IFERROR(E5/O5-1,"") | AD5: =IFERROR(E5/U5-1,"") | AE5: =IFERROR(Z5/AA5-1,"")
A6: 202304 | B6: 2131 | C6: 0.10361779 | D6: 0.13117086 | E6: 0.089440401 | F6: 0.0065696856 | G6: 0.019239794 | H6: 0.029563585 | I6: 0.044580009 | J6: 0.057719381 | K6: 0.070389489 | L6: 0.084936649 | M6: 0.098076021 | N6: 0.10886908 | O6: 0.11731581 | P6: 0.20398831 | Q6: 8.0421126 | R6: 12 | S6: 0.11731581 | T6: 1 | U6: 0.11731581 | Y6: 2131 | Z6: 0.089440401 | AA6: 0.11731581 | AB6: =IFERROR(D6/O6-1,"") | AC6: =IFERROR(E6/O6-1,"") | AD6: =IFERROR(E6/U6-1,"") | AE6: =IFERROR(Z6/AA6-1,"")
A7: 202305 | B7: 2511 | C7: 0.10671639 | D7: 0.13473184 | E7: 0.092859698 | F7: 0.0047789725 | G7: 0.022301872 | H7: 0.036240542 | I7: 0.050179211 | J7: 0.066507368 | K7: 0.081640781 | L7: 0.091995221 | M7: 0.10593389 | N7: 0.11469534 | O7: 0.11987256 | P7: 0.20154202 | Q7: 7.9862335 | R7: 12 | S7: 0.11987256 | T7: 1 | U7: 0.11987256 | Y7: 2511 | Z7: 0.092859698 | AA7: 0.11987256 | AB7: =IFERROR(D7/O7-1,"") | AC7: =IFERROR(E7/O7-1,"") | AD7: =IFERROR(E7/U7-1,"") | AE7: =IFERROR(Z7/AA7-1,"")
A8: 202306 | B8: 1808 | C8: 0.10047568 | D8: 0.12690394 | E8: 0.086118474 | F8: 0.0077433628 | G8: 0.012721239 | H8: 0.03539823 | I8: 0.049225664 | J8: 0.059734513 | K8: 0.075221239 | L8: 0.087389381 | M8: 0.097345133 | N8: 0.10896018 | O8: 0.11449115 | P8: 0.14563116 | Q8: 6.7090957 | R8: 12 | S8: 0.11449115 | T8: 1 | U8: 0.11449115 | Y8: 1808 | Z8: 0.086118474 | AA8: 0.11449115 | AB8: =IFERROR(D8/O8-1,"") | AC8: =IFERROR(E8/O8-1,"") | AD8: =IFERROR(E8/U8-1,"") | AE8: =IFERROR(Z8/AA8-1,"")
A9: 202307 | B9: 1213 | C9: 0.083441289 | D9: 0.085794547 | E9: 0.066802135 | F9: 0.0024732069 | G9: 0.01071723 | H9: 0.015663644 | I9: 0.022258862 | J9: 0.026380874 | K9: 0.034624897 | L9: 0.037922506 | M9: 0.043693322 | N9: 0.051112943 | O9: 0.05358615 | P9: 0.11544766 | Q9: 6.0196325 | R9: 12 | S9: 0.05358615 | T9: 1 | U9: 0.05358615 | Y9: 1213 | Z9: 0.066802135 | AA9: 0.05358615 | AB9: =IFERROR(D9/O9-1,"") | AC9: =IFERROR(E9/O9-1,"") | AD9: =IFERROR(E9/U9-1,"") | AE9: =IFERROR(Z9/AA9-1,"")
A10: 202308 | B10: 1418 | C10: 0.087107787 | D10: 0.089627009 | E10: 0.070301313 | F10: 0.0049365303 | G10: 0.011283498 | H10: 0.016220028 | I10: 0.02045134 | J10: 0.026798307 | K10: 0.034555712 | L10: 0.039492243 | M10: 0.044428773 | N10: 0.048660085 | O10: 0.052891396 | P10: 0.10524205 | Q10: 5.7865118 | R10: 12 | S10: 0.052891396 | T10: 1 | U10: 0.052891396 | Y10: 1418 | Z10: 0.070301313 | AA10: 0.052891396 | AB10: =IFERROR(D10/O10-1,"") | AC10: =IFERROR(E10/O10-1,"") | AD10: =IFERROR(E10/U10-1,"") | AE10: =IFERROR(Z10/AA10-1,"")
A11: 202309 | B11: 919 | C11: 0.084266115 | D11: 0.080106029 | E11: 0.065379588 | F11: 0.0010881393 | G11: 0.0097932535 | H11: 0.013057671 | I11: 0.019586507 | J11: 0.028291621 | K11: 0.033732318 | L11: 0.040261153 | M11: 0.044613711 | N11: 0.046789989 | O11: 0.052230686 | P11: 0.082642878 | Q11: 5.2702928 | R11: 12 | S11: 0.052230686 | T11: 1 | U11: 0.052230686 | Y11: 919 | Z11: 0.065379588 | AA11: 0.052230686 | AB11: =IFERROR(D11/O11-1,"") | AC11: =IFERROR(E11/O11-1,"") | AD11: =IFERROR(E11/U11-1,"") | AE11: =IFERROR(Z11/AA11-1,"")
A12: 202310 | B12: 888 | C12: 0.087891235 | D12: 0.088644015 | E12: 0.065449989 | F12: 0.0022522523 | G12: 0.009009009 | H12: 0.018018018 | I12: 0.025900901 | J12: 0.03490991 | K12: 0.040540541 | L12: 0.048423423 | M12: 0.054054054 | N12: 0.058558559 | O12: 0.063063063 | P12: 0.049681202 | Q12: 4.5173693 | R12: 12 | S12: 0.063063063 | T12: 1 | U12: 0.063063063 | Y12: 888 | Z12: 0.065449989 | AA12: 0.063063063 | AB12: =IFERROR(D12/O12-1,"") | AC12: =IFERROR(E12/O12-1,"") | AD12: =IFERROR(E12/U12-1,"") | AE12: =IFERROR(Z12/AA12-1,"")
A13: 202311 | B13: 828 | C13: 0.11543075 | D13: 0.11700124 | E13: 0.088990434 | F13: 0.0012077295 | G13: 0.015700483 | H13: 0.036231884 | I13: 0.047101449 | J13: 0.062801932 | K13: 0.076086957 | L13: 0.080917874 | M13: 0.09057971 | N13: 0.094202899 | O13: 0.097826087 | P13: 0.017692212 | Q13: 3.7866642 | R13: 12 | S13: 0.097826087 | T13: 1 | U13: 0.097826087 | Y13: 828 | Z13: 0.088990434 | AA13: 0.097826087 | AB13: =IFERROR(D13/O13-1,"") | AC13: =IFERROR(E13/O13-1,"") | AD13: =IFERROR(E13/U13-1,"") | AE13: =IFERROR(Z13/AA13-1,"")
A14: 202312 | B14: 896 | C14: 0.13810363 | D14: 0.13941653 | E14: 0.10866352 | F14: 0.013392857 | G14: 0.033482143 | H14: 0.060267857 | I14: 0.072544643 | J14: 0.083705357 | K14: 0.094866071 | L14: 0.10267857 | M14: 0.10714286 | N14: 0.12053571 | O14: 0.13058036 | P14: 0.0012463847 | Q14: 3.4110022 | R14: 12 | S14: 0.13058036 | T14: 1 | U14: 0.13058036 | Y14: 896 | Z14: 0.10866352 | AA14: 0.13058036 | AB14: =IFERROR(D14/O14-1,"") | AC14: =IFERROR(E14/O14-1,"") | AD14: =IFERROR(E14/U14-1,"") | AE14: =IFERROR(Z14/AA14-1,"")
A15: 202401 | B15: 1016 | C15: 0.11997624 | D15: 0.11298579 | E15: 0.088299158 | F15: 0.0088582677 | G15: 0.028543307 | H15: 0.042322835 | I15: 0.05511811 | J15: 0.058070866 | K15: 0.061023622 | L15: 0.066929134 | M15: 0.076771654 | N15: 0.083661417 | O15: 0.090551181 | P15: -0.019064283 | Q15: 2.947058 | R15: 12 | S15: 0.090551181 | T15: 1 | U15: 0.090551181 | Y15: 1016 | Z15: 0.088299158 | AA15: 0.090551181 | AB15: =IFERROR(D15/O15-1,"") | AC15: =IFERROR(E15/O15-1,"") | AD15: =IFERROR(E15/U15-1,"") | AE15: =IFERROR(Z15/AA15-1,"")
A16: 202402 | B16: 1020 | C16: 0.12228091 | D16: 0.11514337 | E16: 0.090233298 | F16: 0.0098039216 | G16: 0.02745098 | H16: 0.033333333 | I16: 0.041176471 | J16: 0.047058824 | K16: 0.05 | L16: 0.056862745 | M16: 0.067647059 | N16: 0.075490196 | O16: 0.083333333 | P16: -0.019828668 | Q16: 2.9295976 | R16: 12 | S16: 0.083333333 | T16: 1 | U16: 0.083333333 | Y16: 1020 | Z16: 0.090233298 | AA16: 0.083333333 | AB16: =IFERROR(D16/O16-1,"") | AC16: =IFERROR(E16/O16-1,"") | AD16: =IFERROR(E16/U16-1,"") | AE16: =IFERROR(Z16/AA16-1,"")
... A32: 202506 | B32: 631 | C32: 0.081967843 | D32: 0.078228992 | E32: 0.047372802 | F32: 0.0063391442 | G32: 0.012678288 | H32: 0.022187005 | I32: 0.026941363 | J32: 0.034865293 | K32: 0.04437401 | L32: 0.045958796 | M32: 0.050713154 | N32: 0.053882726 | O32: 0.055467512 | P32: -0.073765695 | Q32: 1.697547 | R32: 12 | S32: 0.055467512 | T32: 1 | U32: 0.055467512 | Y32: 631 | Z32: 0.047372802 | AA32: 0.055467512 | AB32: =IFERROR(D32/O32-1,"") | AC32: =IFERROR(E32/O32-1,"") | AD32: =IFERROR(E32/U32-1,"") | AE32: =IFERROR(Z32/AA32-1,"")
A33: 202507 | B33: 769 | C33: 0.089751887 | D33: 0.085792041 | E33: 0.053507904 | F33: 0.0052015605 | G33: 0.014304291 | H33: 0.024707412 | I33: 0.027308192 | J33: 0.035110533 | K33: 0.039011704 | L33: 0.046814044 | M33: 0.055916775 | N33: 0.055916775 | P33: -0.073640896 | Q33: 1.7003977 | R33: 11 | S33: 0.055916775 | T33: 1.0830465 | U33: 0.060560466 | V33: 0.059489236 | W33: 0.060412045 | X33: 0.062201994 | Y33: 769 | Z33: 0.053507904 | AB33: =IFERROR(D33/O33-1,"") | AC33: =IFERROR(E33/O33-1,"") | AD33: =IFERROR(E33/U33-1,"") | AE33: =IFERROR(Z33/AA33-1,"")
A34: 202508 | B34: 709 | C34: 0.088665799 | D34: 0.084520242 | E34: 0.05178037 | F34: 0.0028208745 | G34: 0.012693935 | H34: 0.01551481 | I34: 0.021156559 | J34: 0.02538787 | K34: 0.029619182 | L34: 0.036671368 | M34: 0.038081805 | P34: -0.10033144 | Q34: 1.0907218 | R34: 10 | S34: 0.038081805 | T34: 1.1900709 | U34: 0.045320049 | V34: 0.044544876 | W34: 0.045443941 | X34: 0.046952612 | Y34: 709 | Z34: 0.05178037 | AB34: =IFERROR(D34/O34-1,"") | AC34: =IFERROR(E34/O34-1,"") | AD34: =IFERROR(E34/U34-1,"") | AE34: =IFERROR(Z34/AA34-1,"")
A35: 202509 | B35: 752 | C35: 0.089500488 | D35: 0.085217064 | E35: 0.052911594 | F35: 0.0066489362 | G35: 0.010638298 | H35: 0.017287234 | I35: 0.021276596 | J35: 0.022606383 | K35: 0.02393617 | L35: 0.02393617 | P35: -0.094338164 | Q35: 1.2276226 | R35: 9 | S35: 0.02393617 | T35: 1.3452699 | U35: 0.03220061 | V35: 0.030899388 | W35: 0.032091982 | X35: 0.034223024 | Y35: 752 | Z35: 0.052911594 | AB35: =IFERROR(D35/O35-1,"") | AC35: =IFERROR(E35/O35-1,"") | AD35: =IFERROR(E35/U35-1,"") | AE35: =IFERROR(Z35/AA35-1,"")
A36: 202510 | B36: 795 | C36: 0.084440106 | D36: 0.080464165 | E36: 0.048294786 | F36: 0.0012578616 | G36: 0.011320755 | H36: 0.018867925 | I36: 0.022641509 | J36: 0.026415094 | K36: 0.032704403 | P36: -0.097186463 | Q36: 1.1625606 | R36: 8 | S36: 0.032704403 | T36: 1.5489231 | U36: 0.050656604 | V36: 0.047824649 | W36: 0.050756295 | X36: 0.054610182 | Y36: 795 | Z36: 0.048294786 | AB36: =IFERROR(D36/O36-1,"") | AC36: =IFERROR(E36/O36-1,"") | AD36: =IFERROR(E36/U36-1,"") | AE36: =IFERROR(Z36/AA36-1,"")
A37: 202511 | B37: 699 | C37: 0.089092401 | D37: 0.085098855 | E37: 0.05261295 | F37: 0 | G37: 0.012875536 | H37: 0.015736767 | I37: 0.017167382 | J37: 0.017167382 | P37: -0.095195045 | Q37: 1.2080494 | R37: 7 | S37: 0.017167382 | T37: 1.8603104 | U37: 0.03193666 | V37: 0.027179087 | W37: 0.032298889 | X37: 0.034876697 | Y37: 699 | Z37: 0.05261295 | AB37: =IFERROR(D37/O37-1,"") | AC37: =IFERROR(E37/O37-1,"") | AD37: =IFERROR(E37/U37-1,"") | AE37: =IFERROR(Z37/AA37-1,"")
A38: 202512 | B38: 785 | C38: 0.092837411 | D38: 0.088446975 | E38: 0.05583896 | F38: 0.0063694268 | G38: 0.014012739 | H38: 0.020382166 | I38: 0.029299363 | P38: -0.090738963 | Q38: 1.3098369 | R38: 6 | S38: 0.029299363 | T38: 2.3049451 | U38: 0.067533422 | V38: 0.060065746 | W38: 0.069069316 | X38: 0.077012877 | Y38: 784 | Z38: 0.055781154 | AB38: =IFERROR(D38/O38-1,"") | AC38: =IFERROR(E38/O38-1,"") | AD38: =IFERROR(E38/U38-1,"") | AE38: =IFERROR(Z38/AA38-1,"")
A39: 202601 | B39: 930 | C39: 0.087904403 | D39: 0.083975671 | E39: 0.051561874 | F39: 0.0064516129 | G39: 0.015053763 | H39: 0.020430108 | P39: -0.082751237 | Q39: 1.4922957 | R39: 5 | S39: 0.020430108 | T39: 3.0252404 | U39: 0.061805986 | V39: 0.051075269 | W39: 0.062992832 | X39: 0.071206885 | Y39: 930 | Z39: 0.051561874 | AB39: =IFERROR(D39/O39-1,"") | AC39: =IFERROR(E39/O39-1,"") | AD39: =IFERROR(E39/U39-1,"") | AE39: =IFERROR(Z39/AA39-1,"")
A40: 202602 | B40: 878 | C40: 0.084767441 | D40: 0.080692672 | E40: 0.052930633 | F40: 0.0045558087 | G40: 0.0091116173 | P40: -0.037038893 | Q40: 2.5364749 | R40: 4 | S40: 0.0091116173 | T40: 5.0139442 | U40: 0.045685141 | V40: 0.039147413 | W40: 0.046630042 | X40: 0.050368568 | Y40: 878 | Z40: 0.052930633 | AB40: =IFERROR(D40/O40-1,"") | AC40: =IFERROR(E40/O40-1,"") | AD40: =IFERROR(E40/U40-1,"") | AE40: =IFERROR(Z40/AA40-1,"")
A41: 202603 | B41: 913 | C41: 0.090583605 | D41: 0.086400115 | E41: 0.063266211 | F41: 0.0010952903 | P41: 0.014389803 | Q41: 3.7112293 | R41: 3 | S41: 0.0010952903 | T41: 14.830303 | U41: 0.016243486 | V41: 0.010808385 | W41: 0.015946905 | X41: 0.026195692 | Y41: 913 | Z41: 0.063266211 | AB41: =IFERROR(D41/O41-1,"") | AC41: =IFERROR(E41/O41-1,"") | AD41: =IFERROR(E41/U41-1,"") | AE41: =IFERROR(Z41/AA41-1,"")
A42: 202604 | B42: 869 | C42: 0.089478198 | D42: 0.084120645 | E42: 0.06357591 | P42: 0.024185191 | Q42: 3.9349794 | Y42: 869 | Z42: 0.06357591 | AB42: =IFERROR(D42/O42-1,"") | AC42: =IFERROR(E42/O42-1,"") | AD42: =IFERROR(E42/U42-1,"") | AE42: =IFERROR(Z42/AA42-1,"")
A43: 202605 | B43: 955 | C43: 0.09437141 | D43: 0.088262344 | E43: 0.067183211 | P43: 0.019247124 | Q43: 3.8221822 | Y43: 955 | Z43: 0.067183211 | AB43: =IFERROR(D43/O43-1,"") | AC43: =IFERROR(E43/O43-1,"") | AD43: =IFERROR(E43/U43-1,"") | AE43: =IFERROR(Z43/AA43-1,"")

Sheet IBK_N3
A1: IBK N3
A2: Interbank, nodo N3
A4: codmes | B4: n | C4: PD sin calibrar | D4: PD cal vigente | E4: PD cal NUEVA | F4: mora 3m | G4: mora 4m | H4: mora 5m | I4: mora 6m | J4: mora 7m | K4: mora 8m | L4: mora 9m | M4: mora 10m | N4: mora 11m | O4: mora 12m | P4: ft ciclo | Q4: inflacion % | R4: madurez | S4: mora base | T4: factor h->12 | U4: proy mediana | V4: proy V1 | W4: proy V2 | X4: proy V3 | Y4: n visible IBK | Z4: PD cal NUEVA visible | AA4: mora 12m visible | AB4: EC vigente | AC4: EC NUEVA | AD4: EC NUEVA vs proy | AE4: EC NUEVA visible
A5: 202303 | B5: 4071 | C5: 0.1390946 | D5: 0.17540367 | E5: 0.16150717 | F5: 0.017194792 | G5: 0.056988455 | H5: 0.076394006 | I5: 0.10071236 | J5: 0.12331123 | K5: 0.14984033 | L5: 0.16703513 | M5: 0.18251044 | N5: 0.19135348 | O5: 0.19945959 | P5: 0.23130779 | Q5: 8.6661549 | R5: 12 | S5: 0.19945959 | T5: 1 | U5: 0.19945959 | Y5: 3729 | Z5: 0.165028 | AA5: 0.2003218 | AB5: =IFERROR(D5/O5-1,"") | AC5: =IFERROR(E5/O5-1,"") | AD5: =IFERROR(E5/U5-1,"") | AE5: =IFERROR(Z5/AA5-1,"")
A6: 202304 | B6: 3172 | C6: 0.13174628 | D6: 0.16622633 | E6: 0.15188905 | F6: 0.013556116 | G6: 0.048865069 | H6: 0.073139975 | I6: 0.096153846 | J6: 0.11696091 | K6: 0.14186633 | L6: 0.15889029 | M6: 0.17307692 | N6: 0.18253468 | O6: 0.18915511 | P6: 0.20398831 | Q6: 8.0421126 | R6: 12 | S6: 0.18915511 | T6: 1 | U6: 0.18915511 | Y6: 2938 | Z6: 0.15478009 | AA6: 0.19298843 | AB6: =IFERROR(D6/O6-1,"") | AC6: =IFERROR(E6/O6-1,"") | AD6: =IFERROR(E6/U6-1,"") | AE6: =IFERROR(Z6/AA6-1,"")
A7: 202305 | B7: 4160 | C7: 0.13097219 | D7: 0.16563746 | E7: 0.15152322 | F7: 0.013461538 | G7: 0.050480769 | H7: 0.078846154 | I7: 0.10168269 | J7: 0.12307692 | K7: 0.14831731 | L7: 0.16923077 | M7: 0.184375 | N7: 0.19278846 | O7: 0.20072115 | P7: 0.20154202 | Q7: 7.9862335 | R7: 12 | S7: 0.20072115 | T7: 1 | U7: 0.20072115 | Y7: 3813 | Z7: 0.15417759 | AA7: 0.20403881 | AB7: =IFERROR(D7/O7-1,"") | AC7: =IFERROR(E7/O7-1,"") | AD7: =IFERROR(E7/U7-1,"") | AE7: =IFERROR(Z7/AA7-1,"")
A8: 202306 | B8: 2754 | C8: 0.12504354 | D8: 0.15803732 | E8: 0.1438902 | F8: 0.015976761 | G8: 0.051924473 | H8: 0.07697894 | I8: 0.098765432 | J8: 0.1151053 | K8: 0.13398693 | L8: 0.14778504 | M8: 0.15577342 | N8: 0.16666667 | O8: 0.17538126 | P8: 0.14563116 | Q8: 6.7090957 | R8: 12 | S8: 0.17538126 | T8: 1 | U8: 0.17538126 | Y8: 2467 | Z8: 0.14705634 | AA8: 0.17349007 | AB8: =IFERROR(D8/O8-1,"") | AC8: =IFERROR(E8/O8-1,"") | AD8: =IFERROR(E8/U8-1,"") | AE8: =IFERROR(Z8/AA8-1,"")
A9: 202307 | B9: 1590 | C9: 0.10690057 | D9: 0.10940713 | E9: 0.11899708 | F9: 0.0094339623 | G9: 0.029559748 | H9: 0.041509434 | I9: 0.055974843 | J9: 0.070440252 | K9: 0.08427673 | L9: 0.093081761 | M9: 0.10251572 | N9: 0.11006289 | O9: 0.11383648 | P9: 0.11544766 | Q9: 6.0196325 | R9: 12 | S9: 0.11383648 | T9: 1 | U9: 0.11383648 | Y9: 1362 | Z9: 0.12040252 | AA9: 0.11160059 | AB9: =IFERROR(D9/O9-1,"") | AC9: =IFERROR(E9/O9-1,"") | AD9: =IFERROR(E9/U9-1,"") | AE9: =IFERROR(Z9/AA9-1,"")
A10: 202308 | B10: 2075 | C10: 0.10969778 | D10: 0.11244568 | E10: 0.12229195 | F10: 0.0062650602 | G10: 0.02746988 | H10: 0.042409639 | I10: 0.054457831 | J10: 0.070361446 | K10: 0.081927711 | L10: 0.096385542 | M10: 0.10506024 | N10: 0.11084337 | O10: 0.11759036 | P10: 0.10524205 | Q10: 5.7865118 | R10: 12 | S10: 0.11759036 | T10: 1 | U10: 0.11759036 | Y10: 1832 | Z10: 0.12409268 | AA10: 0.11681223 | AB10: =IFERROR(D10/O10-1,"") | AC10: =IFERROR(E10/O10-1,"") | AD10: =IFERROR(E10/U10-1,"") | AE10: =IFERROR(Z10/AA10-1,"")
A11: 202309 | B11: 1452 | C11: 0.1076777 | D11: 0.10272965 | E11: 0.11644419 | F11: 0.011707989 | G11: 0.035812672 | H11: 0.045454545 | I11: 0.060606061 | J11: 0.071625344 | K11: 0.08677686 | L11: 0.093663912 | M11: 0.098484848 | N11: 0.1053719 | O11: 0.11294766 | P11: 0.082642878 | Q11: 5.2702928 | R11: 12 | S11: 0.11294766 | T11: 1 | U11: 0.11294766 | Y11: 1251 | Z11: 0.11697482 | AA11: 0.11270983 | AB11: =IFERROR(D11/O11-1,"") | AC11: =IFERROR(E11/O11-1,"") | AD11: =IFERROR(E11/U11-1,"") | AE11: =IFERROR(Z11/AA11-1,"")
A12: 202310 | B12: 1196 | C12: 0.11205376 | D12: 0.11340123 | E12: 0.11566489 | F12: 0.010869565 | G12: 0.02173913 | H12: 0.043478261 | I12: 0.052675585 | J12: 0.061036789 | K12: 0.069397993 | L12: 0.076923077 | M12: 0.080267559 | N12: 0.086956522 | O12: 0.090301003 | P12: 0.049681202 | Q12: 4.5173693 | R12: 12 | S12: 0.090301003 | T12: 1 | U12: 0.090301003 | Y12: 1079 | Z12: 0.11496176 | AA12: 0.091751622 | AB12: =IFERROR(D12/O12-1,"") | AC12: =IFERROR(E12/O12-1,"") | AD12: =IFERROR(E12/U12-1,"") | AE12: =IFERROR(Z12/AA12-1,"")
A13: 202311 | B13: 1625 | C13: 0.13954916 | D13: 0.14165929 | E13: 0.14087355 | F13: 0.008 | G13: 0.046153846 | H13: 0.070769231 | I13: 0.082461538 | J13: 0.094769231 | K13: 0.112 | L13: 0.11753846 | M13: 0.12615385 | N13: 0.13353846 | O13: 0.14953846 | P13: 0.017692212 | Q13: 3.7866642 | R13: 12 | S13: 0.14953846 | T13: 1 | U13: 0.14953846 | Y13: 1416 | Z13: 0.14117737 | AA13: 0.14336158 | AB13: =IFERROR(D13/O13-1,"") | AC13: =IFERROR(E13/O13-1,"") | AD13: =IFERROR(E13/U13-1,"") | AE13: =IFERROR(Z13/AA13-1,"")
A14: 202312 | B14: 1858 | C14: 0.14770452 | D14: 0.14967951 | E14: 0.14668987 | F14: 0.016684607 | G14: 0.059203445 | H14: 0.08934338 | I14: 0.11141012 | J14: 0.12540366 | K14: 0.13724435 | L14: 0.15285253 | M14: 0.16576964 | N14: 0.17868676 | O14: 0.19052745 | P14: 0.0012463847 | Q14: 3.4110022 | R14: 12 | S14: 0.19052745 | T14: 1 | U14: 0.19052745 | Y14: 1541 | Z14: 0.15061634 | AA14: 0.18883842 | AB14: =IFERROR(D14/O14-1,"") | AC14: =IFERROR(E14/O14-1,"") | AD14: =IFERROR(E14/U14-1,"") | AE14: =IFERROR(Z14/AA14-1,"")
A15: 202401 | B15: 2145 | C15: 0.1380348 | D15: 0.13126593 | E15: 0.13210568 | F15: 0.012121212 | G15: 0.048018648 | H15: 0.072261072 | I15: 0.087645688 | J15: 0.095571096 | K15: 0.10675991 | L15: 0.11655012 | M15: 0.13426573 | N15: 0.14265734 | O15: 0.15198135 | P15: -0.019064283 | Q15: 2.947058 | R15: 12 | S15: 0.15198135 | T15: 1 | U15: 0.15198135 | Y15: 1725 | Z15: 0.13568312 | AA15: 0.15478261 | AB15: =IFERROR(D15/O15-1,"") | AC15: =IFERROR(E15/O15-1,"") | AD15: =IFERROR(E15/U15-1,"") | AE15: =IFERROR(Z15/AA15-1,"")
A16: 202402 | B16: 2128 | C16: 0.14133216 | D16: 0.13453315 | E16: 0.13531095 | F16: 0.015507519 | G16: 0.053571429 | H16: 0.073778195 | I16: 0.086466165 | J16: 0.10009398 | K16: 0.10996241 | L16: 0.12546992 | M16: 0.14191729 | N16: 0.15742481 | O16: 0.16682331 | P16: -0.019828668 | Q16: 2.9295976 | R16: 12 | S16: 0.16682331 | T16: 1 | U16: 0.16682331 | Y16: 1745 | Z16: 0.13780565 | AA16: 0.1713467 | AB16: =IFERROR(D16/O16-1,"") | AC16: =IFERROR(E16/O16-1,"") | AD16: =IFERROR(E16/U16-1,"") | AE16: =IFERROR(Z16/AA16-1,"")
... A32: 202506 | B32: 1119 | C32: 0.1038352 | D32: 0.099009301 | E32: 0.086701896 | F32: 0.00089365505 | G32: 0.012511171 | H32: 0.018766756 | I32: 0.028596962 | J32: 0.040214477 | K32: 0.044682752 | L32: 0.050044683 | M32: 0.059874888 | N32: 0.063449508 | O32: 0.068811439 | P32: -0.073765695 | Q32: 1.697547 | R32: 12 | S32: 0.068811439 | T32: 1 | U32: 0.068811439 | Y32: 845 | Z32: 0.089957973 | AA32: 0.065088757 | AB32: =IFERROR(D32/O32-1,"") | AC32: =IFERROR(E32/O32-1,"") | AD32: =IFERROR(E32/U32-1,"") | AE32: =IFERROR(Z32/AA32-1,"")
A33: 202507 | B33: 1762 | C33: 0.11316877 | D33: 0.10830223 | E33: 0.095799674 | F33: 0.005107832 | G33: 0.014755959 | H33: 0.027809308 | I33: 0.03461975 | J33: 0.040862656 | K33: 0.046538025 | L33: 0.055618615 | M33: 0.064131669 | N33: 0.072077185 | P33: -0.073640896 | Q33: 1.7003977 | R33: 11 | S33: 0.072077185 | T33: 1.0642202 | U33: 0.076705995 | V33: 0.076042344 | W33: 0.076922461 | X33: 0.078522784 | Y33: 1375 | Z33: 0.094626594 | AB33: =IFERROR(D33/O33-1,"") | AC33: =IFERROR(E33/O33-1,"") | AD33: =IFERROR(E33/U33-1,"") | AE33: =IFERROR(Z33/AA33-1,"")
A34: 202508 | B34: 1696 | C34: 0.10930783 | D34: 0.10441595 | E34: 0.090729687 | F34: 0.0076650943 | G34: 0.024764151 | H34: 0.035966981 | I34: 0.047169811 | J34: 0.054245283 | K34: 0.061910377 | L34: 0.071933962 | M34: 0.083726415 | P34: -0.10033144 | Q34: 1.0907218 | R34: 10 | S34: 0.083726415 | T34: 1.1409836 | U34: 0.095530467 | V34: 0.094542177 | W34: 0.096725896 | X34: 0.099260681 | Y34: 1312 | Z34: 0.09050505 | AB34: =IFERROR(D34/O34-1,"") | AC34: =IFERROR(E34/O34-1,"") | AD34: =IFERROR(E34/U34-1,"") | AE34: =IFERROR(Z34/AA34-1,"")
A35: 202509 | B35: 1792 | C35: 0.1136029 | D35: 0.10859287 | E35: 0.095198813 | F35: 0.0072544643 | G35: 0.025111607 | H35: 0.034598214 | I35: 0.044642857 | J35: 0.052455357 | K35: 0.061941964 | L35: 0.067522321 | P35: -0.094338164 | Q35: 1.2276226 | R35: 9 | S35: 0.067522321 | T35: 1.2511848 | U35: 0.084482905 | V35: 0.08215385 | W35: 0.086957152 | X35: 0.089905521 | Y35: 1398 | Z35: 0.094917682 | AB35: =IFERROR(D35/O35-1,"") | AC35: =IFERROR(E35/O35-1,"") | AD35: =IFERROR(E35/U35-1,"") | AE35: =IFERROR(Z35/AA35-1,"")
A36: 202510 | B36: 1832 | C36: 0.10622629 | D36: 0.10143199 | E36: 0.087792438 | F36: 0.0060043668 | G36: 0.023471616 | H36: 0.031113537 | I36: 0.03930131 | J36: 0.052947598 | K36: 0.063864629 | P36: -0.097186463 | Q36: 1.1625606 | R36: 8 | S36: 0.063864629 | T36: 1.4065773 | U36: 0.089830534 | V36: 0.086016133 | W36: 0.091429307 | X36: 0.098438617 | Y36: 1386 | Z36: 0.087931461 | AB36: =IFERROR(D36/O36-1,"") | AC36: =IFERROR(E36/O36-1,"") | AD36: =IFERROR(E36/U36-1,"") | AE36: =IFERROR(Z36/AA36-1,"")
A37: 202511 | B37: 1792 | C37: 0.11151836 | D37: 0.10664958 | E37: 0.09294214 | F37: 0.0066964286 | G37: 0.025111607 | H37: 0.040178571 | I37: 0.051897321 | J37: 0.063616071 | P37: -0.095195045 | Q37: 1.2080494 | R37: 7 | S37: 0.063616071 | T37: 1.6432711 | U37: 0.10453845 | V37: 0.1009691 | W37: 0.10507906 | X37: 0.1143314 | Y37: 1345 | Z37: 0.092751571 | AB37: =IFERROR(D37/O37-1,"") | AC37: =IFERROR(E37/O37-1,"") | AD37: =IFERROR(E37/U37-1,"") | AE37: =IFERROR(Z37/AA37-1,"")
A38: 202512 | B38: 1962 | C38: 0.11397751 | D38: 0.10894154 | E38: 0.095358985 | F38: 0.0066258919 | G38: 0.027522936 | H38: 0.041284404 | I38: 0.057084608 | P38: -0.090738963 | Q38: 1.3098369 | R38: 6 | S38: 0.057084608 | T38: 1.9762519 | U38: 0.11281357 | V38: 0.10599574 | W38: 0.11493715 | X38: 0.13258248 | Y38: 1543 | Z38: 0.094786555 | AB38: =IFERROR(D38/O38-1,"") | AC38: =IFERROR(E38/O38-1,"") | AD38: =IFERROR(E38/U38-1,"") | AE38: =IFERROR(Z38/AA38-1,"")
A39: 202601 | B39: 2328 | C39: 0.10900988 | D39: 0.10416466 | E39: 0.090526093 | F39: 0.0090206186 | G39: 0.036941581 | H39: 0.054553265 | P39: -0.082751237 | Q39: 1.4922957 | R39: 5 | S39: 0.054553265 | T39: 2.5571142 | U39: 0.13949893 | V39: 0.13240063 | W39: 0.14257506 | X39: 0.18639032 | Y39: 1705 | Z39: 0.088208839 | AB39: =IFERROR(D39/O39-1,"") | AC39: =IFERROR(E39/O39-1,"") | AD39: =IFERROR(E39/U39-1,"") | AE39: =IFERROR(Z39/AA39-1,"")
A40: 202602 | B40: 2179 | C40: 0.11202753 | D40: 0.10709176 | E40: 0.10056046 | F40: 0.013767783 | G40: 0.037631941 | P40: -0.037038893 | Q40: 2.5364749 | R40: 4 | S40: 0.037631941 | T40: 3.7957362 | U40: 0.14284092 | V40: 0.13085192 | W40: 0.15297453 | X40: 0.19908957 | Y40: 1660 | Z40: 0.099524629 | AB40: =IFERROR(D40/O40-1,"") | AC40: =IFERROR(E40/O40-1,"") | AD40: =IFERROR(E40/U40-1,"") | AE40: =IFERROR(Z40/AA40-1,"")
A41: 202603 | B41: 2658 | C41: 0.11486647 | D41: 0.10988657 | E41: 0.11235626 | F41: 0.0090293454 | P41: 0.014389803 | Q41: 3.7112293 | R41: 3 | S41: 0.0090293454 | T41: 12.675497 | U41: 0.11445144 | V41: 0.098621657 | W41: 0.12362104 | X41: 0.16357006 | Y41: 2012 | Z41: 0.1109854 | AB41: =IFERROR(D41/O41-1,"") | AC41: =IFERROR(E41/O41-1,"") | AD41: =IFERROR(E41/U41-1,"") | AE41: =IFERROR(Z41/AA41-1,"")
A42: 202604 | B42: 2576 | C42: 0.1194438 | D42: 0.1126205 | E42: 0.11949711 | P42: 0.024185191 | Q42: 3.9349794 | Y42: 1967 | Z42: 0.11800982 | AB42: =IFERROR(D42/O42-1,"") | AC42: =IFERROR(E42/O42-1,"") | AD42: =IFERROR(E42/U42-1,"") | AE42: =IFERROR(Z42/AA42-1,"")
A43: 202605 | B43: 3373 | C43: 0.11933644 | D43: 0.11210463 | E43: 0.11862698 | P43: 0.019247124 | Q43: 3.8221822 | Y43: 2569 | Z43: 0.11786361 | AB43: =IFERROR(D43/O43-1,"") | AC43: =IFERROR(E43/O43-1,"") | AD43: =IFERROR(E43/U43-1,"") | AE43: =IFERROR(Z43/AA43-1,"")

Sheet SSFF_con_BCP
A1: SSFF con BCP
A2: BCP + Scotiabank + BBVA + Falabella (el sistema SIN Interbank)
A4: codmes | B4: n | C4: PD sin calibrar | D4: PD cal vigente | E4: PD cal NUEVA | F4: mora 3m | G4: mora 4m | H4: mora 5m | I4: mora 6m | J4: mora 7m | K4: mora 8m | L4: mora 9m | M4: mora 10m | N4: mora 11m | O4: mora 12m | P4: ft ciclo | Q4: inflacion % | R4: madurez | S4: mora base | T4: factor h->12 | U4: proy mediana | V4: n visible IBK | W4: PD cal NUEVA visible | X4: mora 12m visible | Y4: EC vigente | Z4: EC NUEVA | AA4: EC NUEVA vs proy | AB4: EC NUEVA visible
A5: 202303 | B5: 18845 | C5: 0.13454715 | D5: 0.16973027 | E5: 0.15342186 | F5: 0.0054125763 | G5: 0.019315468 | H5: 0.031997877 | I5: 0.042876094 | J5: 0.053913505 | K5: 0.064685593 | L5: 0.074396392 | M5: 0.083098965 | N5: 0.091642345 | O5: 0.10045105 | P5: 0.23130779 | Q5: 8.6661549 | R5: 12 | S5: 0.10045105 | T5: 1 | U5: 0.10045105 | V5: 6772 | W5: 0.15512533 | X5: 0.11591849 | Y5: =IFERROR(D5/O5-1,"") | Z5: =IFERROR(E5/O5-1,"") | AA5: =IFERROR(E5/U5-1,"") | AB5: =IFERROR(W5/X5-1,"")
A6: 202304 | B6: 20578 | C6: 0.13721611 | D6: 0.17292146 | E6: 0.15658622 | F6: 0.0032559044 | G6: 0.017445816 | H6: 0.030323647 | I6: 0.043250073 | J6: 0.05583633 | K6: 0.067110506 | L6: 0.077558558 | M6: 0.086743124 | N6: 0.096316454 | O6: 0.10637574 | P6: 0.20398831 | Q6: 8.0421126 | R6: 12 | S6: 0.10637574 | T6: 1 | U6: 0.10637574 | V6: 7676 | W6: 0.15933139 | X6: 0.11985409 | Y6: =IFERROR(D6/O6-1,"") | Z6: =IFERROR(E6/O6-1,"") | AA6: =IFERROR(E6/U6-1,"") | AB6: =IFERROR(W6/X6-1,"")
A7: 202305 | B7: 16149 | C7: 0.13537868 | D7: 0.17063036 | E7: 0.15418767 | F7: 0.0048919438 | G7: 0.019196235 | H7: 0.032943216 | I7: 0.045327884 | J7: 0.055421388 | K7: 0.066134126 | L7: 0.07511301 | M7: 0.084029971 | N7: 0.094371168 | O7: 0.10384544 | P7: 0.20154202 | Q7: 7.9862335 | R7: 12 | S7: 0.10384544 | T7: 1 | U7: 0.10384544 | V7: 5827 | W7: 0.15622353 | X7: 0.1175562 | Y7: =IFERROR(D7/O7-1,"") | Z7: =IFERROR(E7/O7-1,"") | AA7: =IFERROR(E7/U7-1,"") | AB7: =IFERROR(W7/X7-1,"")
A8: 202306 | B8: 12321 | C8: 0.13253649 | D8: 0.16701058 | E8: 0.15030789 | F8: 0.0043015989 | G8: 0.01517734 | H8: 0.026377729 | I8: 0.036766496 | J8: 0.046911777 | K8: 0.054459865 | L8: 0.063387712 | M8: 0.072396721 | N8: 0.080999919 | O8: 0.088385683 | P8: 0.14563116 | Q8: 6.7090957 | R8: 12 | S8: 0.088385683 | T8: 1 | U8: 0.088385683 | V8: 4522 | W8: 0.1530644 | X8: 0.10526316 | Y8: =IFERROR(D8/O8-1,"") | Z8: =IFERROR(E8/O8-1,"") | AA8: =IFERROR(E8/U8-1,"") | AB8: =IFERROR(W8/X8-1,"")
A9: 202307 | B9: 10733 | C9: 0.13043735 | D9: 0.13303649 | E9: 0.14557679 | F9: 0.0027019473 | G9: 0.014907295 | H9: 0.024690208 | I9: 0.032982391 | J9: 0.040063356 | K9: 0.049007733 | L9: 0.058697475 | M9: 0.067641852 | N9: 0.076213547 | O9: 0.08599646 | P9: 0.11544766 | Q9: 6.0196325 | R9: 12 | S9: 0.08599646 | T9: 1 | U9: 0.08599646 | V9: 4078 | W9: 0.14938358 | X9: 0.10323688 | Y9: =IFERROR(D9/O9-1,"") | Z9: =IFERROR(E9/O9-1,"") | AA9: =IFERROR(E9/U9-1,"") | AB9: =IFERROR(W9/X9-1,"")
A10: 202308 | B10: 11994 | C10: 0.13103286 | D10: 0.1336693 | E10: 0.1467013 | F10: 0.003835251 | G10: 0.014257129 | H10: 0.024762381 | I10: 0.032266133 | J10: 0.042104386 | K10: 0.050275138 | L10: 0.059696515 | M10: 0.067783892 | N10: 0.076038019 | O10: 0.082374521 | P10: 0.10524205 | Q10: 5.7865118 | R10: 12 | S10: 0.082374521 | T10: 1 | U10: 0.082374521 | V10: 4400 | W10: 0.14654745 | X10: 0.099318182 | Y10: =IFERROR(D10/O10-1,"") | Z10: =IFERROR(E10/O10-1,"") | AA10: =IFERROR(E10/U10-1,"") | AB10: =IFERROR(W10/X10-1,"")
A11: 202309 | B11: 10921 | C11: 0.12791971 | D11: 0.12287714 | E11: 0.13924271 | F11: 0.0026554345 | G11: 0.013185606 | H11: 0.022159143 | I11: 0.031590514 | J11: 0.039648384 | K11: 0.049079755 | L11: 0.057320758 | M11: 0.063913561 | N11: 0.069682264 | O11: 0.0764582 | P11: 0.082642878 | Q11: 5.2702928 | R11: 12 | S11: 0.0764582 | T11: 1 | U11: 0.0764582 | V11: 4017 | W11: 0.1402118 | X11: 0.086631815 | Y11: =IFERROR(D11/O11-1,"") | Z11: =IFERROR(E11/O11-1,"") | AA11: =IFERROR(E11/U11-1,"") | AB11: =IFERROR(W11/X11-1,"")
A12: 202310 | B12: 11826 | C12: 0.12672998 | D12: 0.12857377 | E12: 0.13129248 | F12: 0.0027059022 | G12: 0.011922882 | H12: 0.021562659 | I12: 0.030356841 | J12: 0.038897345 | K12: 0.046930492 | L12: 0.054963639 | M12: 0.062235752 | N12: 0.068239472 | O12: 0.073397599 | P12: 0.049681202 | Q12: 4.5173693 | R12: 12 | S12: 0.073397599 | T12: 1 | U12: 0.073397599 | V12: 4255 | W12: 0.12981202 | X12: 0.090951821 | Y12: =IFERROR(D12/O12-1,"") | Z12: =IFERROR(E12/O12-1,"") | AA12: =IFERROR(E12/U12-1,"") | AB12: =IFERROR(W12/X12-1,"")
A13: 202311 | B13: 12398 | C13: 0.12707223 | D13: 0.12933227 | E13: 0.12569809 | F13: 0.002823036 | G13: 0.011292144 | H13: 0.020890466 | I13: 0.029601549 | J13: 0.038070657 | K13: 0.04629779 | L13: 0.052266495 | M13: 0.058315857 | N13: 0.064526537 | O13: 0.07009195 | P13: 0.017692212 | Q13: 3.7866642 | R13: 12 | S13: 0.07009195 | T13: 1 | U13: 0.07009195 | V13: 4503 | W13: 0.12516113 | X13: 0.086164779 | Y13: =IFERROR(D13/O13-1,"") | Z13: =IFERROR(E13/O13-1,"") | AA13: =IFERROR(E13/U13-1,"") | AB13: =IFERROR(W13/X13-1,"")
A14: 202312 | B14: 12132 | C14: 0.13109735 | D14: 0.13342365 | E14: 0.12699472 | F14: 0.003214639 | G14: 0.014589515 | H14: 0.024563139 | I14: 0.034866469 | J14: 0.044345532 | K14: 0.052176063 | L14: 0.057698648 | M14: 0.065364326 | N14: 0.073030003 | O14: 0.079541708 | P14: 0.0012463847 | Q14: 3.4110022 | R14: 12 | S14: 0.079541708 | T14: 1 | U14: 0.079541708 | V14: 4379 | W14: 0.12688457 | X14: 0.092258507 | Y14: =IFERROR(D14/O14-1,"") | Z14: =IFERROR(E14/O14-1,"") | AA14: =IFERROR(E14/U14-1,"") | AB14: =IFERROR(W14/X14-1,"")
A15: 202401 | B15: 14511 | C15: 0.13030638 | D15: 0.12515089 | E15: 0.12243233 | F15: 0.0034456619 | G15: 0.015712218 | H15: 0.025911378 | I15: 0.035697057 | J15: 0.042588381 | K15: 0.049479705 | L15: 0.055681896 | M15: 0.061677348 | N15: 0.066570188 | O15: 0.071600855 | P15: -0.019064283 | Q15: 2.947058 | R15: 12 | S15: 0.071600855 | T15: 1 | U15: 0.071600855 | V15: 5200 | W15: 0.12306035 | X15: 0.089423077 | Y15: =IFERROR(D15/O15-1,"") | Z15: =IFERROR(E15/O15-1,"") | AA15: =IFERROR(E15/U15-1,"") | AB15: =IFERROR(W15/X15-1,"")
A16: 202402 | B16: 14265 | C16: 0.13086722 | D16: 0.12568045 | E16: 0.12279291 | F16: 0.0044164038 | G16: 0.016263582 | H16: 0.027129338 | I16: 0.033438486 | J16: 0.041219769 | K16: 0.049211356 | L16: 0.055240098 | M16: 0.060988433 | N16: 0.066876972 | O16: 0.073676831 | P16: -0.019828668 | Q16: 2.9295976 | R16: 12 | S16: 0.073676831 | T16: 1 | U16: 0.073676831 | V16: 5285 | W16: 0.12267361 | X16: 0.087038789 | Y16: =IFERROR(D16/O16-1,"") | Z16: =IFERROR(E16/O16-1,"") | AA16: =IFERROR(E16/U16-1,"") | AB16: =IFERROR(W16/X16-1,"")
... A32: 202506 | B32: 21701 | C32: 0.15699073 | D32: 0.1509895 | E32: 0.1392537 | F32: 0.0047463251 | G32: 0.021888392 | H32: 0.038108843 | I32: 0.050596747 | J32: 0.060964932 | K32: 0.069628128 | L32: 0.078567808 | M32: 0.087507488 | N32: 0.096124603 | O32: 0.10418875 | P32: -0.073765695 | Q32: 1.697547 | R32: 12 | S32: 0.10418875 | T32: 1 | U32: 0.10418875 | V32: 8829 | W32: 0.14270333 | X32: 0.11915279 | Y32: =IFERROR(D32/O32-1,"") | Z32: =IFERROR(E32/O32-1,"") | AA32: =IFERROR(E32/U32-1,"") | AB32: =IFERROR(W32/X32-1,"")
A33: 202507 | B33: 20916 | C33: 0.15859265 | D33: 0.15258394 | E33: 0.14071323 | F33: 0.0048288392 | G33: 0.022423025 | H33: 0.036670491 | I33: 0.04637598 | J33: 0.055507745 | K33: 0.065069803 | L33: 0.074153758 | M33: 0.08275961 | N33: 0.090935169 | P33: -0.073640896 | Q33: 1.7003977 | R33: 11 | S33: 0.090935169 | T33: 1.0883006 | U33: 0.098964803 | V33: 8617 | W33: 0.14812441 | Y33: =IFERROR(D33/O33-1,"") | Z33: =IFERROR(E33/O33-1,"") | AA33: =IFERROR(E33/U33-1,"") | AB33: =IFERROR(W33/X33-1,"")
A34: 202508 | B34: 20638 | C34: 0.16817657 | D34: 0.16193069 | E34: 0.14836186 | F34: 0.0057176083 | G34: 0.027618955 | H34: 0.042349065 | I34: 0.054753368 | J34: 0.065994767 | K34: 0.077575346 | L34: 0.088913654 | M34: 0.10000969 | P34: -0.10033144 | Q34: 1.0907218 | R34: 10 | S34: 0.10000969 | T34: 1.1985379 | U34: 0.1198654 | V34: 8694 | W34: 0.15787182 | Y34: =IFERROR(D34/O34-1,"") | Z34: =IFERROR(E34/O34-1,"") | AA34: =IFERROR(E34/U34-1,"") | AB34: =IFERROR(W34/X34-1,"")
A35: 202509 | B35: 23394 | C35: 0.16831393 | D35: 0.16207984 | E35: 0.14876688 | F35: 0.0069248525 | G35: 0.02769941 | H35: 0.042660511 | I35: 0.056809438 | J35: 0.069334017 | K35: 0.080063264 | L35: 0.090963495 | P35: -0.094338164 | Q35: 1.2276226 | R35: 9 | S35: 0.090963495 | T35: 1.3375362 | U35: 0.12166697 | V35: 9531 | W35: 0.15815347 | Y35: =IFERROR(D35/O35-1,"") | Z35: =IFERROR(E35/O35-1,"") | AA35: =IFERROR(E35/U35-1,"") | AB35: =IFERROR(W35/X35-1,"")
A36: 202510 | B36: 25164 | C36: 0.17354346 | D36: 0.16714369 | E36: 0.15380366 | F36: 0.0070338579 | G36: 0.029725004 | H36: 0.049594659 | I36: 0.06509299 | J36: 0.077610873 | K36: 0.08989032 | P36: -0.097186463 | Q36: 1.1625606 | R36: 8 | S36: 0.08989032 | T36: 1.5215924 | U36: 0.13677643 | V36: 10281 | W36: 0.16397651 | Y36: =IFERROR(D36/O36-1,"") | Z36: =IFERROR(E36/O36-1,"") | AA36: =IFERROR(E36/U36-1,"") | AB36: =IFERROR(W36/X36-1,"")
A37: 202511 | B37: 25402 | C37: 0.1731559 | D37: 0.16673869 | E37: 0.15314332 | F37: 0.00755846 | G37: 0.03739863 | H37: 0.057751358 | I37: 0.072907645 | J37: 0.086056216 | P37: -0.095195045 | Q37: 1.2080494 | R37: 7 | S37: 0.086056216 | T37: 1.7901006 | U37: 0.15404929 | V37: 10557 | W37: 0.16219149 | Y37: =IFERROR(D37/O37-1,"") | Z37: =IFERROR(E37/O37-1,"") | AA37: =IFERROR(E37/U37-1,"") | AB37: =IFERROR(W37/X37-1,"")
A38: 202512 | B38: 25171 | C38: 0.16852339 | D38: 0.16223867 | E38: 0.14878109 | F38: 0.0075483692 | G38: 0.032060705 | H38: 0.050772715 | I38: 0.064598149 | P38: -0.090738963 | Q38: 1.3098369 | R38: 6 | S38: 0.064598149 | T38: 2.2281254 | U38: 0.14393277 | V38: 10221 | W38: 0.15847261 | Y38: =IFERROR(D38/O38-1,"") | Z38: =IFERROR(E38/O38-1,"") | AA38: =IFERROR(E38/U38-1,"") | AB38: =IFERROR(W38/X38-1,"")
A39: 202601 | B39: 26557 | C39: 0.16328581 | D39: 0.15713031 | E39: 0.14346849 | F39: 0.0059118123 | G39: 0.028542381 | H39: 0.04575065 | P39: -0.082751237 | Q39: 1.4922957 | R39: 5 | S39: 0.04575065 | T39: 3.0327167 | U39: 0.13874876 | V39: 10946 | W39: 0.14929301 | Y39: =IFERROR(D39/O39-1,"") | Z39: =IFERROR(E39/O39-1,"") | AA39: =IFERROR(E39/U39-1,"") | AB39: =IFERROR(W39/X39-1,"")
A40: 202602 | B40: 24910 | C40: 0.16691283 | D40: 0.16067247 | E40: 0.15688823 | F40: 0.0091529506 | G40: 0.032396628 | P40: -0.037038893 | Q40: 2.5364749 | R40: 4 | S40: 0.032396628 | T40: 5.2444151 | U40: 0.16990136 | V40: 10146 | W40: 0.16503357 | Y40: =IFERROR(D40/O40-1,"") | Z40: =IFERROR(E40/O40-1,"") | AA40: =IFERROR(E40/U40-1,"") | AB40: =IFERROR(W40/X40-1,"")
A41: 202603 | B41: 27126 | C41: 0.16499483 | D41: 0.15882837 | E41: 0.16632309 | F41: 0.0073361351 | P41: 0.014389803 | Q41: 3.7112293 | R41: 3 | S41: 0.0073361351 | T41: 22.351549 | U41: 0.16397398 | V41: 11250 | W41: 0.17497196 | Y41: =IFERROR(D41/O41-1,"") | Z41: =IFERROR(E41/O41-1,"") | AA41: =IFERROR(E41/U41-1,"") | AB41: =IFERROR(W41/X41-1,"")
A42: 202604 | B42: 24689 | C42: 0.16231404 | D42: 0.15399171 | E42: 0.16552022 | P42: 0.024185191 | Q42: 3.9349794 | V42: 10250 | W42: 0.17058262 | Y42: =IFERROR(D42/O42-1,"") | Z42: =IFERROR(E42/O42-1,"") | AA42: =IFERROR(E42/U42-1,"") | AB42: =IFERROR(W42/X42-1,"")
A43: 202605 | B43: 25907 | C43: 0.16236311 | D43: 0.1540411 | E43: 0.16443061 | P43: 0.019247124 | Q43: 3.8221822 | V43: 10639 | W43: 0.1706907 | Y43: =IFERROR(D43/O43-1,"") | Z43: =IFERROR(E43/O43-1,"") | AA43: =IFERROR(E43/U43-1,"") | AB43: =IFERROR(W43/X43-1,"")

Sheet SSFF_sin_BCP
A1: SSFF sin BCP
A2: Scotiabank + BBVA + Falabella
A4: codmes | B4: n | C4: PD sin calibrar | D4: PD cal vigente | E4: PD cal NUEVA | F4: mora 3m | G4: mora 4m | H4: mora 5m | I4: mora 6m | J4: mora 7m | K4: mora 8m | L4: mora 9m | M4: mora 10m | N4: mora 11m | O4: mora 12m | P4: ft ciclo | Q4: inflacion % | R4: madurez | S4: mora base | T4: factor h->12 | U4: proy mediana | V4: n visible IBK | W4: PD cal NUEVA visible | X4: mora 12m visible | Y4: EC vigente | Z4: EC NUEVA | AA4: EC NUEVA vs proy | AB4: EC NUEVA visible
A5: 202303 | B5: 10958 | C5: 0.13758316 | D5: 0.17329097 | E5: 0.15717006 | F5: 0.0073918598 | G5: 0.025734623 | H5: 0.042160978 | I5: 0.056397153 | J5: 0.069812009 | K5: 0.082040518 | L5: 0.093173937 | M5: 0.10403358 | N5: 0.11416317 | O5: 0.12474904 | P5: 0.23130779 | Q5: 8.6661549 | R5: 12 | S5: 0.12474904 | T5: 1 | U5: 0.12474904 | V5: 3883 | W5: 0.16216752 | X5: 0.14730878 | Y5: =IFERROR(D5/O5-1,"") | Z5: =IFERROR(E5/O5-1,"") | AA5: =IFERROR(E5/U5-1,"") | AB5: =IFERROR(W5/X5-1,"")
A6: 202304 | B6: 12457 | C6: 0.13950291 | D6: 0.17563376 | E6: 0.15952385 | F6: 0.0045757405 | G6: 0.024564502 | H6: 0.041181665 | I6: 0.057397447 | J6: 0.072248535 | K6: 0.086617966 | L6: 0.098097455 | M6: 0.10957694 | N6: 0.12113671 | O6: 0.13301758 | P6: 0.20398831 | Q6: 8.0421126 | R6: 12 | S6: 0.13301758 | T6: 1 | U6: 0.13301758 | V6: 4636 | W6: 0.16493015 | X6: 0.15293356 | Y6: =IFERROR(D6/O6-1,"") | Z6: =IFERROR(E6/O6-1,"") | AA6: =IFERROR(E6/U6-1,"") | AB6: =IFERROR(W6/X6-1,"")
A7: 202305 | B7: 10971 | C7: 0.13955877 | D7: 0.17559781 | E7: 0.15925281 | F7: 0.0065627564 | G7: 0.025704129 | H7: 0.04366056 | I7: 0.059611704 | J7: 0.072737216 | K7: 0.085953878 | L7: 0.097165254 | M7: 0.10755628 | N7: 0.11986145 | O7: 0.13161972 | P7: 0.20154202 | Q7: 7.9862335 | R7: 12 | S7: 0.13161972 | T7: 1 | U7: 0.13161972 | V7: 4027 | W7: 0.16286789 | X7: 0.14998758 | Y7: =IFERROR(D7/O7-1,"") | Z7: =IFERROR(E7/O7-1,"") | AA7: =IFERROR(E7/U7-1,"") | AB7: =IFERROR(W7/X7-1,"")
A8: 202306 | B8: 7877 | C8: 0.13714953 | D8: 0.1723776 | E8: 0.15587209 | F8: 0.0063475943 | G8: 0.02158182 | H8: 0.035927384 | I8: 0.049638187 | J8: 0.062714231 | K8: 0.071727815 | L8: 0.083407389 | M8: 0.094833058 | N8: 0.10600482 | O8: 0.11539926 | P8: 0.14563116 | Q8: 6.7090957 | R8: 12 | S8: 0.11539926 | T8: 1 | U8: 0.11539926 | V8: 3019 | W8: 0.16055038 | X8: 0.13381915 | Y8: =IFERROR(D8/O8-1,"") | Z8: =IFERROR(E8/O8-1,"") | AA8: =IFERROR(E8/U8-1,"") | AB8: =IFERROR(W8/X8-1,"")
A9: 202307 | B9: 6313 | C9: 0.13631151 | D9: 0.13903373 | E9: 0.15256697 | F9: 0.0045936955 | G9: 0.023126881 | H9: 0.038016791 | I9: 0.049263425 | J9: 0.058767622 | K9: 0.071281483 | L9: 0.08411215 | M9: 0.096309203 | N9: 0.10771424 | O9: 0.11975289 | P9: 0.11544766 | Q9: 6.0196325 | R9: 12 | S9: 0.11975289 | T9: 1 | U9: 0.11975289 | V9: 2463 | W9: 0.15776695 | X9: 0.13885505 | Y9: =IFERROR(D9/O9-1,"") | Z9: =IFERROR(E9/O9-1,"") | AA9: =IFERROR(E9/U9-1,"") | AB9: =IFERROR(W9/X9-1,"")
A10: 202308 | B10: 6452 | C10: 0.13289145 | D10: 0.13562854 | E10: 0.14894763 | F10: 0.0058896466 | G10: 0.022008679 | H10: 0.038127712 | I10: 0.048822071 | J10: 0.063236206 | K10: 0.073620583 | L10: 0.087724737 | M10: 0.097954123 | N10: 0.10802852 | O10: 0.11732796 | P10: 0.10524205 | Q10: 5.7865118 | R10: 12 | S10: 0.11732796 | T10: 1 | U10: 0.11732796 | V10: 2439 | W10: 0.15010411 | X10: 0.13735137 | Y10: =IFERROR(D10/O10-1,"") | Z10: =IFERROR(E10/O10-1,"") | AA10: =IFERROR(E10/U10-1,"") | AB10: =IFERROR(W10/X10-1,"")
A11: 202309 | B11: 6294 | C11: 0.13194179 | D11: 0.12668506 | E11: 0.14393371 | F11: 0.0039720369 | G11: 0.019224658 | H11: 0.031140769 | I11: 0.044645694 | J11: 0.056720686 | K11: 0.069431204 | L11: 0.079917382 | M11: 0.0883381 | N11: 0.096758818 | O11: 0.10533842 | P11: 0.082642878 | Q11: 5.2702928 | R11: 12 | S11: 0.10533842 | T11: 1 | U11: 0.10533842 | V11: 2360 | W11: 0.14920522 | X11: 0.11779661 | Y11: =IFERROR(D11/O11-1,"") | Z11: =IFERROR(E11/O11-1,"") | AA11: =IFERROR(E11/U11-1,"") | AB11: =IFERROR(W11/X11-1,"")
A12: 202310 | B12: 6796 | C12: 0.13135571 | D12: 0.13317713 | E12: 0.13668757 | F12: 0.0039729253 | G12: 0.017068864 | H12: 0.030753384 | I12: 0.043260742 | J12: 0.055620954 | K12: 0.067392584 | L12: 0.078134197 | M12: 0.087551501 | N12: 0.094761624 | O12: 0.10094173 | P12: 0.049681202 | Q12: 4.5173693 | R12: 12 | S12: 0.10094173 | T12: 1 | U12: 0.10094173 | V12: 2432 | W12: 0.14032809 | X12: 0.12171053 | Y12: =IFERROR(D12/O12-1,"") | Z12: =IFERROR(E12/O12-1,"") | AA12: =IFERROR(E12/U12-1,"") | AB12: =IFERROR(W12/X12-1,"")
A13: 202311 | B13: 6764 | C13: 0.13247567 | D13: 0.13479585 | E13: 0.13174438 | F13: 0.0036960378 | G13: 0.017740982 | H13: 0.030751035 | I13: 0.043021881 | J13: 0.055736251 | K13: 0.067563572 | L13: 0.075547014 | M13: 0.082939089 | N13: 0.090922531 | O13: 0.097871082 | P13: 0.017692212 | Q13: 3.7866642 | R13: 12 | S13: 0.097871082 | T13: 1 | U13: 0.097871082 | V13: 2457 | W13: 0.13432456 | X13: 0.12006512 | Y13: =IFERROR(D13/O13-1,"") | Z13: =IFERROR(E13/O13-1,"") | AA13: =IFERROR(E13/U13-1,"") | AB13: =IFERROR(W13/X13-1,"")
A14: 202312 | B14: 6870 | C14: 0.13649716 | D14: 0.13887673 | E14: 0.13284491 | F14: 0.0049490539 | G14: 0.022416303 | H14: 0.03580786 | I14: 0.048471616 | J14: 0.06069869 | K14: 0.071615721 | L14: 0.079184862 | M14: 0.089956332 | N14: 0.099272198 | O14: 0.10829694 | P14: 0.0012463847 | Q14: 3.4110022 | R14: 12 | S14: 0.10829694 | T14: 1 | U14: 0.10829694 | V14: 2501 | W14: 0.13781897 | X14: 0.12754898 | Y14: =IFERROR(D14/O14-1,"") | Z14: =IFERROR(E14/O14-1,"") | AA14: =IFERROR(E14/U14-1,"") | AB14: =IFERROR(W14/X14-1,"")
A15: 202401 | B15: 8014 | C15: 0.13765552 | D15: 0.13221134 | E15: 0.13035155 | F15: 0.0052408286 | G15: 0.023334165 | H15: 0.039181432 | I15: 0.053406539 | J15: 0.063888196 | K15: 0.074245071 | L15: 0.083229349 | M15: 0.091589718 | N15: 0.098702271 | O15: 0.1053157 | P15: -0.019064283 | Q15: 2.947058 | R15: 12 | S15: 0.1053157 | T15: 1 | U15: 0.1053157 | V15: 2905 | W15: 0.13616302 | X15: 0.13080895 | Y15: =IFERROR(D15/O15-1,"") | Z15: =IFERROR(E15/O15-1,"") | AA15: =IFERROR(E15/U15-1,"") | AB15: =IFERROR(W15/X15-1,"")
A16: 202402 | B16: 8096 | C16: 0.136895 | D16: 0.13144211 | E16: 0.12926146 | F16: 0.006916996 | G16: 0.024456522 | H16: 0.040637352 | I16: 0.050024704 | J16: 0.061264822 | K16: 0.07312253 | L16: 0.082139328 | M16: 0.090909091 | N16: 0.099061265 | O16: 0.10820158 | P16: -0.019828668 | Q16: 2.9295976 | R16: 12 | S16: 0.10820158 | T16: 1 | U16: 0.10820158 | V16: 3028 | W16: 0.13389944 | X16: 0.12879789 | Y16: =IFERROR(D16/O16-1,"") | Z16: =IFERROR(E16/O16-1,"") | AA16: =IFERROR(E16/U16-1,"") | AB16: =IFERROR(W16/X16-1,"")
... A32: 202506 | B32: 15852 | C32: 0.16979372 | D32: 0.16339207 | E32: 0.1521794 | F32: 0.0062452687 | G32: 0.02882917 | H32: 0.049899066 | I32: 0.065922281 | J32: 0.078728236 | K32: 0.089515519 | L32: 0.10074439 | M32: 0.111784 | N32: 0.12257128 | O32: 0.13241231 | P32: -0.073765695 | Q32: 1.697547 | R32: 12 | S32: 0.13241231 | T32: 1 | U32: 0.13241231 | V32: 6575 | W32: 0.15709364 | X32: 0.14980989 | Y32: =IFERROR(D32/O32-1,"") | Z32: =IFERROR(E32/O32-1,"") | AA32: =IFERROR(E32/U32-1,"") | AB32: =IFERROR(W32/X32-1,"")
A33: 202507 | B33: 15111 | C33: 0.17394421 | D33: 0.1674756 | E33: 0.15615466 | F33: 0.0064191648 | G33: 0.029911985 | H33: 0.04870624 | I33: 0.060948978 | J33: 0.072728476 | K33: 0.085103567 | L33: 0.096684534 | M33: 0.10766991 | N33: 0.11753028 | P33: -0.073640896 | Q33: 1.7003977 | R33: 11 | S33: 0.11753028 | T33: 1.0815362 | U33: 0.12711325 | V33: 6429 | W33: 0.16563163 | Y33: =IFERROR(D33/O33-1,"") | Z33: =IFERROR(E33/O33-1,"") | AA33: =IFERROR(E33/U33-1,"") | AB33: =IFERROR(W33/X33-1,"")
A34: 202508 | B34: 15261 | C34: 0.18548574 | D34: 0.17874018 | E34: 0.16554563 | F34: 0.0075355481 | G34: 0.036301684 | H34: 0.055238844 | I34: 0.071096258 | J34: 0.085381037 | K34: 0.10005897 | L34: 0.11401612 | M34: 0.12803879 | P34: -0.10033144 | Q34: 1.0907218 | R34: 10 | S34: 0.12803879 | T34: 1.1841568 | U34: 0.15161801 | V34: 6618 | W34: 0.17803646 | Y34: =IFERROR(D34/O34-1,"") | Z34: =IFERROR(E34/O34-1,"") | AA34: =IFERROR(E34/U34-1,"") | AB34: =IFERROR(W34/X34-1,"")
A35: 202509 | B35: 16147 | C35: 0.18554313 | D35: 0.17882396 | E35: 0.16587112 | F35: 0.0096612374 | G35: 0.039016536 | H35: 0.059267975 | I35: 0.078528519 | J35: 0.095497616 | K35: 0.11011333 | L35: 0.12367622 | P35: -0.094338164 | Q35: 1.2276226 | R35: 9 | S35: 0.12367622 | T35: 1.311355 | U35: 0.16218344 | V35: 6775 | W35: 0.17882633 | Y35: =IFERROR(D35/O35-1,"") | Z35: =IFERROR(E35/O35-1,"") | AA35: =IFERROR(E35/U35-1,"") | AB35: =IFERROR(W35/X35-1,"")
A36: 202510 | B36: 17843 | C36: 0.19104545 | D36: 0.18416971 | E36: 0.17110643 | F36: 0.0096396346 | G36: 0.040295914 | H36: 0.067029087 | I36: 0.087709466 | J36: 0.1042986 | K36: 0.12015917 | P36: -0.097186463 | Q36: 1.1625606 | R36: 8 | S36: 0.12015917 | T36: 1.4800073 | U36: 0.17783644 | V36: 7516 | W36: 0.185211 | Y36: =IFERROR(D36/O36-1,"") | Z36: =IFERROR(E36/O36-1,"") | AA36: =IFERROR(E36/U36-1,"") | AB36: =IFERROR(W36/X36-1,"")
A37: 202511 | B37: 17413 | C37: 0.19120623 | D37: 0.18428048 | E37: 0.17099809 | F37: 0.010624246 | G37: 0.052948946 | H37: 0.080973985 | I37: 0.1008442 | J37: 0.11870442 | P37: -0.095195045 | Q37: 1.2080494 | R37: 7 | S37: 0.11870442 | T37: 1.7273307 | U37: 0.20504178 | V37: 7360 | W37: 0.18529126 | Y37: =IFERROR(D37/O37-1,"") | Z37: =IFERROR(E37/O37-1,"") | AA37: =IFERROR(E37/U37-1,"") | AB37: =IFERROR(W37/X37-1,"")
A38: 202512 | B38: 16530 | C38: 0.18706062 | D38: 0.18025663 | E38: 0.16709265 | F38: 0.011010284 | G38: 0.047065941 | H38: 0.072655777 | I38: 0.092014519 | P38: -0.090738963 | Q38: 1.3098369 | R38: 6 | S38: 0.092014519 | T38: 2.1282253 | U38: 0.19582763 | V38: 6936 | W38: 0.18199241 | Y38: =IFERROR(D38/O38-1,"") | Z38: =IFERROR(E38/O38-1,"") | AA38: =IFERROR(E38/U38-1,"") | AB38: =IFERROR(W38/X38-1,"")
A39: 202601 | B39: 15788 | C39: 0.18260164 | D39: 0.17591394 | E39: 0.16261574 | F39: 0.0088674943 | G39: 0.043957436 | H39: 0.069736509 | P39: -0.082751237 | Q39: 1.4922957 | R39: 5 | S39: 0.069736509 | T39: 2.869834 | U39: 0.2001322 | V39: 6592 | W39: 0.17301316 | Y39: =IFERROR(D39/O39-1,"") | Z39: =IFERROR(E39/O39-1,"") | AA39: =IFERROR(E39/U39-1,"") | AB39: =IFERROR(W39/X39-1,"")
A40: 202602 | B40: 14754 | C40: 0.18278896 | D40: 0.17607779 | E40: 0.1733085 | F40: 0.013148977 | G40: 0.047783652 | P40: -0.037038893 | Q40: 2.5364749 | R40: 4 | S40: 0.047783652 | T40: 4.9068398 | U40: 0.23446672 | V40: 6094 | W40: 0.18604232 | Y40: =IFERROR(D40/O40-1,"") | Z40: =IFERROR(E40/O40-1,"") | AA40: =IFERROR(E40/U40-1,"") | AB40: =IFERROR(W40/X40-1,"")
A41: 202603 | B41: 16591 | C41: 0.17979271 | D41: 0.17323458 | E41: 0.18230837 | F41: 0.010969803 | P41: 0.014389803 | Q41: 3.7112293 | R41: 3 | S41: 0.010969803 | T41: 20.738992 | U41: 0.22750265 | V41: 6949 | W41: 0.19635231 | Y41: =IFERROR(D41/O41-1,"") | Z41: =IFERROR(E41/O41-1,"") | AA41: =IFERROR(E41/U41-1,"") | AB41: =IFERROR(W41/X41-1,"")
A42: 202604 | B42: 15347 | C42: 0.17626035 | D42: 0.16726987 | E42: 0.18060665 | P42: 0.024185191 | Q42: 3.9349794 | V42: 6441 | W42: 0.1899772 | Y42: =IFERROR(D42/O42-1,"") | Z42: =IFERROR(E42/O42-1,"") | AA42: =IFERROR(E42/U42-1,"") | AB42: =IFERROR(W42/X42-1,"")
A43: 202605 | B43: 16743 | C43: 0.17656014 | D43: 0.16765771 | E43: 0.17977686 | P43: 0.019247124 | Q43: 3.8221822 | V43: 6989 | W43: 0.19007518 | Y43: =IFERROR(D43/O43-1,"") | Z43: =IFERROR(E43/O43-1,"") | AA43: =IFERROR(E43/U43-1,"") | AB43: =IFERROR(W43/X43-1,"")

Sheet SISTEMA_5
A1: SISTEMA 5
A2: Las cinco entidades del alcance, Interbank incluido
A4: codmes | B4: n | C4: PD sin calibrar | D4: PD cal vigente | E4: PD cal NUEVA | F4: mora 3m | G4: mora 4m | H4: mora 5m | I4: mora 6m | J4: mora 7m | K4: mora 8m | L4: mora 9m | M4: mora 10m | N4: mora 11m | O4: mora 12m | P4: ft ciclo | Q4: inflacion % | R4: madurez | S4: mora base | T4: factor h->12 | U4: proy mediana | V4: n visible IBK | W4: PD cal NUEVA visible | X4: mora 12m visible | Y4: EC vigente | Z4: EC NUEVA | AA4: EC NUEVA vs proy | AB4: EC NUEVA visible
A5: 202303 | B5: 25592 | C5: 0.13169266 | D5: 0.16603796 | E5: 0.14761132 | F5: 0.0071115974 | G5: 0.025085964 | H5: 0.038801188 | I5: 0.051852141 | J5: 0.065059394 | K5: 0.078696468 | L5: 0.08991091 | M5: 0.099874961 | N5: 0.10843232 | O5: 0.11730228 | P5: 0.23130779 | Q5: 8.6661549 | R5: 12 | S5: 0.11730228 | T5: 1 | U5: 0.11730228 | V5: 13177 | W5: 0.14379877 | X5: 0.13880246 | Y5: =IFERROR(D5/O5-1,"") | Z5: =IFERROR(E5/O5-1,"") | AA5: =IFERROR(E5/U5-1,"") | AB5: =IFERROR(W5/X5-1,"")
A6: 202304 | B6: 26520 | C6: 0.1320401 | D6: 0.166408 | E6: 0.14786582 | F6: 0.0047134238 | G6: 0.021078431 | H6: 0.034841629 | I6: 0.048944193 | J6: 0.062330317 | K6: 0.07515083 | L6: 0.086651584 | M6: 0.096568627 | N6: 0.1061463 | O6: 0.11546003 | P6: 0.20398831 | Q6: 8.0421126 | R6: 12 | S6: 0.11546003 | T6: 1 | U6: 0.11546003 | V6: 13384 | W6: 0.14159816 | X6: 0.1315003 | Y6: =IFERROR(D6/O6-1,"") | Z6: =IFERROR(E6/O6-1,"") | AA6: =IFERROR(E6/U6-1,"") | AB6: =IFERROR(W6/X6-1,"")
A7: 202305 | B7: 23566 | C7: 0.12932012 | D7: 0.16299544 | E7: 0.14377459 | F7: 0.0063226683 | G7: 0.024696597 | H7: 0.040736655 | I7: 0.05495205 | J7: 0.067470084 | K7: 0.081133837 | L7: 0.092251549 | M7: 0.10260545 | N7: 0.1122804 | O7: 0.12080964 | P7: 0.20154202 | Q7: 7.9862335 | R7: 12 | S7: 0.12080964 | T7: 1 | U7: 0.12080964 | V7: 12897 | W7: 0.13693668 | X7: 0.13941227 | Y7: =IFERROR(D7/O7-1,"") | Z7: =IFERROR(E7/O7-1,"") | AA7: =IFERROR(E7/U7-1,"") | AB7: =IFERROR(W7/X7-1,"")
A8: 202306 | B8: 17557 | C8: 0.12527749 | D8: 0.15783692 | E8: 0.13849255 | F8: 0.0064361793 | G8: 0.020504642 | H8: 0.034687019 | I8: 0.047046762 | J8: 0.057982571 | K8: 0.068348807 | L8: 0.078202426 | M8: 0.086859942 | N8: 0.095916159 | O8: 0.10309278 | P8: 0.14563116 | Q8: 6.7090957 | R8: 12 | S8: 0.10309278 | T8: 1 | U8: 0.10309278 | V8: 9471 | W8: 0.13074033 | X8: 0.12057861 | Y8: =IFERROR(D8/O8-1,"") | Z8: =IFERROR(E8/O8-1,"") | AA8: =IFERROR(E8/U8-1,"") | AB8: =IFERROR(W8/X8-1,"")
A9: 202307 | B9: 14094 | C9: 0.12075114 | D9: 0.12333648 | E9: 0.13138726 | F9: 0.0034057046 | G9: 0.015822336 | H9: 0.025117071 | I9: 0.033773237 | J9: 0.04136512 | K9: 0.050517951 | L9: 0.059316021 | M9: 0.06775933 | N9: 0.075989783 | O9: 0.08436214 | P9: 0.11544766 | Q9: 6.0196325 | R9: 12 | S9: 0.08436214 | T9: 1 | U9: 0.08436214 | V9: 7211 | W9: 0.12110186 | X9: 0.09124948 | Y9: =IFERROR(D9/O9-1,"") | Z9: =IFERROR(E9/O9-1,"") | AA9: =IFERROR(E9/U9-1,"") | AB9: =IFERROR(W9/X9-1,"")
A10: 202308 | B10: 16271 | C10: 0.12169245 | D10: 0.12442684 | E10: 0.13254666 | F10: 0.0041177555 | G10: 0.015180382 | H10: 0.025751337 | I10: 0.033372257 | J10: 0.043574458 | K10: 0.052055805 | L10: 0.061581956 | M10: 0.069264335 | N10: 0.076455043 | O10: 0.082478028 | P10: 0.10524205 | Q10: 5.7865118 | R10: 12 | S10: 0.082478028 | T10: 1 | U10: 0.082478028 | V10: 8434 | W10: 0.12040813 | X10: 0.090230021 | Y10: =IFERROR(D10/O10-1,"") | Z10: =IFERROR(E10/O10-1,"") | AA10: =IFERROR(E10/U10-1,"") | AB10: =IFERROR(W10/X10-1,"")
A11: 202309 | B11: 13798 | C11: 0.12068461 | D11: 0.11568668 | E11: 0.12861132 | F11: 0.003478765 | G11: 0.015074648 | H11: 0.023554138 | I11: 0.033410639 | J11: 0.041672706 | K11: 0.051529207 | L11: 0.059428903 | M11: 0.06566169 | N11: 0.071314683 | O11: 0.077982316 | P11: 0.082642878 | Q11: 5.2702928 | R11: 12 | S11: 0.077982316 | T11: 1 | U11: 0.077982316 | V11: 6693 | W11: 0.11869097 | X11: 0.084565964 | Y11: =IFERROR(D11/O11-1,"") | Z11: =IFERROR(E11/O11-1,"") | AA11: =IFERROR(E11/U11-1,"") | AB11: =IFERROR(W11/X11-1,"")
A12: 202310 | B12: 14300 | C12: 0.12121334 | D12: 0.1228169 | E12: 0.12326057 | F12: 0.0032867133 | G12: 0.012447552 | H12: 0.022797203 | I12: 0.031398601 | J12: 0.03993007 | K12: 0.047692308 | L12: 0.055454545 | M12: 0.062167832 | N12: 0.068041958 | O12: 0.073006993 | P12: 0.049681202 | Q12: 4.5173693 | R12: 12 | S12: 0.073006993 | T12: 1 | U12: 0.073006993 | V12: 6612 | W12: 0.11313065 | X12: 0.083787054 | Y12: =IFERROR(D12/O12-1,"") | Z12: =IFERROR(E12/O12-1,"") | AA12: =IFERROR(E12/U12-1,"") | AB12: =IFERROR(W12/X12-1,"")
A13: 202311 | B13: 15264 | C13: 0.1276704 | D13: 0.12982333 | E13: 0.12494937 | F13: 0.0032756813 | G13: 0.015592243 | H13: 0.027712264 | I13: 0.037015199 | J13: 0.046514675 | K13: 0.056145178 | L13: 0.061975891 | M13: 0.068592767 | N13: 0.074947589 | O13: 0.081695493 | P13: 0.017692212 | Q13: 3.7866642 | R13: 12 | S13: 0.081695493 | T13: 1 | U13: 0.081695493 | V13: 7160 | W13: 0.12338136 | X13: 0.10139665 | Y13: =IFERROR(D13/O13-1,"") | Z13: =IFERROR(E13/O13-1,"") | AA13: =IFERROR(E13/U13-1,"") | AB13: =IFERROR(W13/X13-1,"")
A14: 202312 | B14: 15508 | C14: 0.13350741 | D14: 0.13563645 | E14: 0.12796244 | F14: 0.005481042 | G14: 0.021537271 | H14: 0.035207635 | I14: 0.047201444 | J14: 0.057260769 | K14: 0.065772505 | L14: 0.072543204 | M14: 0.080474594 | N14: 0.089373227 | O14: 0.096659788 | P14: 0.0012463847 | Q14: 3.4110022 | R14: 12 | S14: 0.096659788 | T14: 1 | U14: 0.096659788 | V14: 7438 | W14: 0.12892164 | X14: 0.11763915 | Y14: =IFERROR(D14/O14-1,"") | Z14: =IFERROR(E14/O14-1,"") | AA14: =IFERROR(E14/U14-1,"") | AB14: =IFERROR(W14/X14-1,"")
A15: 202401 | B15: 18530 | C15: 0.1293426 | D15: 0.12374103 | E15: 0.11969127 | F15: 0.0048030221 | G15: 0.020237453 | H15: 0.032379924 | I15: 0.042849433 | J15: 0.049433351 | K15: 0.056556935 | L15: 0.06303292 | M15: 0.070642202 | N15: 0.076092822 | O15: 0.081813276 | P15: -0.019064283 | Q15: 2.947058 | R15: 12 | S15: 0.081813276 | T15: 1 | U15: 0.081813276 | V15: 8799 | W15: 0.11727062 | X15: 0.10035231 | Y15: =IFERROR(D15/O15-1,"") | Z15: =IFERROR(E15/O15-1,"") | AA15: =IFERROR(E15/U15-1,"") | AB15: =IFERROR(W15/X15-1,"")
A16: 202402 | B16: 18181 | C16: 0.13062127 | D16: 0.12497362 | E16: 0.12088394 | F16: 0.0061602772 | G16: 0.021395963 | H16: 0.033276497 | I16: 0.040536824 | J16: 0.048952203 | K16: 0.057202574 | L16: 0.064627908 | M16: 0.072163247 | N16: 0.079478577 | O16: 0.086683901 | P16: -0.019828668 | Q16: 2.9295976 | R16: 12 | S16: 0.086683901 | T16: 1 | U16: 0.086683901 | V16: 8818 | W16: 0.11873546 | X16: 0.10535269 | Y16: =IFERROR(D16/O16-1,"") | Z16: =IFERROR(E16/O16-1,"") | AA16: =IFERROR(E16/U16-1,"") | AB16: =IFERROR(W16/X16-1,"")
... A32: 202506 | B32: 23960 | C32: 0.15065854 | D32: 0.14479134 | E32: 0.13218808 | F32: 0.0045075125 | G32: 0.020742905 | H32: 0.0360601 | I32: 0.048038397 | J32: 0.058222037 | K32: 0.066652755 | L32: 0.075083472 | M32: 0.083806344 | N32: 0.091903172 | O32: 0.099499165 | P32: -0.073765695 | Q32: 1.697547 | R32: 12 | S32: 0.099499165 | T32: 1 | U32: 0.099499165 | V32: 10814 | W32: 0.12800116 | X32: 0.10662105 | Y32: =IFERROR(D32/O32-1,"") | Z32: =IFERROR(E32/O32-1,"") | AA32: =IFERROR(E32/U32-1,"") | AB32: =IFERROR(W32/X32-1,"")
A33: 202507 | B33: 24008 | C33: 0.15099687 | D33: 0.14515709 | E33: 0.13221111 | F33: 0.0047484172 | G33: 0.021117961 | H33: 0.034863379 | I33: 0.043902033 | J33: 0.052607464 | K33: 0.06152116 | L33: 0.070393202 | M33: 0.07889037 | N33: 0.08667944 | P33: -0.073640896 | Q33: 1.7003977 | R33: 11 | S33: 0.08667944 | T33: 1.0844833 | U33: 0.094002406 | V33: 11322 | W33: 0.12971798 | Y33: =IFERROR(D33/O33-1,"") | Z33: =IFERROR(E33/O33-1,"") | AA33: =IFERROR(E33/U33-1,"") | AB33: =IFERROR(W33/X33-1,"")
A34: 202508 | B34: 23694 | C34: 0.15888867 | D34: 0.15282451 | E34: 0.13826992 | F34: 0.005697645 | G34: 0.026335781 | H34: 0.040221153 | I34: 0.052038491 | J34: 0.062463071 | K34: 0.073351903 | L34: 0.084198531 | M34: 0.094918545 | P34: -0.10033144 | Q34: 1.0907218 | R34: 10 | S34: 0.094918545 | T34: 1.1904662 | U34: 0.11299732 | V34: 11366 | W34: 0.13651927 | Y34: =IFERROR(D34/O34-1,"") | Z34: =IFERROR(E34/O34-1,"") | AA34: =IFERROR(E34/U34-1,"") | AB34: =IFERROR(W34/X34-1,"")
A35: 202509 | B35: 26530 | C35: 0.16011742 | D35: 0.15404583 | E35: 0.13983426 | F35: 0.006784772 | G35: 0.026498304 | H35: 0.040595552 | I35: 0.053863551 | J35: 0.065548436 | K35: 0.075725594 | L35: 0.085751979 | P35: -0.094338164 | Q35: 1.2276226 | R35: 9 | S35: 0.085751979 | T35: 1.3256681 | U35: 0.11367866 | V35: 12273 | W35: 0.13843475 | Y35: =IFERROR(D35/O35-1,"") | Z35: =IFERROR(E35/O35-1,"") | AA35: =IFERROR(E35/U35-1,"") | AB35: =IFERROR(W35/X35-1,"")
A36: 202510 | B36: 28391 | C36: 0.16454691 | D36: 0.15834269 | E36: 0.14411816 | F36: 0.0066922616 | G36: 0.028248389 | H36: 0.046634497 | I36: 0.061040471 | J36: 0.073121764 | K36: 0.0849565 | P36: -0.097186463 | Q36: 1.1625606 | R36: 8 | S36: 0.0849565 | T36: 1.5067714 | U36: 0.12801002 | V36: 13062 | W36: 0.14302734 | Y36: =IFERROR(D36/O36-1,"") | Z36: =IFERROR(E36/O36-1,"") | AA36: =IFERROR(E36/U36-1,"") | AB36: =IFERROR(W36/X36-1,"")
A37: 202511 | B37: 28418 | C37: 0.16528841 | D37: 0.15905589 | E37: 0.1446941 | F37: 0.0071785488 | G37: 0.035400099 | H37: 0.054648462 | I37: 0.069181505 | J37: 0.081708776 | P37: -0.095195045 | Q37: 1.2080494 | R37: 7 | S37: 0.081708776 | T37: 1.7742341 | U37: 0.14497049 | V37: 13126 | W37: 0.14415849 | Y37: =IFERROR(D37/O37-1,"") | Z37: =IFERROR(E37/O37-1,"") | AA37: =IFERROR(E37/U37-1,"") | AB37: =IFERROR(W37/X37-1,"")
A38: 202512 | B38: 28456 | C38: 0.16097165 | D38: 0.15484174 | E38: 0.14054649 | F38: 0.0073446725 | G38: 0.030714085 | H38: 0.04842564 | I38: 0.062025583 | P38: -0.090738963 | Q38: 1.3098369 | R38: 6 | S38: 0.062025583 | T38: 2.1958024 | U38: 0.13619592 | V38: 13086 | W38: 0.14009101 | Y38: =IFERROR(D38/O38-1,"") | Z38: =IFERROR(E38/O38-1,"") | AA38: =IFERROR(E38/U38-1,"") | AB38: =IFERROR(W38/X38-1,"")
A39: 202601 | B39: 30471 | C39: 0.15487066 | D39: 0.14890211 | E39: 0.13433261 | F39: 0.0060713465 | G39: 0.028190739 | H39: 0.04482951 | P39: -0.082751237 | Q39: 1.4922957 | R39: 5 | S39: 0.04482951 | T39: 2.9597765 | U39: 0.13268533 | V39: 14237 | W39: 0.1304326 | Y39: =IFERROR(D39/O39-1,"") | Z39: =IFERROR(E39/O39-1,"") | AA39: =IFERROR(E39/U39-1,"") | AB39: =IFERROR(W39/X39-1,"")
A40: 202602 | B40: 28574 | C40: 0.15820145 | D40: 0.15213646 | E40: 0.14694738 | F40: 0.0092041716 | G40: 0.031427172 | P40: -0.037038893 | Q40: 2.5364749 | R40: 4 | S40: 0.031427172 | T40: 4.9644601 | U40: 0.15601894 | V40: 13291 | W40: 0.14380476 | Y40: =IFERROR(D40/O40-1,"") | Z40: =IFERROR(E40/O40-1,"") | AA40: =IFERROR(E40/U40-1,"") | AB40: =IFERROR(W40/X40-1,"")
A41: 202603 | B41: 31395 | C41: 0.15644956 | D41: 0.15045852 | E41: 0.15597589 | F41: 0.0071348941 | P41: 0.014389803 | Q41: 3.7112293 | R41: 3 | S41: 0.0071348941 | T41: 19.639243 | U41: 0.14012392 | V41: 14873 | W41: 0.1531821 | Y41: =IFERROR(D41/O41-1,"") | Z41: =IFERROR(E41/O41-1,"") | AA41: =IFERROR(E41/U41-1,"") | AB41: =IFERROR(W41/X41-1,"")
A42: 202604 | B42: 28736 | C42: 0.15423751 | D42: 0.14620319 | E42: 0.15563853 | P42: 0.024185191 | Q42: 3.9349794 | V42: 13688 | W42: 0.15039981 | Y42: =IFERROR(D42/O42-1,"") | Z42: =IFERROR(E42/O42-1,"") | AA42: =IFERROR(E42/U42-1,"") | AB42: =IFERROR(W42/X42-1,"")
A43: 202605 | B43: 30843 | C43: 0.15376467 | D43: 0.14566866 | E43: 0.1540495 | P43: 0.019247124 | Q43: 3.8221822 | V43: 14771 | W43: 0.14962332 | Y43: =IFERROR(D43/O43-1,"") | Z43: =IFERROR(E43/O43-1,"") | AA43: =IFERROR(E43/U43-1,"") | AB43: =IFERROR(W43/X43-1,"")

Sheet ENT_00001_BCP
A1: ENT 00001 BCP
A2: Entidad 00001 (BCP), poblacion clean
A4: codmes | B4: n | C4: PD sin calibrar | D4: PD cal vigente | E4: PD cal NUEVA | F4: mora 3m | G4: mora 4m | H4: mora 5m | I4: mora 6m | J4: mora 7m | K4: mora 8m | L4: mora 9m | M4: mora 10m | N4: mora 11m | O4: mora 12m | P4: ft ciclo | Q4: inflacion % | R4: madurez | S4: mora base | T4: factor h->12 | U4: proy mediana | V4: n visible IBK | W4: PD cal NUEVA visible | X4: mora 12m visible | Y4: EC vigente | Z4: EC NUEVA | AA4: EC NUEVA vs proy | AB4: EC NUEVA visible
A5: 202303 | B5: 7887 | C5: 0.13032899 | D5: 0.16478313 | E5: 0.14821421 | F5: 0.0026626094 | G5: 0.010396856 | H5: 0.01787752 | I5: 0.024090275 | J5: 0.031824521 | K5: 0.040573095 | L5: 0.048307341 | M5: 0.054012933 | N5: 0.060352479 | O5: 0.066692025 | P5: 0.23130779 | Q5: 8.6661549 | R5: 12 | S5: 0.066692025 | T5: 1 | U5: 0.066692025 | V5: 2889 | W5: 0.14566017 | X5: 0.073727934 | Y5: =IFERROR(D5/O5-1,"") | Z5: =IFERROR(E5/O5-1,"") | AA5: =IFERROR(E5/U5-1,"") | AB5: =IFERROR(W5/X5-1,"")
A6: 202304 | B6: 8121 | C6: 0.13370833 | D6: 0.168761 | E6: 0.15208011 | F6: 0.0012313754 | G6: 0.0065262899 | H6: 0.013668267 | I6: 0.02154907 | J6: 0.030661249 | K6: 0.037187538 | L6: 0.046053442 | M6: 0.051717769 | N6: 0.058244059 | O6: 0.065509174 | P6: 0.20398831 | Q6: 8.0421126 | R6: 12 | S6: 0.065509174 | T6: 1 | U6: 0.065509174 | V6: 3040 | W6: 0.15079327 | X6: 0.069407895 | Y6: =IFERROR(D6/O6-1,"") | Z6: =IFERROR(E6/O6-1,"") | AA6: =IFERROR(E6/U6-1,"") | AB6: =IFERROR(W6/X6-1,"")
A7: 202305 | B7: 5178 | C7: 0.12652202 | D7: 0.16010546 | E7: 0.1434558 | F7: 0.0013518733 | G7: 0.0054074932 | H7: 0.010235612 | I7: 0.015063731 | J7: 0.018733102 | K7: 0.024140595 | L7: 0.02838934 | M7: 0.034183082 | N7: 0.040363075 | O7: 0.044998069 | P7: 0.20154202 | Q7: 7.9862335 | R7: 12 | S7: 0.044998069 | T7: 1 | U7: 0.044998069 | V7: 1800 | W7: 0.14135861 | X7: 0.045 | Y7: =IFERROR(D7/O7-1,"") | Z7: =IFERROR(E7/O7-1,"") | AA7: =IFERROR(E7/U7-1,"") | AB7: =IFERROR(W7/X7-1,"")
A8: 202306 | B8: 4444 | C8: 0.12435987 | D8: 0.15749754 | E8: 0.14044535 | F8: 0.00067506751 | G8: 0.0038253825 | H8: 0.0094509451 | I8: 0.013951395 | J8: 0.01890189 | K8: 0.023852385 | L8: 0.02790279 | M8: 0.032628263 | N8: 0.036678668 | O8: 0.04050405 | P8: 0.14563116 | Q8: 6.7090957 | R8: 12 | S8: 0.04050405 | T8: 1 | U8: 0.04050405 | V8: 1503 | W8: 0.1380277 | X8: 0.047904192 | Y8: =IFERROR(D8/O8-1,"") | Z8: =IFERROR(E8/O8-1,"") | AA8: =IFERROR(E8/U8-1,"") | AB8: =IFERROR(W8/X8-1,"")
A9: 202307 | B9: 4420 | C9: 0.1220474 | D9: 0.12447076 | E9: 0.13559285 | F9: 0 | G9: 0.0031674208 | H9: 0.0056561086 | I9: 0.0097285068 | J9: 0.013348416 | K9: 0.01719457 | L9: 0.02239819 | M9: 0.026696833 | N9: 0.031221719 | O9: 0.037782805 | P9: 0.11544766 | Q9: 6.0196325 | R9: 12 | S9: 0.037782805 | T9: 1 | U9: 0.037782805 | V9: 1615 | W9: 0.13659828 | X9: 0.048916409 | Y9: =IFERROR(D9/O9-1,"") | Z9: =IFERROR(E9/O9-1,"") | AA9: =IFERROR(E9/U9-1,"") | AB9: =IFERROR(W9/X9-1,"")
A10: 202308 | B10: 5542 | C10: 0.12886909 | D10: 0.13138835 | E10: 0.14408612 | F10: 0.0014435222 | G10: 0.005232768 | H10: 0.009202454 | I10: 0.0129917 | J10: 0.017502707 | K10: 0.023096355 | L10: 0.027066041 | M10: 0.03265969 | N10: 0.038794659 | O10: 0.041681703 | P10: 0.10524205 | Q10: 5.7865118 | R10: 12 | S10: 0.041681703 | T10: 1 | U10: 0.041681703 | V10: 1961 | W10: 0.14212383 | X10: 0.052014278 | Y10: =IFERROR(D10/O10-1,"") | Z10: =IFERROR(E10/O10-1,"") | AA10: =IFERROR(E10/U10-1,"") | AB10: =IFERROR(W10/X10-1,"")
A11: 202309 | B11: 4627 | C11: 0.12244857 | D11: 0.11769731 | E11: 0.13286165 | F11: 0.00086449103 | G11: 0.0049708234 | H11: 0.0099416469 | I11: 0.013831856 | J11: 0.01642533 | K11: 0.021396153 | L11: 0.026583099 | M11: 0.030689432 | N11: 0.032850659 | O11: 0.037173114 | P11: 0.082642878 | Q11: 5.2702928 | R11: 12 | S11: 0.037173114 | T11: 1 | U11: 0.037173114 | V11: 1657 | W11: 0.12740282 | X11: 0.042245021 | Y11: =IFERROR(D11/O11-1,"") | Z11: =IFERROR(E11/O11-1,"") | AA11: =IFERROR(E11/U11-1,"") | AB11: =IFERROR(W11/X11-1,"")
A12: 202310 | B12: 5030 | C12: 0.12048017 | D12: 0.1223542 | E12: 0.12400321 | F12: 0.00099403579 | G12: 0.0049701789 | H12: 0.0091451292 | I12: 0.012922465 | J12: 0.016302187 | K12: 0.019284294 | L12: 0.023658052 | M12: 0.028031809 | N12: 0.032405567 | O12: 0.036182903 | P12: 0.049681202 | Q12: 4.5173693 | R12: 12 | S12: 0.036182903 | T12: 1 | U12: 0.036182903 | V12: 1823 | W12: 0.1157829 | X12: 0.049917718 | Y12: =IFERROR(D12/O12-1,"") | Z12: =IFERROR(E12/O12-1,"") | AA12: =IFERROR(E12/U12-1,"") | AB12: =IFERROR(W12/X12-1,"")
A13: 202311 | B13: 5634 | C13: 0.12058503 | D13: 0.12277286 | E13: 0.1184391 | F13: 0.0017749379 | G13: 0.0035498758 | H13: 0.0090521832 | I13: 0.013489528 | J13: 0.01686191 | K13: 0.020766773 | L13: 0.024316649 | M13: 0.028753994 | N13: 0.032836351 | O13: 0.036741214 | P13: 0.017692212 | Q13: 3.7866642 | R13: 12 | S13: 0.036741214 | T13: 1 | U13: 0.036741214 | V13: 2046 | W13: 0.11415697 | X13: 0.045454545 | Y13: =IFERROR(D13/O13-1,"") | Z13: =IFERROR(E13/O13-1,"") | AA13: =IFERROR(E13/U13-1,"") | AB13: =IFERROR(W13/X13-1,"")
A14: 202312 | B14: 5262 | C14: 0.12404744 | D14: 0.12630419 | E14: 0.11935678 | F14: 0.00095020905 | G14: 0.0043709616 | H14: 0.0098821741 | I14: 0.017103763 | J14: 0.022995059 | K14: 0.026795895 | L14: 0.029646522 | M14: 0.033257317 | N14: 0.038768529 | O14: 0.04199924 | P14: 0.0012463847 | Q14: 3.4110022 | R14: 12 | S14: 0.04199924 | T14: 1 | U14: 0.04199924 | V14: 1878 | W14: 0.11232284 | X14: 0.045260916 | Y14: =IFERROR(D14/O14-1,"") | Z14: =IFERROR(E14/O14-1,"") | AA14: =IFERROR(E14/U14-1,"") | AB14: =IFERROR(W14/X14-1,"")
A15: 202401 | B15: 6497 | C15: 0.12124127 | D15: 0.11644189 | E15: 0.11266403 | F15: 0.0012313375 | G15: 0.0063106049 | H15: 0.0095428659 | I15: 0.013852547 | J15: 0.016315222 | K15: 0.018931815 | L15: 0.021702324 | M15: 0.024780668 | N15: 0.026935509 | O15: 0.030013853 | P15: -0.019064283 | Q15: 2.947058 | R15: 12 | S15: 0.030013853 | T15: 1 | U15: 0.030013853 | V15: 2295 | W15: 0.10647505 | X15: 0.037037037 | Y15: =IFERROR(D15/O15-1,"") | Z15: =IFERROR(E15/O15-1,"") | AA15: =IFERROR(E15/U15-1,"") | AB15: =IFERROR(W15/X15-1,"")
A16: 202402 | B16: 6169 | C16: 0.12295655 | D16: 0.11811904 | E16: 0.11430379 | F16: 0.0011347058 | G16: 0.0055114281 | H16: 0.0094018479 | I16: 0.01167126 | J16: 0.014913276 | K16: 0.017831091 | L16: 0.019938402 | M16: 0.021721511 | N16: 0.024639326 | O16: 0.028367645 | P16: -0.019828668 | Q16: 2.9295976 | R16: 12 | S16: 0.028367645 | T16: 1 | U16: 0.028367645 | V16: 2257 | W16: 0.10761298 | X16: 0.031014621 | Y16: =IFERROR(D16/O16-1,"") | Z16: =IFERROR(E16/O16-1,"") | AA16: =IFERROR(E16/U16-1,"") | AB16: =IFERROR(W16/X16-1,"")
... A32: 202506 | B32: 5849 | C32: 0.12229198 | D32: 0.11737597 | E32: 0.10422236 | F32: 0.00068387759 | G32: 0.0030774491 | H32: 0.0061548983 | I32: 0.009061378 | J32: 0.012822705 | K32: 0.015729184 | L32: 0.018464695 | M32: 0.021713113 | N32: 0.024448624 | O32: 0.027697042 | P32: -0.073765695 | Q32: 1.697547 | R32: 12 | S32: 0.027697042 | T32: 1 | U32: 0.027697042 | V32: 2254 | W32: 0.10072626 | X32: 0.029724933 | Y32: =IFERROR(D32/O32-1,"") | Z32: =IFERROR(E32/O32-1,"") | AA32: =IFERROR(E32/U32-1,"") | AB32: =IFERROR(W32/X32-1,"")
A33: 202507 | B33: 5805 | C33: 0.11863102 | D33: 0.11381947 | E33: 0.10051761 | F33: 0.00068906115 | G33: 0.0029285099 | H33: 0.0053402239 | I33: 0.0084409991 | J33: 0.010680448 | K33: 0.012919897 | L33: 0.015503876 | M33: 0.01791559 | N33: 0.021705426 | P33: -0.073640896 | Q33: 1.7003977 | R33: 11 | S33: 0.021705426 | T33: 1.120025 | U33: 0.02431062 | V33: 2188 | W33: 0.096682955 | Y33: =IFERROR(D33/O33-1,"") | Z33: =IFERROR(E33/O33-1,"") | AA33: =IFERROR(E33/U33-1,"") | AB33: =IFERROR(W33/X33-1,"")
A34: 202508 | B34: 5377 | C34: 0.11904968 | D34: 0.11422198 | E34: 0.099590889 | F34: 0.00055793193 | G34: 0.002975637 | H34: 0.0057652966 | I34: 0.008368979 | J34: 0.010972661 | K34: 0.013762321 | L34: 0.017667845 | M34: 0.020457504 | P34: -0.10033144 | Q34: 1.0907218 | R34: 10 | S34: 0.020457504 | T34: 1.2682927 | U34: 0.025946103 | V34: 2076 | W34: 0.093589735 | Y34: =IFERROR(D34/O34-1,"") | Z34: =IFERROR(E34/O34-1,"") | AA34: =IFERROR(E34/U34-1,"") | AB34: =IFERROR(W34/X34-1,"")
A35: 202509 | B35: 7247 | C35: 0.12992563 | D35: 0.12477238 | E35: 0.11065702 | F35: 0.0008279288 | G35: 0.0024837864 | H35: 0.0056575135 | I35: 0.0084172761 | J35: 0.011039051 | K35: 0.013108873 | L35: 0.018076445 | P35: -0.094338164 | Q35: 1.2276226 | R35: 9 | S35: 0.018076445 | T35: 1.4704918 | U35: 0.026581265 | V35: 2756 | W35: 0.10733392 | Y35: =IFERROR(D35/O35-1,"") | Z35: =IFERROR(E35/O35-1,"") | AA35: =IFERROR(E35/U35-1,"") | AB35: =IFERROR(W35/X35-1,"")
A36: 202510 | B36: 7321 | C36: 0.130887 | D36: 0.1256473 | E36: 0.11163274 | F36: 0.00068296681 | G36: 0.0039612075 | H36: 0.0071028548 | I36: 0.0099713154 | J36: 0.012566589 | K36: 0.016118017 | P36: -0.097186463 | Q36: 1.1625606 | R36: 8 | S36: 0.016118017 | T36: 1.7434402 | U36: 0.028100799 | V36: 2765 | W36: 0.10625556 | Y36: =IFERROR(D36/O36-1,"") | Z36: =IFERROR(E36/O36-1,"") | AA36: =IFERROR(E36/U36-1,"") | AB36: =IFERROR(W36/X36-1,"")
A37: 202511 | B37: 7989 | C37: 0.133813 | D37: 0.1285042 | E37: 0.11422666 | F37: 0.00087620478 | G37: 0.0035048191 | H37: 0.0071348104 | I37: 0.012016523 | J37: 0.014895481 | P37: -0.095195045 | Q37: 1.2080494 | R37: 7 | S37: 0.014895481 | T37: 2.1427292 | U37: 0.031916982 | V37: 3197 | W37: 0.10901216 | Y37: =IFERROR(D37/O37-1,"") | Z37: =IFERROR(E37/O37-1,"") | AA37: =IFERROR(E37/U37-1,"") | AB37: =IFERROR(W37/X37-1,"")
A38: 202512 | B38: 8641 | C38: 0.13306217 | D38: 0.1277708 | E38: 0.11375156 | F38: 0.00092581877 | G38: 0.003356093 | H38: 0.0089110057 | I38: 0.012151371 | P38: -0.090738963 | Q38: 1.3098369 | R38: 6 | S38: 0.012151371 | T38: 2.829653 | U38: 0.034384164 | V38: 3285 | W38: 0.10881255 | Y38: =IFERROR(D38/O38-1,"") | Z38: =IFERROR(E38/O38-1,"") | AA38: =IFERROR(E38/U38-1,"") | AB38: =IFERROR(W38/X38-1,"")
A39: 202601 | B39: 10769 | C39: 0.13496764 | D39: 0.12959237 | E39: 0.11539747 | F39: 0.0015786053 | G39: 0.0059429845 | H39: 0.010585941 | P39: -0.082751237 | Q39: 1.4922957 | R39: 5 | S39: 0.010585941 | T39: 4.0819113 | U39: 0.043210872 | V39: 4354 | W39: 0.11338046 | Y39: =IFERROR(D39/O39-1,"") | Z39: =IFERROR(E39/O39-1,"") | AA39: =IFERROR(E39/U39-1,"") | AB39: =IFERROR(W39/X39-1,"")
A40: 202602 | B40: 10156 | C40: 0.14384898 | D40: 0.13829259 | E40: 0.13303388 | F40: 0.0033477747 | G40: 0.010043324 | P40: -0.037038893 | Q40: 2.5364749 | R40: 4 | S40: 0.010043324 | T40: 7.6178344 | U40: 0.07650838 | V40: 4052 | W40: 0.13343751 | Y40: =IFERROR(D40/O40-1,"") | Z40: =IFERROR(E40/O40-1,"") | AA40: =IFERROR(E40/U40-1,"") | AB40: =IFERROR(W40/X40-1,"")
A41: 202603 | B41: 10535 | C41: 0.14169045 | D41: 0.13614082 | E41: 0.14114874 | F41: 0.0016136687 | P41: 0.014389803 | Q41: 3.7112293 | R41: 3 | S41: 0.0016136687 | T41: 33.697115 | U41: 0.054375981 | V41: 4301 | W41: 0.14042835 | Y41: =IFERROR(D41/O41-1,"") | Z41: =IFERROR(E41/O41-1,"") | AA41: =IFERROR(E41/U41-1,"") | AB41: =IFERROR(W41/X41-1,"")
A42: 202604 | B42: 9342 | C42: 0.13940311 | D42: 0.13217839 | E42: 0.14073629 | P42: 0.024185191 | Q42: 3.9349794 | V42: 3809 | W42: 0.13778649 | Y42: =IFERROR(D42/O42-1,"") | Z42: =IFERROR(E42/O42-1,"") | AA42: =IFERROR(E42/U42-1,"") | AB42: =IFERROR(W42/X42-1,"")
A43: 202605 | B43: 9164 | C43: 0.13642456 | D43: 0.12916301 | E43: 0.13639239 | P43: 0.019247124 | Q43: 3.8221822 | V43: 3650 | W43: 0.1335734 | Y43: =IFERROR(D43/O43-1,"") | Z43: =IFERROR(E43/O43-1,"") | AA43: =IFERROR(E43/U43-1,"") | AB43: =IFERROR(W43/X43-1,"")

Sheet ENT_00006_BBVA
A1: ENT 00006 BBVA
A2: Entidad 00006 (BBVA), poblacion clean
A4: codmes | B4: n | C4: PD sin calibrar | D4: PD cal vigente | E4: PD cal NUEVA | F4: mora 3m | G4: mora 4m | H4: mora 5m | I4: mora 6m | J4: mora 7m | K4: mora 8m | L4: mora 9m | M4: mora 10m | N4: mora 11m | O4: mora 12m | P4: ft ciclo | Q4: inflacion % | R4: madurez | S4: mora base | T4: factor h->12 | U4: proy mediana | V4: n visible IBK | W4: PD cal NUEVA visible | X4: mora 12m visible | Y4: EC vigente | Z4: EC NUEVA | AA4: EC NUEVA vs proy | AB4: EC NUEVA visible
A5: 202303 | B5: 6224 | C5: 0.13987842 | D5: 0.17600689 | E5: 0.16026447 | F5: 0.0073907455 | G5: 0.024421594 | H5: 0.038399743 | I5: 0.051895887 | J5: 0.06748072 | K5: 0.079691517 | L5: 0.093026992 | M5: 0.10571979 | N5: 0.11728792 | O5: 0.12773136 | P5: 0.23130779 | Q5: 8.6661549 | R5: 12 | S5: 0.12773136 | T5: 1 | U5: 0.12773136 | V5: 2046 | W5: 0.16627425 | X5: 0.14956012 | Y5: =IFERROR(D5/O5-1,"") | Z5: =IFERROR(E5/O5-1,"") | AA5: =IFERROR(E5/U5-1,"") | AB5: =IFERROR(W5/X5-1,"")
A6: 202304 | B6: 8412 | C6: 0.14633691 | D6: 0.18401852 | E6: 0.16812836 | F6: 0.004636234 | G6: 0.024845459 | H6: 0.042439372 | I6: 0.059320019 | J6: 0.07596291 | K6: 0.090822634 | L6: 0.10425583 | M6: 0.11757014 | N6: 0.12981455 | O6: 0.14324774 | P6: 0.20398831 | Q6: 8.0421126 | R6: 12 | S6: 0.14324774 | T6: 1 | U6: 0.14324774 | V6: 3098 | W6: 0.1761596 | X6: 0.16881859 | Y6: =IFERROR(D6/O6-1,"") | Z6: =IFERROR(E6/O6-1,"") | AA6: =IFERROR(E6/U6-1,"") | AB6: =IFERROR(W6/X6-1,"")
A7: 202305 | B7: 6968 | C7: 0.14706052 | D7: 0.18466658 | E7: 0.16874196 | F7: 0.0078932262 | G7: 0.027123995 | H7: 0.044058553 | I7: 0.061997704 | J7: 0.075487945 | K7: 0.090413318 | L7: 0.10318599 | M7: 0.11538462 | N7: 0.12787026 | O7: 0.14035591 | P7: 0.20154202 | Q7: 7.9862335 | R7: 12 | S7: 0.14035591 | T7: 1 | U7: 0.14035591 | V7: 2455 | W7: 0.17671364 | X7: 0.16171079 | Y7: =IFERROR(D7/O7-1,"") | Z7: =IFERROR(E7/O7-1,"") | AA7: =IFERROR(E7/U7-1,"") | AB7: =IFERROR(W7/X7-1,"")
A8: 202306 | B8: 5081 | C8: 0.14323892 | D8: 0.17950616 | E8: 0.1634777 | F8: 0.0057075379 | G8: 0.020468412 | H8: 0.033457981 | I8: 0.050186971 | J8: 0.064554222 | K8: 0.073804369 | L8: 0.086400315 | M8: 0.097224956 | N8: 0.10962409 | O8: 0.11966148 | P8: 0.14563116 | Q8: 6.7090957 | R8: 12 | S8: 0.11966148 | T8: 1 | U8: 0.11966148 | V8: 1824 | W8: 0.1714369 | X8: 0.1441886 | Y8: =IFERROR(D8/O8-1,"") | Z8: =IFERROR(E8/O8-1,"") | AA8: =IFERROR(E8/U8-1,"") | AB8: =IFERROR(W8/X8-1,"")
A9: 202307 | B9: 4227 | C9: 0.14136005 | D9: 0.1441238 | E9: 0.1586715 | F9: 0.0047314881 | G9: 0.022711143 | H9: 0.036432458 | I9: 0.046841732 | J9: 0.056541282 | K9: 0.069552874 | L9: 0.082091318 | M9: 0.093683463 | N9: 0.10574876 | O9: 0.11781405 | P9: 0.11544766 | Q9: 6.0196325 | R9: 12 | S9: 0.11781405 | T9: 1 | U9: 0.11781405 | V9: 1584 | W9: 0.16690388 | X9: 0.1395202 | Y9: =IFERROR(D9/O9-1,"") | Z9: =IFERROR(E9/O9-1,"") | AA9: =IFERROR(E9/U9-1,"") | AB9: =IFERROR(W9/X9-1,"")
A10: 202308 | B10: 4582 | C10: 0.13432887 | D10: 0.13705533 | E10: 0.15100845 | F10: 0.0054561327 | G10: 0.019642078 | H10: 0.033173287 | I10: 0.042994326 | J10: 0.056962025 | K10: 0.067001309 | L10: 0.079659537 | M10: 0.088607595 | N10: 0.097992143 | O10: 0.10803143 | P10: 0.10524205 | Q10: 5.7865118 | R10: 12 | S10: 0.10803143 | T10: 1 | U10: 0.10803143 | V10: 1643 | W10: 0.15437705 | X10: 0.13207547 | Y10: =IFERROR(D10/O10-1,"") | Z10: =IFERROR(E10/O10-1,"") | AA10: =IFERROR(E10/U10-1,"") | AB10: =IFERROR(W10/X10-1,"")
A11: 202309 | B11: 4452 | C11: 0.13405951 | D11: 0.1287981 | E11: 0.14658621 | F11: 0.0033692722 | G11: 0.019317161 | H11: 0.029424978 | I11: 0.042228212 | J11: 0.052336029 | K11: 0.062893082 | L11: 0.072551662 | M11: 0.081985624 | N11: 0.090296496 | O11: 0.099056604 | P11: 0.082642878 | Q11: 5.2702928 | R11: 12 | S11: 0.099056604 | T11: 1 | U11: 0.099056604 | V11: 1600 | W11: 0.15337041 | X11: 0.11375 | Y11: =IFERROR(D11/O11-1,"") | Z11: =IFERROR(E11/O11-1,"") | AA11: =IFERROR(E11/U11-1,"") | AB11: =IFERROR(W11/X11-1,"")
A12: 202310 | B12: 4943 | C12: 0.13378418 | D12: 0.1356582 | E12: 0.13960589 | F12: 0.0042484321 | G12: 0.017196035 | H12: 0.029132106 | I12: 0.040056646 | J12: 0.050778879 | K12: 0.061501113 | L12: 0.072830265 | M12: 0.082540967 | N12: 0.088812462 | O12: 0.094881651 | P12: 0.049681202 | Q12: 4.5173693 | R12: 12 | S12: 0.094881651 | T12: 1 | U12: 0.094881651 | V12: 1679 | W12: 0.14532335 | X12: 0.11494937 | Y12: =IFERROR(D12/O12-1,"") | Z12: =IFERROR(E12/O12-1,"") | AA12: =IFERROR(E12/U12-1,"") | AB12: =IFERROR(W12/X12-1,"")
A13: 202311 | B13: 4862 | C13: 0.13534227 | D13: 0.13770227 | E13: 0.13494727 | F13: 0.0041135335 | G13: 0.017276841 | H13: 0.028177705 | I13: 0.038255862 | J13: 0.051007816 | K13: 0.063348416 | L13: 0.072603867 | M13: 0.078774167 | N13: 0.087823941 | O13: 0.093994241 | P13: 0.017692212 | Q13: 3.7866642 | R13: 12 | S13: 0.093994241 | T13: 1 | U13: 0.093994241 | V13: 1682 | W13: 0.1393392 | X13: 0.11890606 | Y13: =IFERROR(D13/O13-1,"") | Z13: =IFERROR(E13/O13-1,"") | AA13: =IFERROR(E13/U13-1,"") | AB13: =IFERROR(W13/X13-1,"")
A14: 202312 | B14: 4874 | C14: 0.13780721 | D14: 0.14020347 | E14: 0.1343967 | F14: 0.003487895 | G14: 0.019080837 | H14: 0.031185884 | I14: 0.041854739 | J14: 0.055190808 | K14: 0.065244153 | L14: 0.072219943 | M14: 0.083504309 | N14: 0.092736972 | O14: 0.10053344 | P14: 0.0012463847 | Q14: 3.4110022 | R14: 12 | S14: 0.10053344 | T14: 1 | U14: 0.10053344 | V14: 1678 | W14: 0.14343485 | X14: 0.13051251 | Y14: =IFERROR(D14/O14-1,"") | Z14: =IFERROR(E14/O14-1,"") | AA14: =IFERROR(E14/U14-1,"") | AB14: =IFERROR(W14/X14-1,"")
A15: 202401 | B15: 6360 | C15: 0.13780517 | D15: 0.13237552 | E15: 0.13070616 | F15: 0.004245283 | G15: 0.021855346 | H15: 0.036006289 | I15: 0.050786164 | J15: 0.060691824 | K15: 0.070754717 | L15: 0.079245283 | M15: 0.087106918 | N15: 0.091981132 | O15: 0.098584906 | P15: -0.019064283 | Q15: 2.947058 | R15: 12 | S15: 0.098584906 | T15: 1 | U15: 0.098584906 | V15: 2247 | W15: 0.13744053 | X15: 0.12950601 | Y15: =IFERROR(D15/O15-1,"") | Z15: =IFERROR(E15/O15-1,"") | AA15: =IFERROR(E15/U15-1,"") | AB15: =IFERROR(W15/X15-1,"")
A16: 202402 | B16: 6055 | C16: 0.13764665 | D16: 0.13221245 | E16: 0.13003996 | F16: 0.004954583 | G16: 0.02146986 | H16: 0.035342692 | I16: 0.043930636 | J16: 0.054500413 | K16: 0.065895954 | L16: 0.075144509 | M16: 0.084393064 | N16: 0.091659785 | O16: 0.10107349 | P16: -0.019828668 | Q16: 2.9295976 | R16: 12 | S16: 0.10107349 | T16: 1 | U16: 0.10107349 | V16: 2187 | W16: 0.13655278 | X16: 0.12528578 | Y16: =IFERROR(D16/O16-1,"") | Z16: =IFERROR(E16/O16-1,"") | AA16: =IFERROR(E16/U16-1,"") | AB16: =IFERROR(W16/X16-1,"")
... A32: 202506 | B32: 10063 | C32: 0.18319005 | D32: 0.17647808 | E32: 0.16607018 | F32: 0.0059624366 | G32: 0.02772533 | H32: 0.045413892 | I32: 0.063102455 | J32: 0.075722945 | K32: 0.087846567 | L32: 0.099373944 | M32: 0.10990758 | N32: 0.12044122 | O32: 0.1315711 | P32: -0.073765695 | Q32: 1.697547 | R32: 12 | S32: 0.1315711 | T32: 1 | U32: 0.1315711 | V32: 3939 | W32: 0.17596729 | X32: 0.15816197 | Y32: =IFERROR(D32/O32-1,"") | Z32: =IFERROR(E32/O32-1,"") | AA32: =IFERROR(E32/U32-1,"") | AB32: =IFERROR(W32/X32-1,"")
A33: 202507 | B33: 9615 | C33: 0.18775386 | D33: 0.18100396 | E33: 0.17020642 | F33: 0.0055122205 | G33: 0.027041082 | H33: 0.043369735 | I33: 0.057514301 | J33: 0.070930837 | K33: 0.08299532 | L33: 0.095163807 | M33: 0.10587624 | N33: 0.11638066 | P33: -0.073640896 | Q33: 1.7003977 | R33: 11 | S33: 0.11638066 | T33: 1.0884904 | U33: 0.12667922 | V33: 3954 | W33: 0.18515878 | Y33: =IFERROR(D33/O33-1,"") | Z33: =IFERROR(E33/O33-1,"") | AA33: =IFERROR(E33/U33-1,"") | AB33: =IFERROR(W33/X33-1,"")
A34: 202508 | B34: 10254 | C34: 0.20297654 | D34: 0.19587076 | E34: 0.18308754 | F34: 0.0076067876 | G34: 0.039009167 | H34: 0.056660815 | I34: 0.07519017 | J34: 0.089623562 | K34: 0.10522723 | L34: 0.11975814 | M34: 0.13516676 | P34: -0.10033144 | Q34: 1.0907218 | R34: 10 | S34: 0.13516676 | T34: 1.1956228 | U34: 0.16160846 | V34: 4293 | W34: 0.20205931 | Y34: =IFERROR(D34/O34-1,"") | Z34: =IFERROR(E34/O34-1,"") | AA34: =IFERROR(E34/U34-1,"") | AB34: =IFERROR(W34/X34-1,"")
A35: 202509 | B35: 11676 | C35: 0.19978868 | D35: 0.19274779 | E35: 0.18017639 | F35: 0.010191847 | G35: 0.04230901 | H35: 0.06294964 | I35: 0.082819459 | J35: 0.10046249 | K35: 0.11690647 | L35: 0.13172319 | P35: -0.094338164 | Q35: 1.2276226 | R35: 9 | S35: 0.13172319 | T35: 1.3296585 | U35: 0.17514687 | V35: 4768 | W35: 0.19895703 | Y35: =IFERROR(D35/O35-1,"") | Z35: =IFERROR(E35/O35-1,"") | AA35: =IFERROR(E35/U35-1,"") | AB35: =IFERROR(W35/X35-1,"")
A36: 202510 | B36: 13741 | C36: 0.2046762 | D36: 0.19748581 | E36: 0.18481532 | F36: 0.010989011 | G36: 0.045047668 | H36: 0.07088276 | I36: 0.09387963 | J36: 0.11229168 | K36: 0.12895714 | P36: -0.097186463 | Q36: 1.1625606 | R36: 8 | S36: 0.12895714 | T36: 1.5150082 | U36: 0.19537111 | V36: 5626 | W36: 0.2047751 | Y36: =IFERROR(D36/O36-1,"") | Z36: =IFERROR(E36/O36-1,"") | AA36: =IFERROR(E36/U36-1,"") | AB36: =IFERROR(W36/X36-1,"")
A37: 202511 | B37: 12856 | C37: 0.20724498 | D37: 0.19995006 | E37: 0.18700153 | F37: 0.012523335 | G37: 0.060594275 | H37: 0.091630367 | I37: 0.11488799 | J37: 0.13503423 | P37: -0.095195045 | Q37: 1.2080494 | R37: 7 | S37: 0.13503423 | T37: 1.7827047 | U37: 0.24072614 | V37: 5269 | W37: 0.2080323 | Y37: =IFERROR(D37/O37-1,"") | Z37: =IFERROR(E37/O37-1,"") | AA37: =IFERROR(E37/U37-1,"") | AB37: =IFERROR(W37/X37-1,"")
A38: 202512 | B38: 11139 | C38: 0.20398431 | D38: 0.19679933 | E38: 0.18403969 | F38: 0.012748003 | G38: 0.055750067 | H38: 0.083669988 | I38: 0.10692163 | P38: -0.090738963 | Q38: 1.3098369 | R38: 6 | S38: 0.10692163 | T38: 2.2418829 | U38: 0.23970577 | V38: 4570 | W38: 0.20589611 | Y38: =IFERROR(D38/O38-1,"") | Z38: =IFERROR(E38/O38-1,"") | AA38: =IFERROR(E38/U38-1,"") | AB38: =IFERROR(W38/X38-1,"")
A39: 202601 | B39: 11532 | C39: 0.19517469 | D39: 0.18819285 | E39: 0.17527307 | F39: 0.010058966 | G39: 0.050815123 | H39: 0.078043704 | P39: -0.082751237 | Q39: 1.4922957 | R39: 5 | S39: 0.078043704 | T39: 3.0741476 | U39: 0.23991787 | V39: 4572 | W39: 0.19124682 | Y39: =IFERROR(D39/O39-1,"") | Z39: =IFERROR(E39/O39-1,"") | AA39: =IFERROR(E39/U39-1,"") | AB39: =IFERROR(W39/X39-1,"")
A40: 202602 | B40: 10393 | C40: 0.19571738 | D40: 0.18871108 | E40: 0.1867872 | F40: 0.015972289 | G40: 0.055421919 | P40: -0.037038893 | Q40: 2.5364749 | R40: 4 | S40: 0.055421919 | T40: 5.0596568 | U40: 0.28041589 | V40: 4200 | W40: 0.20326819 | Y40: =IFERROR(D40/O40-1,"") | Z40: =IFERROR(E40/O40-1,"") | AA40: =IFERROR(E40/U40-1,"") | AB40: =IFERROR(W40/X40-1,"")
A41: 202603 | B41: 10875 | C41: 0.19351311 | D41: 0.18663872 | E41: 0.19724349 | F41: 0.012965517 | P41: 0.014389803 | Q41: 3.7112293 | R41: 3 | S41: 0.012965517 | T41: 22.085612 | U41: 0.28635139 | V41: 4448 | W41: 0.21617126 | Y41: =IFERROR(D41/O41-1,"") | Z41: =IFERROR(E41/O41-1,"") | AA41: =IFERROR(E41/U41-1,"") | AB41: =IFERROR(W41/X41-1,"")
A42: 202604 | B42: 10653 | C42: 0.18879222 | D42: 0.17928013 | E42: 0.19447305 | P42: 0.024185191 | Q42: 3.9349794 | V42: 4288 | W42: 0.20878077 | Y42: =IFERROR(D42/O42-1,"") | Z42: =IFERROR(E42/O42-1,"") | AA42: =IFERROR(E42/U42-1,"") | AB42: =IFERROR(W42/X42-1,"")
A43: 202605 | B43: 11504 | C43: 0.19074674 | D43: 0.18125302 | E43: 0.1952833 | P43: 0.019247124 | Q43: 3.8221822 | V43: 4611 | W43: 0.21123471 | Y43: =IFERROR(D43/O43-1,"") | Z43: =IFERROR(E43/O43-1,"") | AA43: =IFERROR(E43/U43-1,"") | AB43: =IFERROR(W43/X43-1,"")

Sheet ENT_00004_Scotiabank
A1: ENT 00004 Scotiabank
A2: Entidad 00004 (Scotiabank), poblacion clean
A4: codmes | B4: n | C4: PD sin calibrar | D4: PD cal vigente | E4: PD cal NUEVA | F4: mora 3m | G4: mora 4m | H4: mora 5m | I4: mora 6m | J4: mora 7m | K4: mora 8m | L4: mora 9m | M4: mora 10m | N4: mora 11m | O4: mora 12m | P4: ft ciclo | Q4: inflacion % | R4: madurez | S4: mora base | T4: factor h->12 | U4: proy mediana | V4: n visible IBK | W4: PD cal NUEVA visible | X4: mora 12m visible | Y4: EC vigente | Z4: EC NUEVA | AA4: EC NUEVA vs proy | AB4: EC NUEVA visible
A5: 202303 | B5: 857 | C5: 0.16104674 | D5: 0.20071299 | E5: 0.18551365 | F5: 0.01050175 | G5: 0.050175029 | H5: 0.075845974 | I5: 0.10035006 | J5: 0.11668611 | K5: 0.12835473 | L5: 0.13652275 | M5: 0.14935823 | N5: 0.15752625 | O5: 0.17269545 | P5: 0.23130779 | Q5: 8.6661549 | R5: 12 | S5: 0.17269545 | T5: 1 | U5: 0.17269545 | V5: 300 | W5: 0.20436875 | X5: 0.19333333 | Y5: =IFERROR(D5/O5-1,"") | Z5: =IFERROR(E5/O5-1,"") | AA5: =IFERROR(E5/U5-1,"") | AB5: =IFERROR(W5/X5-1,"")
A6: 202304 | B6: 775 | C6: 0.15623258 | D6: 0.19503284 | E6: 0.18030886 | F6: 0.018064516 | G6: 0.067096774 | H6: 0.087741935 | I6: 0.1083871 | J6: 0.12774194 | K6: 0.14967742 | L6: 0.16258065 | M6: 0.17290323 | N6: 0.1883871 | O6: 0.20258065 | P6: 0.20398831 | Q6: 8.0421126 | R6: 12 | S6: 0.20258065 | T6: 1 | U6: 0.20258065 | V6: 256 | W6: 0.19801489 | X6: 0.22265625 | Y6: =IFERROR(D6/O6-1,"") | Z6: =IFERROR(E6/O6-1,"") | AA6: =IFERROR(E6/U6-1,"") | AB6: =IFERROR(W6/X6-1,"")
A7: 202305 | B7: 676 | C7: 0.15336486 | D7: 0.19173781 | E7: 0.17570952 | F7: 0.01183432 | G7: 0.047337278 | H7: 0.068047337 | I7: 0.087278107 | J7: 0.11538462 | K7: 0.13609467 | L7: 0.14497041 | M7: 0.15088757 | N7: 0.1612426 | O7: 0.1760355 | P7: 0.20154202 | Q7: 7.9862335 | R7: 12 | S7: 0.1760355 | T7: 1 | U7: 0.1760355 | V7: 213 | W7: 0.1938411 | X7: 0.24413146 | Y7: =IFERROR(D7/O7-1,"") | Z7: =IFERROR(E7/O7-1,"") | AA7: =IFERROR(E7/U7-1,"") | AB7: =IFERROR(W7/X7-1,"")
A8: 202306 | B8: 394 | C8: 0.12703986 | D8: 0.16049632 | E8: 0.14431296 | F8: 0.0076142132 | G8: 0.015228426 | H8: 0.027918782 | I8: 0.030456853 | J8: 0.045685279 | K8: 0.053299492 | L8: 0.058375635 | M8: 0.07106599 | N8: 0.073604061 | O8: 0.083756345 | P8: 0.14563116 | Q8: 6.7090957 | R8: 12 | S8: 0.083756345 | T8: 1 | U8: 0.083756345 | V8: 132 | W8: 0.15339399 | X8: 0.090909091 | Y8: =IFERROR(D8/O8-1,"") | Z8: =IFERROR(E8/O8-1,"") | AA8: =IFERROR(E8/U8-1,"") | AB8: =IFERROR(W8/X8-1,"")
A9: 202307 | B9: 343 | C9: 0.12235339 | D9: 0.12486048 | E9: 0.13769374 | F9: 0.0058309038 | G9: 0.026239067 | H9: 0.029154519 | I9: 0.037900875 | J9: 0.043731778 | K9: 0.04664723 | L9: 0.055393586 | M9: 0.064139942 | N9: 0.064139942 | O9: 0.081632653 | P9: 0.11544766 | Q9: 6.0196325 | R9: 12 | S9: 0.081632653 | T9: 1 | U9: 0.081632653 | V9: 121 | W9: 0.13584158 | X9: 0.099173554 | Y9: =IFERROR(D9/O9-1,"") | Z9: =IFERROR(E9/O9-1,"") | AA9: =IFERROR(E9/U9-1,"") | AB9: =IFERROR(W9/X9-1,"")
A10: 202308 | B10: 340 | C10: 0.12406785 | D10: 0.12682581 | E10: 0.13875096 | F10: 0.011764706 | G10: 0.032352941 | H10: 0.055882353 | I10: 0.058823529 | J10: 0.073529412 | K10: 0.073529412 | L10: 0.082352941 | M10: 0.088235294 | N10: 0.097058824 | O10: 0.1 | P10: 0.10524205 | Q10: 5.7865118 | R10: 12 | S10: 0.1 | T10: 1 | U10: 0.1 | V10: 118 | W10: 0.13059038 | X10: 0.084745763 | Y10: =IFERROR(D10/O10-1,"") | Z10: =IFERROR(E10/O10-1,"") | AA10: =IFERROR(E10/U10-1,"") | AB10: =IFERROR(W10/X10-1,"")
A11: 202309 | B11: 327 | C11: 0.11841889 | D11: 0.11348703 | E11: 0.12968903 | F11: 0.012232416 | G11: 0.027522936 | H11: 0.033639144 | I11: 0.042813456 | J11: 0.048929664 | K11: 0.058103976 | L11: 0.067278287 | M11: 0.073394495 | N11: 0.082568807 | O11: 0.082568807 | P11: 0.082642878 | Q11: 5.2702928 | R11: 12 | S11: 0.082568807 | T11: 1 | U11: 0.082568807 | V11: 102 | W11: 0.12689987 | X11: 0.058823529 | Y11: =IFERROR(D11/O11-1,"") | Z11: =IFERROR(E11/O11-1,"") | AA11: =IFERROR(E11/U11-1,"") | AB11: =IFERROR(W11/X11-1,"")
A12: 202310 | B12: 343 | C12: 0.12392473 | D12: 0.12551461 | E12: 0.12883551 | F12: 0.0058309038 | G12: 0.0087463557 | H12: 0.026239067 | I12: 0.040816327 | J12: 0.04664723 | K12: 0.055393586 | L12: 0.06122449 | M12: 0.069970845 | N12: 0.075801749 | O12: 0.078717201 | P12: 0.049681202 | Q12: 4.5173693 | R12: 12 | S12: 0.078717201 | T12: 1 | U12: 0.078717201 | V12: 108 | W12: 0.13557207 | X12: 0.13888889 | Y12: =IFERROR(D12/O12-1,"") | Z12: =IFERROR(E12/O12-1,"") | AA12: =IFERROR(E12/U12-1,"") | AB12: =IFERROR(W12/X12-1,"")
A13: 202311 | B13: 290 | C13: 0.12317062 | D13: 0.12534572 | E13: 0.12291173 | F13: 0 | G13: 0.0068965517 | H13: 0.010344828 | I13: 0.024137931 | J13: 0.034482759 | K13: 0.04137931 | L13: 0.044827586 | M13: 0.051724138 | N13: 0.051724138 | O13: 0.05862069 | P13: 0.017692212 | Q13: 3.7866642 | R13: 12 | S13: 0.05862069 | T13: 1 | U13: 0.05862069 | V13: 98 | W13: 0.12709468 | X13: 0.091836735 | Y13: =IFERROR(D13/O13-1,"") | Z13: =IFERROR(E13/O13-1,"") | AA13: =IFERROR(E13/U13-1,"") | AB13: =IFERROR(W13/X13-1,"")
A14: 202312 | B14: 352 | C14: 0.13024597 | D14: 0.13246581 | E14: 0.12662357 | F14: 0.0056818182 | G14: 0.019886364 | H14: 0.022727273 | I14: 0.028409091 | J14: 0.034090909 | K14: 0.045454545 | L14: 0.053977273 | M14: 0.0625 | N14: 0.0625 | O14: 0.076704545 | P14: 0.0012463847 | Q14: 3.4110022 | R14: 12 | S14: 0.076704545 | T14: 1 | U14: 0.076704545 | V14: 130 | W14: 0.1217467 | X14: 0.061538462 | Y14: =IFERROR(D14/O14-1,"") | Z14: =IFERROR(E14/O14-1,"") | AA14: =IFERROR(E14/U14-1,"") | AB14: =IFERROR(W14/X14-1,"")
A15: 202401 | B15: 237 | C15: 0.1159785 | D15: 0.11126143 | E15: 0.10786845 | F15: 0 | G15: 0.0084388186 | H15: 0.012658228 | I15: 0.016877637 | J15: 0.016877637 | K15: 0.021097046 | L15: 0.029535865 | M15: 0.033755274 | N15: 0.037974684 | O15: 0.046413502 | P15: -0.019064283 | Q15: 2.947058 | R15: 12 | S15: 0.046413502 | T15: 1 | U15: 0.046413502 | V15: 71 | W15: 0.10991301 | X15: 0 | Y15: =IFERROR(D15/O15-1,"") | Z15: =IFERROR(E15/O15-1,"") | AA15: =IFERROR(E15/U15-1,"") | AB15: =IFERROR(W15/X15-1,"")
A16: 202402 | B16: 288 | C16: 0.13838862 | D16: 0.1331173 | E16: 0.13211014 | F16: 0 | G16: 0.0034722222 | H16: 0.0069444444 | I16: 0.010416667 | J16: 0.017361111 | K16: 0.020833333 | L16: 0.020833333 | M16: 0.024305556 | N16: 0.024305556 | O16: 0.03125 | P16: -0.019828668 | Q16: 2.9295976 | R16: 12 | S16: 0.03125 | T16: 1 | U16: 0.03125 | V16: 95 | W16: 0.13385619 | X16: 0.021052632 | Y16: =IFERROR(D16/O16-1,"") | Z16: =IFERROR(E16/O16-1,"") | AA16: =IFERROR(E16/U16-1,"") | AB16: =IFERROR(W16/X16-1,"")
... A32: 202506 | B32: 472 | C32: 0.1374582 | D32: 0.13193832 | E32: 0.11935861 | F32: 0.0042372881 | G32: 0.016949153 | H32: 0.029661017 | I32: 0.042372881 | J32: 0.050847458 | K32: 0.059322034 | L32: 0.063559322 | M32: 0.069915254 | N32: 0.074152542 | O32: 0.074152542 | P32: -0.073765695 | Q32: 1.697547 | R32: 12 | S32: 0.074152542 | T32: 1 | U32: 0.074152542 | V32: 175 | W32: 0.12289497 | X32: 0.068571429 | Y32: =IFERROR(D32/O32-1,"") | Z32: =IFERROR(E32/O32-1,"") | AA32: =IFERROR(E32/U32-1,"") | AB32: =IFERROR(W32/X32-1,"")
A33: 202507 | B33: 517 | C33: 0.14117764 | D33: 0.13543179 | E33: 0.12330045 | F33: 0.003868472 | G33: 0.01934236 | H33: 0.03868472 | I33: 0.042553191 | J33: 0.048355899 | K33: 0.050290135 | L33: 0.056092843 | M33: 0.067698259 | N33: 0.071566731 | P33: -0.073640896 | Q33: 1.7003977 | R33: 11 | S33: 0.071566731 | T33: 1.0995475 | U33: 0.078691021 | V33: 216 | W33: 0.1144717 | Y33: =IFERROR(D33/O33-1,"") | Z33: =IFERROR(E33/O33-1,"") | AA33: =IFERROR(E33/U33-1,"") | AB33: =IFERROR(W33/X33-1,"")
A34: 202508 | B34: 515 | C34: 0.149132 | D34: 0.14325487 | E34: 0.13033811 | F34: 0.0038834951 | G34: 0.0097087379 | H34: 0.017475728 | I34: 0.023300971 | J34: 0.033009709 | K34: 0.044660194 | L34: 0.058252427 | M34: 0.066019417 | P34: -0.10033144 | Q34: 1.0907218 | R34: 10 | S34: 0.066019417 | T34: 1.1994077 | U34: 0.079184198 | V34: 209 | W34: 0.14067277 | Y34: =IFERROR(D34/O34-1,"") | Z34: =IFERROR(E34/O34-1,"") | AA34: =IFERROR(E34/U34-1,"") | AB34: =IFERROR(W34/X34-1,"")
A35: 202509 | B35: 546 | C35: 0.15199814 | D35: 0.14609808 | E35: 0.13334464 | F35: 0 | G35: 0.010989011 | H35: 0.010989011 | I35: 0.023809524 | J35: 0.043956044 | K35: 0.049450549 | L35: 0.067765568 | P35: -0.094338164 | Q35: 1.2276226 | R35: 9 | S35: 0.067765568 | T35: 1.3293217 | U35: 0.090082237 | V35: 217 | W35: 0.13923191 | Y35: =IFERROR(D35/O35-1,"") | Z35: =IFERROR(E35/O35-1,"") | AA35: =IFERROR(E35/U35-1,"") | AB35: =IFERROR(W35/X35-1,"")
A36: 202510 | B36: 384 | C36: 0.14313568 | D36: 0.13731648 | E36: 0.12391565 | F36: 0 | G36: 0.013020833 | H36: 0.028645833 | I36: 0.036458333 | J36: 0.044270833 | K36: 0.0546875 | P36: -0.097186463 | Q36: 1.1625606 | R36: 8 | S36: 0.0546875 | T36: 1.4907975 | U36: 0.081527991 | V36: 151 | W36: 0.12407904 | Y36: =IFERROR(D36/O36-1,"") | Z36: =IFERROR(E36/O36-1,"") | AA36: =IFERROR(E36/U36-1,"") | AB36: =IFERROR(W36/X36-1,"")
A37: 202511 | B37: 384 | C37: 0.14038503 | D37: 0.13452925 | E37: 0.12120909 | F37: 0.0026041667 | G37: 0.020833333 | H37: 0.028645833 | I37: 0.033854167 | J37: 0.049479167 | P37: -0.095195045 | Q37: 1.2080494 | R37: 7 | S37: 0.049479167 | T37: 1.7307692 | U37: 0.085637019 | V37: 131 | W37: 0.13645156 | Y37: =IFERROR(D37/O37-1,"") | Z37: =IFERROR(E37/O37-1,"") | AA37: =IFERROR(E37/U37-1,"") | AB37: =IFERROR(W37/X37-1,"")
A38: 202512 | B38: 570 | C38: 0.14851879 | D38: 0.14277721 | E38: 0.12955867 | F38: 0.001754386 | G38: 0.014035088 | H38: 0.019298246 | I38: 0.026315789 | P38: -0.090738963 | Q38: 1.3098369 | R38: 6 | S38: 0.026315789 | T38: 2.1057192 | U38: 0.055413664 | V38: 209 | W38: 0.13506309 | Y38: =IFERROR(D38/O38-1,"") | Z38: =IFERROR(E38/O38-1,"") | AA38: =IFERROR(E38/U38-1,"") | AB38: =IFERROR(W38/X38-1,"")
A39: 202601 | B39: 551 | C39: 0.15377598 | D39: 0.14773717 | E39: 0.13468206 | F39: 0.0036297641 | G39: 0.025408348 | H39: 0.030852995 | P39: -0.082751237 | Q39: 1.4922957 | R39: 5 | S39: 0.030852995 | T39: 2.7459954 | U39: 0.084722182 | V39: 229 | W39: 0.14786007 | Y39: =IFERROR(D39/O39-1,"") | Z39: =IFERROR(E39/O39-1,"") | AA39: =IFERROR(E39/U39-1,"") | AB39: =IFERROR(W39/X39-1,"")
A40: 202602 | B40: 959 | C40: 0.15027184 | D40: 0.14449778 | E40: 0.14031694 | F40: 0 | G40: 0.022940563 | P40: -0.037038893 | Q40: 2.5364749 | R40: 4 | S40: 0.022940563 | T40: 4.2553191 | U40: 0.097619417 | V40: 358 | W40: 0.14749667 | Y40: =IFERROR(D40/O40-1,"") | Z40: =IFERROR(E40/O40-1,"") | AA40: =IFERROR(E40/U40-1,"") | AB40: =IFERROR(W40/X40-1,"")
A41: 202603 | B41: 1380 | C41: 0.14971023 | D41: 0.14396764 | E41: 0.15030652 | F41: 0.0079710145 | P41: 0.014389803 | Q41: 3.7112293 | R41: 3 | S41: 0.0079710145 | T41: 14.558442 | U41: 0.11604555 | V41: 480 | W41: 0.16774189 | Y41: =IFERROR(D41/O41-1,"") | Z41: =IFERROR(E41/O41-1,"") | AA41: =IFERROR(E41/U41-1,"") | AB41: =IFERROR(W41/X41-1,"")
A42: 202604 | B42: 1103 | C42: 0.15279103 | D42: 0.14506481 | E42: 0.15557636 | P42: 0.024185191 | Q42: 3.9349794 | V42: 405 | W42: 0.17048733 | Y42: =IFERROR(D42/O42-1,"") | Z42: =IFERROR(E42/O42-1,"") | AA42: =IFERROR(E42/U42-1,"") | AB42: =IFERROR(W42/X42-1,"")
A43: 202605 | B43: 1049 | C43: 0.14734071 | D43: 0.13943019 | E43: 0.14847641 | P43: 0.019247124 | Q43: 3.8221822 | V43: 403 | W43: 0.16736688 | Y43: =IFERROR(D43/O43-1,"") | Z43: =IFERROR(E43/O43-1,"") | AA43: =IFERROR(E43/U43-1,"") | AB43: =IFERROR(W43/X43-1,"")

Sheet ENT_00142_Falabella
A1: ENT 00142 Falabella
A2: Entidad 00142 (Falabella), poblacion clean
A4: codmes | B4: n | C4: PD sin calibrar | D4: PD cal vigente | E4: PD cal NUEVA | F4: mora 3m | G4: mora 4m | H4: mora 5m | I4: mora 6m | J4: mora 7m | K4: mora 8m | L4: mora 9m | M4: mora 10m | N4: mora 11m | O4: mora 12m | P4: ft ciclo | Q4: inflacion % | R4: madurez | S4: mora base | T4: factor h->12 | U4: proy mediana | V4: n visible IBK | W4: PD cal NUEVA visible | X4: mora 12m visible | Y4: EC vigente | Z4: EC NUEVA | AA4: EC NUEVA vs proy | AB4: EC NUEVA visible
A5: 202303 | B5: 3877 | C5: 0.12871188 | D5: 0.16286938 | E5: 0.14593714 | F5: 0.0067062161 | G5: 0.022440031 | H5: 0.04075316 | I5: 0.053907661 | J5: 0.063193191 | K5: 0.075573897 | L5: 0.083827702 | M5: 0.091307712 | N5: 0.099561517 | O5: 0.10936291 | P5: 0.23130779 | Q5: 8.6661549 | R5: 12 | S5: 0.10936291 | T5: 1 | U5: 0.10936291 | V5: 1537 | W5: 0.14846372 | X5: 0.13532856 | Y5: =IFERROR(D5/O5-1,"") | Z5: =IFERROR(E5/O5-1,"") | AA5: =IFERROR(E5/U5-1,"") | AB5: =IFERROR(W5/X5-1,"")
A6: 202304 | B6: 3270 | C6: 0.11795764 | D6: 0.14946652 | E6: 0.13246285 | F6: 0.0012232416 | G6: 0.013761468 | H6: 0.026911315 | I6: 0.040366972 | J6: 0.049541284 | K6: 0.060856269 | L6: 0.066972477 | M6: 0.074006116 | N6: 0.082874618 | O6: 0.090214067 | P6: 0.20398831 | Q6: 8.0421126 | R6: 12 | S6: 0.090214067 | T6: 1 | U6: 0.090214067 | V6: 1282 | W6: 0.13118717 | X6: 0.10062402 | Y6: =IFERROR(D6/O6-1,"") | Z6: =IFERROR(E6/O6-1,"") | AA6: =IFERROR(E6/U6-1,"") | AB6: =IFERROR(W6/X6-1,"")
A7: 202305 | B7: 3327 | C7: 0.12104206 | D7: 0.15332494 | E7: 0.13603514 | F7: 0.0027051398 | G7: 0.018334836 | H7: 0.037871957 | I7: 0.048993087 | J7: 0.058310791 | K7: 0.06642621 | L7: 0.0748422 | M7: 0.082356477 | N7: 0.094679892 | O7: 0.10429817 | P7: 0.20154202 | Q7: 7.9862335 | R7: 12 | S7: 0.10429817 | T7: 1 | U7: 0.10429817 | V7: 1359 | W7: 0.13300137 | X7: 0.11405445 | Y7: =IFERROR(D7/O7-1,"") | Z7: =IFERROR(E7/O7-1,"") | AA7: =IFERROR(E7/U7-1,"") | AB7: =IFERROR(W7/X7-1,"")
A8: 202306 | B8: 2402 | C8: 0.12592683 | D8: 0.15924729 | E8: 0.14167982 | F8: 0.0074937552 | G8: 0.024979184 | H8: 0.042464613 | I8: 0.051623647 | J8: 0.061615321 | K8: 0.070358035 | L8: 0.081182348 | M8: 0.09367194 | N8: 0.10366361 | O8: 0.11157369 | P8: 0.14563116 | Q8: 6.7090957 | R8: 12 | S8: 0.11157369 | T8: 1 | U8: 0.11157369 | V8: 1063 | W8: 0.14275886 | X8: 0.12135466 | Y8: =IFERROR(D8/O8-1,"") | Z8: =IFERROR(E8/O8-1,"") | AA8: =IFERROR(E8/U8-1,"") | AB8: =IFERROR(W8/X8-1,"")
A9: 202307 | B9: 1743 | C9: 0.12681495 | D9: 0.12947875 | E9: 0.14068957 | F9: 0.0040160643 | G9: 0.023522662 | H9: 0.043602983 | I9: 0.057372347 | J9: 0.067125645 | K9: 0.080321285 | L9: 0.094664372 | M9: 0.10900746 | N9: 0.12105565 | O9: 0.1319564 | P9: 0.11544766 | Q9: 6.0196325 | R9: 12 | S9: 0.1319564 | T9: 1 | U9: 0.1319564 | V9: 758 | W9: 0.14217338 | X9: 0.14379947 | Y9: =IFERROR(D9/O9-1,"") | Z9: =IFERROR(E9/O9-1,"") | AA9: =IFERROR(E9/U9-1,"") | AB9: =IFERROR(W9/X9-1,"")
A10: 202308 | B10: 1530 | C10: 0.13054751 | D10: 0.13331182 | E10: 0.14504188 | F10: 0.0058823529 | G10: 0.026797386 | H10: 0.049019608 | I10: 0.064052288 | J10: 0.079738562 | K10: 0.093464052 | L10: 0.1130719 | M10: 0.12810458 | N10: 0.14052288 | O10: 0.14901961 | P10: 0.10524205 | Q10: 5.7865118 | R10: 12 | S10: 0.14901961 | T10: 1 | U10: 0.14901961 | V10: 678 | W10: 0.1431457 | X10: 0.15929204 | Y10: =IFERROR(D10/O10-1,"") | Z10: =IFERROR(E10/O10-1,"") | AA10: =IFERROR(E10/U10-1,"") | AB10: =IFERROR(W10/X10-1,"")
A11: 202309 | B11: 1515 | C11: 0.12863744 | D11: 0.12332434 | E11: 0.13921361 | F11: 0.003960396 | G11: 0.017161716 | H11: 0.035643564 | I11: 0.052145215 | J11: 0.071287129 | K11: 0.091089109 | L11: 0.10429043 | M11: 0.11023102 | N11: 0.11881188 | O11: 0.12871287 | P11: 0.082642878 | Q11: 5.2702928 | R11: 12 | S11: 0.12871287 | T11: 1 | U11: 0.12871287 | V11: 658 | W11: 0.14253477 | X11: 0.13677812 | Y11: =IFERROR(D11/O11-1,"") | Z11: =IFERROR(E11/O11-1,"") | AA11: =IFERROR(E11/U11-1,"") | AB11: =IFERROR(W11/X11-1,"")
A12: 202310 | B12: 1510 | C12: 0.12509405 | D12: 0.12679589 | E12: 0.12891801 | F12: 0.0026490066 | G12: 0.018543046 | H12: 0.037086093 | I12: 0.054304636 | J12: 0.073509934 | K12: 0.089403974 | L12: 0.099337748 | M12: 0.10794702 | N12: 0.11854305 | O12: 0.12582781 | P12: 0.049681202 | Q12: 4.5173693 | R12: 12 | S12: 0.12582781 | T12: 1 | U12: 0.12582781 | V12: 645 | W12: 0.12812128 | X12: 0.13643411 | Y12: =IFERROR(D12/O12-1,"") | Z12: =IFERROR(E12/O12-1,"") | AA12: =IFERROR(E12/U12-1,"") | AB12: =IFERROR(W12/X12-1,"")
A13: 202311 | B13: 1612 | C13: 0.12550362 | D13: 0.12772981 | E13: 0.12367307 | F13: 0.003101737 | G13: 0.021091811 | H13: 0.042183623 | I13: 0.060794045 | J13: 0.07382134 | K13: 0.084987593 | L13: 0.089950372 | M13: 0.10111663 | N13: 0.1073201 | O13: 0.11662531 | P13: 0.017692212 | Q13: 3.7866642 | R13: 12 | S13: 0.11662531 | T13: 1 | U13: 0.11662531 | V13: 677 | W13: 0.12291228 | X13: 0.12703102 | Y13: =IFERROR(D13/O13-1,"") | Z13: =IFERROR(E13/O13-1,"") | AA13: =IFERROR(E13/U13-1,"") | AB13: =IFERROR(W13/X13-1,"")
A14: 202312 | B14: 1644 | C14: 0.13395168 | D14: 0.13631598 | E14: 0.12957637 | F14: 0.0091240876 | G14: 0.032846715 | H14: 0.052311436 | I14: 0.072384428 | J14: 0.082725061 | K14: 0.096107056 | L14: 0.10523114 | M14: 0.1149635 | N14: 0.12652068 | O14: 0.13807786 | P14: 0.0012463847 | Q14: 3.4110022 | R14: 12 | S14: 0.13807786 | T14: 1 | U14: 0.13807786 | V14: 693 | W14: 0.1272359 | X14: 0.13275613 | Y14: =IFERROR(D14/O14-1,"") | Z14: =IFERROR(E14/O14-1,"") | AA14: =IFERROR(E14/U14-1,"") | AB14: =IFERROR(W14/X14-1,"")
A15: 202401 | B15: 1417 | C15: 0.14060944 | D15: 0.13497839 | E15: 0.13252037 | F15: 0.010585745 | G15: 0.03246295 | H15: 0.057868737 | I15: 0.071277347 | J15: 0.086097389 | K15: 0.098800282 | L15: 0.11009174 | M15: 0.1213832 | N15: 0.13902611 | O15: 0.14537756 | P15: -0.019064283 | Q15: 2.947058 | R15: 12 | S15: 0.14537756 | T15: 1 | U15: 0.14537756 | V15: 587 | W15: 0.13444784 | X15: 0.1516184 | Y15: =IFERROR(D15/O15-1,"") | Z15: =IFERROR(E15/O15-1,"") | AA15: =IFERROR(E15/U15-1,"") | AB15: =IFERROR(W15/X15-1,"")
A16: 202402 | B16: 1753 | C16: 0.13405333 | D16: 0.12850606 | E16: 0.12610444 | F16: 0.014831717 | G16: 0.038220194 | H16: 0.064460924 | I16: 0.077581289 | J16: 0.091842556 | K16: 0.10667427 | L16: 0.11637193 | M16: 0.12435824 | N16: 0.13690816 | O16: 0.14546492 | P16: -0.019828668 | Q16: 2.9295976 | R16: 12 | S16: 0.14546492 | T16: 1 | U16: 0.14546492 | V16: 746 | W16: 0.12612634 | X16: 0.15281501 | Y16: =IFERROR(D16/O16-1,"") | Z16: =IFERROR(E16/O16-1,"") | AA16: =IFERROR(E16/U16-1,"") | AB16: =IFERROR(W16/X16-1,"")
... A32: 202506 | B32: 5317 | C32: 0.14731021 | D32: 0.14141759 | E32: 0.12880317 | F32: 0.0069588114 | G32: 0.031972917 | H32: 0.060184314 | I32: 0.073349633 | J32: 0.086891104 | K32: 0.095354523 | L32: 0.10663908 | M32: 0.1190521 | N32: 0.13090088 | O32: 0.13917623 | P32: -0.073765695 | Q32: 1.697547 | R32: 12 | S32: 0.13917623 | T32: 1 | U32: 0.13917623 | V32: 2461 | W32: 0.12931689 | X32: 0.14221861 | Y32: =IFERROR(D32/O32-1,"") | Z32: =IFERROR(E32/O32-1,"") | AA32: =IFERROR(E32/U32-1,"") | AB32: =IFERROR(W32/X32-1,"")
A33: 202507 | B33: 4979 | C33: 0.15067859 | D33: 0.14467814 | E33: 0.13243061 | F33: 0.0084354288 | G33: 0.036553525 | H33: 0.060052219 | I33: 0.069491866 | J33: 0.078730669 | K33: 0.092789717 | L33: 0.10383611 | M33: 0.11528419 | N33: 0.124523 | P33: -0.073640896 | Q33: 1.7003977 | R33: 11 | S33: 0.124523 | T33: 1.0698712 | U33: 0.13322357 | V33: 2259 | W33: 0.13634442 | Y33: =IFERROR(D33/O33-1,"") | Z33: =IFERROR(E33/O33-1,"") | AA33: =IFERROR(E33/U33-1,"") | AB33: =IFERROR(W33/X33-1,"")
A34: 202508 | B34: 4492 | C34: 0.14972693 | D34: 0.14370412 | E34: 0.12953877 | F34: 0.0077916296 | G34: 0.03317008 | H34: 0.056322351 | I34: 0.067230632 | J34: 0.081700801 | K34: 0.094612645 | L34: 0.10730187 | M34: 0.11887801 | P34: -0.10033144 | Q34: 1.0907218 | R34: 10 | S34: 0.11887801 | T34: 1.1663913 | U34: 0.13865828 | V34: 2116 | W34: 0.13298869 | Y34: =IFERROR(D34/O34-1,"") | Z34: =IFERROR(E34/O34-1,"") | AA34: =IFERROR(E34/U34-1,"") | AB34: =IFERROR(W34/X34-1,"")
A35: 202509 | B35: 3925 | C35: 0.14783218 | D35: 0.14195609 | E35: 0.12784084 | F35: 0.0094267516 | G35: 0.033121019 | H35: 0.055031847 | I35: 0.073375796 | J35: 0.087898089 | K35: 0.098343949 | L35: 0.10751592 | P35: -0.094338164 | Q35: 1.2276226 | R35: 9 | S35: 0.10751592 | T35: 1.2838671 | U35: 0.13803615 | V35: 1790 | W35: 0.13000443 | Y35: =IFERROR(D35/O35-1,"") | Z35: =IFERROR(E35/O35-1,"") | AA35: =IFERROR(E35/U35-1,"") | AB35: =IFERROR(W35/X35-1,"")
A36: 202510 | B36: 3718 | C36: 0.14561703 | D36: 0.13979506 | E36: 0.12531501 | F36: 0.005648198 | G36: 0.025551372 | H36: 0.056750941 | I36: 0.070199032 | J36: 0.080957504 | K36: 0.094405594 | P36: -0.097186463 | Q36: 1.1625606 | R36: 8 | S36: 0.094405594 | T36: 1.4307103 | U36: 0.13506706 | V36: 1739 | W36: 0.12722556 | Y36: =IFERROR(D36/O36-1,"") | Z36: =IFERROR(E36/O36-1,"") | AA36: =IFERROR(E36/U36-1,"") | AB36: =IFERROR(W36/X36-1,"")
A37: 202511 | B37: 4173 | C37: 0.14647131 | D37: 0.14058444 | E37: 0.12627696 | F37: 0.0055116223 | G37: 0.032350827 | H37: 0.052959502 | I37: 0.06374311 | J37: 0.074766355 | P37: -0.095195045 | Q37: 1.2080494 | R37: 7 | S37: 0.074766355 | T37: 1.6520213 | U37: 0.12351561 | V37: 1960 | W37: 0.1274216 | Y37: =IFERROR(D37/O37-1,"") | Z37: =IFERROR(E37/O37-1,"") | AA37: =IFERROR(E37/U37-1,"") | AB37: =IFERROR(W37/X37-1,"")
A38: 202512 | B38: 4821 | C38: 0.15251507 | D38: 0.14646574 | E38: 0.13237399 | F38: 0.008089608 | G38: 0.030906451 | H38: 0.053515868 | I38: 0.065339141 | P38: -0.090738963 | Q38: 1.3098369 | R38: 6 | S38: 0.065339141 | T38: 1.9833021 | U38: 0.12958726 | V38: 2157 | W38: 0.1358952 | Y38: =IFERROR(D38/O38-1,"") | Z38: =IFERROR(E38/O38-1,"") | AA38: =IFERROR(E38/U38-1,"") | AB38: =IFERROR(W38/X38-1,"")
A39: 202601 | B39: 3705 | C39: 0.14775431 | D39: 0.14188563 | E39: 0.1273734 | F39: 0.0059379217 | G39: 0.02537112 | H39: 0.049662618 | P39: -0.082751237 | Q39: 1.4922957 | R39: 5 | S39: 0.049662618 | T39: 2.6231166 | U39: 0.13027084 | V39: 1791 | W39: 0.12968305 | Y39: =IFERROR(D39/O39-1,"") | Z39: =IFERROR(E39/O39-1,"") | AA39: =IFERROR(E39/U39-1,"") | AB39: =IFERROR(W39/X39-1,"")
A40: 202602 | B40: 3402 | C40: 0.15245941 | D40: 0.14638571 | E40: 0.14143163 | F40: 0.0082304527 | G40: 0.031452087 | P40: -0.037038893 | Q40: 2.5364749 | R40: 4 | S40: 0.031452087 | T40: 4.7599251 | U40: 0.14970958 | V40: 1536 | W40: 0.14792427 | Y40: =IFERROR(D40/O40-1,"") | Z40: =IFERROR(E40/O40-1,"") | AA40: =IFERROR(E40/U40-1,"") | AB40: =IFERROR(W40/X40-1,"")
A41: 202603 | B41: 4336 | C41: 0.15495517 | D41: 0.14893068 | E41: 0.1550351 | F41: 0.0069188192 | P41: 0.014389803 | Q41: 3.7112293 | R41: 3 | S41: 0.0069188192 | T41: 19.582435 | U41: 0.13548732 | V41: 2021 | W41: 0.15952814 | Y41: =IFERROR(D41/O41-1,"") | Z41: =IFERROR(E41/O41-1,"") | AA41: =IFERROR(E41/U41-1,"") | AB41: =IFERROR(W41/X41-1,"")
A42: 202604 | B42: 3591 | C42: 0.14629227 | D42: 0.13846089 | E42: 0.14715908 | P42: 0.024185191 | Q42: 3.9349794 | V42: 1748 | W42: 0.14836602 | Y42: =IFERROR(D42/O42-1,"") | Z42: =IFERROR(E42/O42-1,"") | AA42: =IFERROR(E42/U42-1,"") | AB42: =IFERROR(W42/X42-1,"")
A43: 202605 | B43: 4190 | C43: 0.14492496 | D43: 0.13739762 | E43: 0.14503892 | P43: 0.019247124 | Q43: 3.8221822 | V43: 1975 | W43: 0.14530801 | Y43: =IFERROR(D43/O43-1,"") | Z43: =IFERROR(E43/O43-1,"") | AA43: =IFERROR(E43/U43-1,"") | AB43: =IFERROR(W43/X43-1,"")
